Workbook
Name analysis_period: Inputs!$C$36
Name annual_fuel_usage: Inputs!$C$23
Name AnnualLandLease: Inputs!$D$213
Name AnnualOMCapacity: Inputs!$D$166
Name AnnualOMFixed: Inputs!$D$165
Name AnnualOMProduction: Inputs!$D$167
Name AnnualPBIFederal: Inputs!$D$172
Name AnnualPBIOther: Inputs!$D$175
Name AnnualPBIState: Inputs!$D$173
Name AnnualPBIUtility: Inputs!$D$174
Name AnnualPTCFederal: Inputs!$D$184
Name AnnualPTCState: Inputs!$D$185
Name AnnualTaxFederal: Inputs!$C$170
Name AnnualTaxState: Inputs!$C$169
Name batt_annual_discharge_energy: Inputs!$C$153
Name cbi_fed_amount: Inputs!$C$125
Name cbi_fed_deprbas_fed: Inputs!$G$125
Name cbi_fed_deprbas_sta: Inputs!$H$125
Name cbi_fed_maxvalue: Inputs!$D$125
Name cbi_fed_tax_fed: Inputs!$E$125
Name cbi_fed_tax_sta: Inputs!$F$125
Name cbi_oth_amount: Inputs!$C$128
Name cbi_oth_deprbas_fed: Inputs!$G$128
Name cbi_oth_deprbas_sta: Inputs!$H$128
Name cbi_oth_maxvalue: Inputs!$D$128
Name cbi_oth_tax_fed: Inputs!$E$128
Name cbi_oth_tax_sta: Inputs!$F$128
Name cbi_sta_amount: Inputs!$C$126
Name cbi_sta_deprbas_fed: Inputs!$G$126
Name cbi_sta_deprbas_sta: Inputs!$H$126
Name cbi_sta_maxvalue: Inputs!$D$126
Name cbi_sta_tax_fed: Inputs!$E$126
Name cbi_sta_tax_sta: Inputs!$F$126
Name cbi_uti_amount: Inputs!$C$127
Name cbi_uti_deprbas_fed: Inputs!$G$127
Name cbi_uti_deprbas_sta: Inputs!$H$127
Name cbi_uti_maxvalue: Inputs!$D$127
Name cbi_uti_tax_fed: Inputs!$E$127
Name cbi_uti_tax_sta: Inputs!$F$127
Name cf_annual_cost_lcos: Inputs!$C$210
Name cf_annual_discharge_lcos: Inputs!$C$211
Name cf_battery_replacement_cost: Inputs!$C$190
Name cf_capacity_payment: Inputs!$C$158
Name cf_curtailment_value: Inputs!$C$159
Name cf_disbursement_debtservice: Inputs!$C$205
Name cf_energy_net: Inputs!$C$151
Name cf_energy_purchases: Inputs!$C$150
Name cf_energy_sales: Inputs!$C$149
Name cf_energy_value: Inputs!$C$157
Name cf_energy_without_battery: Inputs!$C$152
Name cf_fuelcell_replacement_cost: Inputs!$C$195
Name cf_funding_debtservice: Inputs!$C$204
Name cf_om_capacity1_expense: Inputs!$C$188
Name cf_om_capacity2_expense: Inputs!$C$193
Name cf_om_fixed1_expense: Inputs!$C$187
Name cf_om_fixed2_expense: Inputs!$C$192
Name cf_om_fuel_expense: Inputs!$C$198
Name cf_om_opt_fuel_1_expense: Inputs!$C$199
Name cf_om_opt_fuel_2_expense: Inputs!$C$200
Name cf_om_production1_expense: Inputs!$C$189

Sheet Inputs
B1: Third Party Ownership - Host/Developer Inputs
B2: SYSTEM DESIGN | E2: KEY
B3: Nameplate capacity (kW) | C3: 0 | E3: Calculated
E4: Input from SAM
B5: SYSTEM COSTS | E5: Annual value from SAM
B6: Total installed cost ($) | C6: 0 | E6: Value depends on option in SAM
B8: OPERATION AND MAINTENANCE COSTS | E8: METRICS
B9: Fixed annual cost ($/yr) | C9: 0 | E9: PPA price, year 1 (¢/kWh) | F9: ='Cash Flow'!C28 -> 0
B10: Escalation (% above inflation) | C10: 0 | E10: PPA price escalation (%/yr) | F10: =ppa_escalation -> 0
B11: Fixed cost by capacity ($/kW-yr) | C11: 0 | E11: Levelized PPA price nominal (¢/kWh) | F11: ='Cash Flow'!B164 -> 0
B12: Escalation (% above inflation) | C12: 0 | E12: LCOE, nominal (¢/kWh) | F12: ='Cash Flow'!B160 -> 0
B13: Variable cost by generation ($/MWh) | C13: 0 | E13: Developer NPV ($) | F13: ='Cash Flow'!B151 -> 0
B14: Escalation (% above inflation) | C14: 0 | E14: Host NPV ($) | F14: ='Cash Flow'!B21 + NPV(host_nominal_discount_rate/100,'Cash Flow'!C21:AP21) -> 0
E15: Host indifference point, year 1 (¢/kWh) | F15: ='Cash Flow'!C16 -> 0
B16: LAND LEASE | E16: Levelized indifference point (nominal) (¢/kWh) | F16: =IF('Cash Flow'!B159<>0,NPV(host_nominal_discount_rate/100,'Cash Flow'!C15:AP15)*100/NPV(host_nominal_discount_rate/100,'Cash Flow'!C156:AP156),0) -> 0
B17: Land area estimate (acres) | C17: 0
B18: Annual land lease cost ($/acre) | C18: 0
B19: Land lease escalation rate (% above inflation) | C19: 0
B21: FUEL COSTS (CSP, GENERIC, AND BIOPOWER SYSTEMS ONLY)
B22: Fuel (CSP and generic system only)
B23: Annual usage (kWh) | C23: 0
B24: Heat rate (MMBtu/MWh) | C24: 0
B25: Cost ($/MMBtu) | C25: 0
B26: Escalation (%/year above inflation) | C26: 0
B28: FINANCIAL PARAMETERS
B29: Solution Mode
B30: IRR Target | C30: Calculated
B31: Target year | C31: Calculated
B32: PPA price ($/kWh) | C32: 0
B33: PPA price escalation (%/year) | C33: 0
B34: PPA price is modified by TOD multipliers | C34: No
B35: Analysis Parameters
B36: Analysis period (years, 40 max) | C36: 0
B37: Inflation rate (%/year) | C37: 0
B38: Host real discount rate (%/year) | C38: 0
B39: Host nominal discount rate (%/year) | C39: =((inflation_rate/100+1)*(host_real_discount_rate/100+1)-1)*100 -> 0
B40: Project (developer) real discount rate (%/year) | C40: 0
B41: Project (developer) nominal discount rate (%/year) | C41: =((inflation_rate/100+1)*(real_discount_rate/100+1)-1)*100 -> 0
B42: Tax and Insurance Rates
B43: Federal income tax rate in Year 1 (%/year) | C43: =AnnualTaxFederal -> 0
B44: State income tax rate in Year 1 (%/year) | C44: =AnnualTaxState -> 0
B45: Sales tax (% of total direct cost) | C45: 0
B46: Insurance rate (annual, % of installed cost) | C46: 0
B47: Property Tax
B48: Assessed percentage (% of total installed cost) | C48: 0
B49: Assesed value ($) | C49: =total_installed_cost*prop_tax_cost_assessed_percent/100 -> 0
B50: Annual decline (%/year) | C50: 0
B51: Property tax rate (%/year) | C51: 0
B52: Salvage Value
B53: Net salvage value (% of total installed cost) | C53: 0
B54: End of analysis period value ($) | C54: =total_installed_cost*salvage_percentage/100 -> 0
B56: PROJECT TERM DEBT
B57: Debt sizing and payment schedule
B58: Debt percent (%) ("Calculated" for sculpted payments) | C58: Calculated
B59: Size of debt ($) ("N/A" for sculpted payments) | C59: N/A
B60: Debt service coverage ratio ("Calculated" for mortgage style) | C60: 0
B61: Limit debt fraction (for sculpted payments only) | C61: No
B62: Maximum debt percent (%) (for sculpted payments only) | C62: 100
B63: Annual payment schedule (for mortgage style debt only) | C63: Equal payments
B64: Debt Parameters
B65: Tenor (years) | C65: 0
B66: Moratorium (years) | C66: 0
B67: Annual all-in interest rate (%) | C67: 0
B68: Debt closing costs ($) | C68: 0
B69: Up-front fee (% of total debt) | C69: 0
B70: Up-front fee amount ($, from SAM results) | C70: 0
B72: COST OF ACQUIRING FINANCING
B73: Other financing cost ($) | C73: 0
B75: CONSTRUCTION FINANCING
B76: Total construction financing cost ($) | C76: 0
B78: CONSTRUCTION FINANCING CALCULATION (provided here for reference, only total financing cost above is input to cash flow)
C79: Percent of installed cost | D79: Up-front fee (% of principal) | E79: Months prior to operation | F79: Annual interest rate (%) | G79: Principal | H79: Interest | I79: Total construction financing cost
B80: Loan 1 | C80: 0 | D80: 0 | E80: 0 | F80: 0 | G80: =C80/100*total_installed_cost -> 0 | H80: =G80*F80/100*E80/12*0.5 -> 0 | I80: =H80+D80/100*G80 -> 0
B81: Loan 2 | C81: 0 | D81: 0 | E81: 0 | F81: 0 | G81: =C81/100*total_installed_cost -> 0 | H81: =G81*F81/100*E81/12*0.5 -> 0 | I81: =H81+D81/100*G81 -> 0
B82: Loan 3 | C82: 0 | D82: 0 | E82: 0 | F82: 0 | G82: =C82/100*total_installed_cost -> 0 | H82: =G82*F82/100*E82/12*0.5 -> 0 | I82: =H82+D82/100*G82 -> 0
B83: Loan 4 | C83: 0 | D83: 0 | E83: 0 | F83: 0 | G83: =C83/100*total_installed_cost -> 0 | H83: =G83*F83/100*E83/12*0.5 -> 0 | I83: =H83+D83/100*G83 -> 0
B84: Loan 5 | C84: 0 | D84: 0 | E84: 0 | F84: 0 | G84: =C84/100*total_installed_cost -> 0 | H84: =G84*F84/100*E84/12*0.5 -> 0 | I84: =H84+D84/100*G84 -> 0
B85: Totals: | G85: =SUM(G80:G84) -> 0 | H85: =SUM(H80:H84) -> 0 | I85: =SUM(I80:I84) -> 0
B87: RESERVE ACCOUNTS
B88: Interest on reserves (%/year) | C88: 0
B89: Working capital reserve (months of operating costs) | C89: 0
B90: Debt service reserve account (months of P&I payments) | C90: 0
B91: Receivables reserve | C91: 0
B92: Major equipment replacement reserve accounts | C92: Replacement cost ($/W) | D92: Year 1 dollars | E92: Replacement frequency (years)
B93: Replacement reserve 1 | C93: 0 | D93: =C93*system_capacity*1000 -> 0 | E93: 0
B94: Replacement reserve 2 | C94: 0 | D94: =C94*system_capacity*1000 -> 0 | E94: 0
B95: Replacement reserve 3 | C95: 0 | D95: =C95*system_capacity*1000 -> 0 | E95: 0
B96: Depreciation treatment for replacement reserves
B97: Federal | C97: 5-yr MACRS
B98: State | C98: 5-yr MACRS
B100: TAX CREDITS
B101: Investment Tax Credit | E101: Reduces depreciation basis
B102: As fixed amount | C102: Amount ($) | E102: Federal | F102: State
B103: Federal ($) | C103: =SUM(D177:AQ177) -> 0 | E103: No | F103: No
B104: State ($) | C104: =SUM(D178:AQ178) -> 0 | E104: No | F104: No
B105: As percentage | C105: % | D105: Maximum ($)
B106: Federal (% of total installed cost) | C106: =SUM(D179:AQ179) -> 0 | D106: =SUM(D180:AQ180) -> 0 | E106: No | F106: No
B107: State (% of total installed cost) | C107: =SUM(D181:AQ181) -> 0 | D107: =SUM(D182:AQ182) -> 0 | E107: No | F107: No
B108: Production Tax Credit | C108: Amount ($/kWh) | D108: Term (years) | E108: Escalation (%/year)
B109: Federal | C109: 0 | D109: 0 | E109: 0
...

Sheet Cash Flow
A1: Third Party Ownership - Host/Developer Cash Flow
A2: Operating Year | B2: 0 | C2: =IF(B2<analysis_period,B2+1,"") | D2: =IF(C2<analysis_period,C2+1,"") | E2: =IF(D2<analysis_period,D2+1,"") | F2: =IF(E2<analysis_period,E2+1,"") | G2: =IF(F2<analysis_period,F2+1,"") | H2: =IF(G2<analysis_period,G2+1,"") | I2: =IF(H2<analysis_period,H2+1,"") | J2: =IF(I2<analysis_period,I2+1,"") | ... AP2: =IF(AO2<analysis_period,AO2+1,"")
A4: Energy
A5: Electricity to grid (AC kWh) | B5: {=Inputs!C149:AQ150} -> 0 | C5: 0 | D5: 0 | E5: 0 | F5: 0 | G5: 0 | H5: 0 | I5: 0 | J5: 0 | K5: 0 | L5: 0 | M5: 0 | N5: 0 | O5: 0 | P5: 0 | Q5: 0 | R5: 0 | S5: 0 | T5: 0 | U5: 0 | V5: 0 | W5: 0 | X5: 0 | Y5: 0 | Z5: 0 | AA5: 0 | AB5: 0 | AC5: 0 | AD5: 0 | AE5: 0 | AF5: 0 | AG5: 0 | AH5: 0 | AI5: 0 | AJ5: 0 | AK5: 0 | AL5: 0 | AM5: 0 | AN5: 0 | AO5: 0 | AP5: 0
A6: Electricity from grid (AC kWh) | B6: 0 | C6: 0 | D6: 0 | E6: 0 | F6: 0 | G6: 0 | H6: 0 | I6: 0 | J6: 0 | K6: 0 | L6: 0 | M6: 0 | N6: 0 | O6: 0 | P6: 0 | Q6: 0 | R6: 0 | S6: 0 | T6: 0 | U6: 0 | V6: 0 | W6: 0 | X6: 0 | Y6: 0 | Z6: 0 | AA6: 0 | AB6: 0 | AC6: 0 | AD6: 0 | AE6: 0 | AF6: 0 | AG6: 0 | AH6: 0 | AI6: 0 | AJ6: 0 | AK6: 0 | AL6: 0 | AM6: 0 | AN6: 0 | AO6: 0 | AP6: 0
A7: Electricity to grid net (AC kWh) | B7: =SUM(B5:B6) -> 0 | C7: =SUM(C5:C6) -> 0 | D7: =SUM(D5:D6) -> 0 | E7: =SUM(E5:E6) -> 0 | F7: =SUM(F5:F6) -> 0 | G7: =SUM(G5:G6) -> 0 | H7: =SUM(H5:H6) -> 0 | I7: =SUM(I5:I6) -> 0 | ... AP7: =SUM(AP5:AP6) -> 0
A8: Electricity generated without storage (AC kWh) | B8: {=Inputs!C152:AQ154} -> 0 | C8: 0 | D8: 0 | E8: 0 | F8: 0 | G8: 0 | H8: 0 | I8: 0 | J8: 0 | K8: 0 | L8: 0 | M8: 0 | N8: 0 | O8: 0 | P8: 0 | Q8: 0 | R8: 0 | S8: 0 | T8: 0 | U8: 0 | V8: 0 | W8: 0 | X8: 0 | Y8: 0 | Z8: 0 | AA8: 0 | AB8: 0 | AC8: 0 | AD8: 0 | AE8: 0 | AF8: 0 | AG8: 0 | AH8: 0 | AI8: 0 | AJ8: 0 | AK8: 0 | AL8: 0 | AM8: 0 | AN8: 0 | AO8: 0 | AP8: 0
A9: Battery annual energy discharged (AC kWh) | B9: 0 | C9: 0 | D9: 0 | E9: 0 | F9: 0 | G9: 0 | H9: 0 | I9: 0 | J9: 0 | K9: 0 | L9: 0 | M9: 0 | N9: 0 | O9: 0 | P9: 0 | Q9: 0 | R9: 0 | S9: 0 | T9: 0 | U9: 0 | V9: 0 | W9: 0 | X9: 0 | Y9: 0 | Z9: 0 | AA9: 0 | AB9: 0 | AC9: 0 | AD9: 0 | AE9: 0 | AF9: 0 | AG9: 0 | AH9: 0 | AI9: 0 | AJ9: 0 | AK9: 0 | AL9: 0 | AM9: 0 | AN9: 0 | AO9: 0 | AP9: 0
A10: Fuel cell annual energy discharged (AC kWh) | B10: 0 | C10: 0 | D10: 0 | E10: 0 | F10: 0 | G10: 0 | H10: 0 | I10: 0 | J10: 0 | K10: 0 | L10: 0 | M10: 0 | N10: 0 | O10: 0 | P10: 0 | Q10: 0 | R10: 0 | S10: 0 | T10: 0 | U10: 0 | V10: 0 | W10: 0 | X10: 0 | Y10: 0 | Z10: 0 | AA10: 0 | AB10: 0 | AC10: 0 | AD10: 0 | AE10: 0 | AF10: 0 | AG10: 0 | AH10: 0 | AI10: 0 | AJ10: 0 | AK10: 0 | AL10: 0 | AM10: 0 | AN10: 0 | AO10: 0 | AP10: 0
A12: Host Costs and Savings
A13: Electricity bill without system | B13: {=Inputs!C163:AQ163} -> 0 | C13: 0 | D13: 0 | E13: 0 | F13: 0 | G13: 0 | H13: 0 | I13: 0 | J13: 0 | K13: 0 | L13: 0 | M13: 0 | N13: 0 | O13: 0 | P13: 0 | Q13: 0 | R13: 0 | S13: 0 | T13: 0 | U13: 0 | V13: 0 | W13: 0 | X13: 0 | Y13: 0 | Z13: 0 | AA13: 0 | AB13: 0 | AC13: 0 | AD13: 0 | AE13: 0 | AF13: 0 | AG13: 0 | AH13: 0 | AI13: 0 | AJ13: 0 | AK13: 0 | AL13: 0 | AM13: 0 | AN13: 0 | AO13: 0 | AP13: 0
A14: Electricity bill with system | B14: {=Inputs!C162:AQ162} -> 0 | C14: 0 | D14: 0 | E14: 0 | F14: 0 | G14: 0 | H14: 0 | I14: 0 | J14: 0 | K14: 0 | L14: 0 | M14: 0 | N14: 0 | O14: 0 | P14: 0 | Q14: 0 | R14: 0 | S14: 0 | T14: 0 | U14: 0 | V14: 0 | W14: 0 | X14: 0 | Y14: 0 | Z14: 0 | AA14: 0 | AB14: 0 | AC14: 0 | AD14: 0 | AE14: 0 | AF14: 0 | AG14: 0 | AH14: 0 | AI14: 0 | AJ14: 0 | AK14: 0 | AL14: 0 | AM14: 0 | AN14: 0 | AO14: 0 | AP14: 0
A15: Savings | B15: =B13-B14 -> 0 | C15: =C13-C14 -> 0 | D15: =D13-D14 -> 0 | E15: =E13-E14 -> 0 | F15: =F13-F14 -> 0 | G15: =G13-G14 -> 0 | H15: =H13-H14 -> 0 | I15: =I13-I14 -> 0 | ... AP15: =AP13-AP14 -> 0
A16: Indifference point (¢/kWh) | B16: =IF(B$5=0,0,B$15*100/B$5) -> 0 | C16: =IF(C$5=0,0,C$15*100/C$5) -> 0 | D16: =IF(D$5=0,0,D$15*100/D$5) -> 0 | E16: =IF(E$5=0,0,E$15*100/E$5) -> 0 | F16: =IF(F$5=0,0,F$15*100/F$5) -> 0 | G16: =IF(G$5=0,0,G$15*100/G$5) -> 0 | H16: =IF(H$5=0,0,H$15*100/H$5) -> 0 | I16: =IF(I$5=0,0,I$15*100/I$5) -> 0 | ... AP16: =IF(AP$5=0,0,AP$15*100/AP$5) -> 0
A17: Agreement cost
A18: Electricity to grid net (AC kWh) | B18: =B$5 -> 0 | C18: =C$5 -> 0 | D18: =D$5 -> 0 | E18: =E$5 -> 0 | F18: =F$5 -> 0 | G18: =G$5 -> 0 | H18: =H$5 -> 0 | I18: =I$5 -> 0 | ... AP18: =AP$5 -> 0
A19: PPA price (¢/kWh) | B19: {=Inputs!C156:AQ156} -> 0 | C19: 0 | D19: 0 | E19: 0 | F19: 0 | G19: 0 | H19: 0 | I19: 0 | J19: 0 | K19: 0 | L19: 0 | M19: 0 | N19: 0 | O19: 0 | P19: 0 | Q19: 0 | R19: 0 | S19: 0 | T19: 0 | U19: 0 | V19: 0 | W19: 0 | X19: 0 | Y19: 0 | Z19: 0 | AA19: 0 | AB19: 0 | AC19: 0 | AD19: 0 | AE19: 0 | AF19: 0 | AG19: 0 | AH19: 0 | AI19: 0 | AJ19: 0 | AK19: 0 | AL19: 0 | AM19: 0 | AN19: 0 | AO19: 0 | AP19: 0
A20: Total agreement cost | B20: =B$19*B$18/100 -> 0 | C20: =C$19*C$18/100 -> 0 | D20: =D$19*D$18/100 -> 0 | E20: =E$19*E$18/100 -> 0 | F20: =F$19*F$18/100 -> 0 | G20: =G$19*G$18/100 -> 0 | H20: =H$19*H$18/100 -> 0 | I20: =I$19*I$18/100 -> 0 | ... AP20: =AP$19*AP$18/100 -> 0
A21: After-tax cash flow | B21: =B$15-B$20 -> 0 | C21: =C$15-C$20 -> 0 | D21: =D$15-D$20 -> 0 | E21: =E$15-E$20 -> 0 | F21: =F$15-F$20 -> 0 | G21: =G$15-G$20 -> 0 | H21: =H$15-H$20 -> 0 | I21: =I$15-I$20 -> 0 | ... AP21: =AP$15-AP$20 -> 0
A22: Payback | B22: =B$21 -> 0 | C22: =C$21 -> 0 | D22: =D$21 -> 0 | E22: =E$21 -> 0 | F22: =F$21 -> 0 | G22: =G$21 -> 0 | H22: =H$21 -> 0 | I22: =I$21 -> 0 | ... AP22: =AP$21 -> 0
A23: Cumulative payback | B23: 0 | C23: =B$23+C$22 -> 0 | D23: =C$23+D$22 -> 0 | E23: =D$23+E$22 -> 0 | F23: =E$23+F$22 -> 0 | G23: =F$23+G$22 -> 0 | H23: =G$23+H$22 -> 0 | I23: =H$23+I$22 -> 0 | J23: =I$23+J$22 -> 0 | ... AP23: =AO$23+AP$22 -> 0
A25: Developer Revenues and Costs
A26: PPA revenue
A27: Electricity to grid (AC kWh) | C27: =C$5 -> 0 | D27: =D$5 -> 0 | E27: =E$5 -> 0 | F27: =F$5 -> 0 | G27: =G$5 -> 0 | H27: =H$5 -> 0 | I27: =I$5 -> 0 | J27: =J$5 -> 0 | ... AP27: =AP$5 -> 0
A28: Price (¢/kWh) | B28: {=Inputs!C156:AQ156} -> 0 | C28: 0 | D28: 0 | E28: 0 | F28: 0 | G28: 0 | H28: 0 | I28: 0 | J28: 0 | K28: 0 | L28: 0 | M28: 0 | N28: 0 | O28: 0 | P28: 0 | Q28: 0 | R28: 0 | S28: 0 | T28: 0 | U28: 0 | V28: 0 | W28: 0 | X28: 0 | Y28: 0 | Z28: 0 | AA28: 0 | AB28: 0 | AC28: 0 | AD28: 0 | AE28: 0 | AF28: 0 | AG28: 0 | AH28: 0 | AI28: 0 | AJ28: 0 | AK28: 0 | AL28: 0 | AM28: 0 | AN28: 0 | AO28: 0 | AP28: 0
A29: PPA revenue (TOD price multipliers may apply) | B29: {=Inputs!C157:AQ157} -> 0 | C29: 0 | D29: 0 | E29: 0 | F29: 0 | G29: 0 | H29: 0 | I29: 0 | J29: 0 | K29: 0 | L29: 0 | M29: 0 | N29: 0 | O29: 0 | P29: 0 | Q29: 0 | R29: 0 | S29: 0 | T29: 0 | U29: 0 | V29: 0 | W29: 0 | X29: 0 | Y29: 0 | Z29: 0 | AA29: 0 | AB29: 0 | AC29: 0 | AD29: 0 | AE29: 0 | AF29: 0 | AG29: 0 | AH29: 0 | AI29: 0 | AJ29: 0 | AK29: 0 | AL29: 0 | AM29: 0 | AN29: 0 | AO29: 0 | AP29: 0
A30: Other revenue
A31: Capacity payments | B31: {=Inputs!C158:AQ160} -> 0 | C31: 0 | D31: 0 | E31: 0 | F31: 0 | G31: 0 | H31: 0 | I31: 0 | J31: 0 | K31: 0 | L31: 0 | M31: 0 | N31: 0 | O31: 0 | P31: 0 | Q31: 0 | R31: 0 | S31: 0 | T31: 0 | U31: 0 | V31: 0 | W31: 0 | X31: 0 | Y31: 0 | Z31: 0 | AA31: 0 | AB31: 0 | AC31: 0 | AD31: 0 | AE31: 0 | AF31: 0 | AG31: 0 | AH31: 0 | AI31: 0 | AJ31: 0 | AK31: 0 | AL31: 0 | AM31: 0 | AN31: 0 | AO31: 0 | AP31: 0
A32: Curtailment payments | B32: 0 | C32: 0 | D32: 0 | E32: 0 | F32: 0 | G32: 0 | H32: 0 | I32: 0 | J32: 0 | K32: 0 | L32: 0 | M32: 0 | N32: 0 | O32: 0 | P32: 0 | Q32: 0 | R32: 0 | S32: 0 | T32: 0 | U32: 0 | V32: 0 | W32: 0 | X32: 0 | Y32: 0 | Z32: 0 | AA32: 0 | AB32: 0 | AC32: 0 | AD32: 0 | AE32: 0 | AF32: 0 | AG32: 0 | AH32: 0 | AI32: 0 | AJ32: 0 | AK32: 0 | AL32: 0 | AM32: 0 | AN32: 0 | AO32: 0 | AP32: 0
A33: Thermal revenue (fuel cell only) | B33: 0 | C33: 0 | D33: 0 | E33: 0 | F33: 0 | G33: 0 | H33: 0 | I33: 0 | J33: 0 | K33: 0 | L33: 0 | M33: 0 | N33: 0 | O33: 0 | P33: 0 | Q33: 0 | R33: 0 | S33: 0 | T33: 0 | U33: 0 | V33: 0 | W33: 0 | X33: 0 | Y33: 0 | Z33: 0 | AA33: 0 | AB33: 0 | AC33: 0 | AD33: 0 | AE33: 0 | AF33: 0 | AG33: 0 | AH33: 0 | AI33: 0 | AJ33: 0 | AK33: 0 | AL33: 0 | AM33: 0 | AN33: 0 | AO33: 0 | AP33: 0
A34: Production Based Incentive (included if available for debt service)
A35: Federal | C35: =IF(pbi_fed_for_ds="Yes",C590,0) -> 0 | D35: =IF(pbi_fed_for_ds="Yes",D590,0) -> 0 | E35: =IF(pbi_fed_for_ds="Yes",E590,0) -> 0 | F35: =IF(pbi_fed_for_ds="Yes",F590,0) -> 0 | G35: =IF(pbi_fed_for_ds="Yes",G590,0) -> 0 | H35: =IF(pbi_fed_for_ds="Yes",H590,0) -> 0 | I35: =IF(pbi_fed_for_ds="Yes",I590,0) -> 0 | J35: =IF(pbi_fed_for_ds="Yes",J590,0) -> 0 | ... AP35: =IF(pbi_fed_for_ds="Yes",AP590,0) -> 0
A36: State | C36: =IF(pbi_sta_for_ds="Yes",C594,0) -> 0 | D36: =IF(pbi_sta_for_ds="Yes",D594,0) -> 0 | E36: =IF(pbi_sta_for_ds="Yes",E594,0) -> 0 | F36: =IF(pbi_sta_for_ds="Yes",F594,0) -> 0 | G36: =IF(pbi_sta_for_ds="Yes",G594,0) -> 0 | H36: =IF(pbi_sta_for_ds="Yes",H594,0) -> 0 | I36: =IF(pbi_sta_for_ds="Yes",I594,0) -> 0 | J36: =IF(pbi_sta_for_ds="Yes",J594,0) -> 0 | ... AP36: =IF(pbi_sta_for_ds="Yes",AP594,0) -> 0
A37: Utility | C37: =IF(pbi_uti_for_ds="Yes",C598,0) -> 0 | D37: =IF(pbi_uti_for_ds="Yes",D598,0) -> 0 | E37: =IF(pbi_uti_for_ds="Yes",E598,0) -> 0 | F37: =IF(pbi_uti_for_ds="Yes",F598,0) -> 0 | G37: =IF(pbi_uti_for_ds="Yes",G598,0) -> 0 | H37: =IF(pbi_uti_for_ds="Yes",H598,0) -> 0 | I37: =IF(pbi_uti_for_ds="Yes",I598,0) -> 0 | J37: =IF(pbi_uti_for_ds="Yes",J598,0) -> 0 | ... AP37: =IF(pbi_uti_for_ds="Yes",AP598,0) -> 0
A38: Other | C38: =IF(pbi_oth_for_ds="Yes",C602,0) -> 0 | D38: =IF(pbi_oth_for_ds="Yes",D602,0) -> 0 | E38: =IF(pbi_oth_for_ds="Yes",E602,0) -> 0 | F38: =IF(pbi_oth_for_ds="Yes",F602,0) -> 0 | G38: =IF(pbi_oth_for_ds="Yes",G602,0) -> 0 | H38: =IF(pbi_oth_for_ds="Yes",H602,0) -> 0 | I38: =IF(pbi_oth_for_ds="Yes",I602,0) -> 0 | J38: =IF(pbi_oth_for_ds="Yes",J602,0) -> 0 | ... AP38: =IF(pbi_oth_for_ds="Yes",AP602,0) -> 0
A39: Total PBI | C39: =SUM(C35:C38) -> 0 | D39: =SUM(D35:D38) -> 0 | E39: =SUM(E35:E38) -> 0 | F39: =SUM(F35:F38) -> 0 | G39: =SUM(G35:G38) -> 0 | H39: =SUM(H35:H38) -> 0 | I39: =SUM(I35:I38) -> 0 | J39: =SUM(J35:J38) -> 0 | ... AP39: =SUM(AP35:AP38) -> 0
A40: Salvage Value | C40: =IF(C2=analysis_period,total_installed_cost*salvage_percentage/100,0) -> 0 | D40: =IF(D2=analysis_period,total_installed_cost*salvage_percentage/100,0) -> 0 | E40: =IF(E2=analysis_period,total_installed_cost*salvage_percentage/100,0) -> 0 | F40: =IF(F2=analysis_period,total_installed_cost*salvage_percentage/100,0) -> 0 | G40: =IF(G2=analysis_period,total_installed_cost*salvage_percentage/100,0) -> 0 | H40: =IF(H2=analysis_period,total_installed_cost*salvage_percentage/100,0) -> 0 | I40: =IF(I2=analysis_period,total_installed_cost*salvage_percentage/100,0) -> 0 | J40: =IF(J2=analysis_period,total_installed_cost*salvage_percentage/100,0) -> 0 | ... AP40: =IF(AP2=analysis_period,total_installed_cost*salvage_percentage/100,0) -> 0
A41: Total Revenue | C41: =IF(C$2<=analysis_period,C$29+SUM(C31:C33)+C$39+C$40,0) -> 0 | D41: =IF(D$2<=analysis_period,D$29+SUM(D31:D33)+D$39+D$40,0) -> 0 | E41: =IF(E$2<=analysis_period,E$29+SUM(E31:E33)+E$39+E$40,0) -> 0 | F41: =IF(F$2<=analysis_period,F$29+SUM(F31:F33)+F$39+F$40,0) -> 0 | G41: =IF(G$2<=analysis_period,G$29+SUM(G31:G33)+G$39+G$40,0) -> 0 | H41: =IF(H$2<=analysis_period,H$29+SUM(H31:H33)+H$39+H$40,0) -> 0 | I41: =IF(I$2<=analysis_period,I$29+SUM(I31:I33)+I$39+I$40,0) -> 0 | J41: =IF(J$2<=analysis_period,J$29+SUM(J31:J33)+J$39+J$40,0) -> 0 | ... AP41: =IF(AP$2<=analysis_period,AP$29+SUM(AP31:AP33)+AP$39+AP$40,0) -> 0
A43: Property tax net assessed value | C43: =PropertyTaxAssessedValue -> 0 | D43: =IF(D$2<=analysis_period,PropertyTaxAssessedValue*(100-(D$2-1)*prop_tax_assessed_decline)/100,0) -> 0 | E43: =IF(E$2<=analysis_period,PropertyTaxAssessedValue*(100-(E$2-1)*prop_tax_assessed_decline)/100,0) -> 0 | F43: =IF(F$2<=analysis_period,PropertyTaxAssessedValue*(100-(F$2-1)*prop_tax_assessed_decline)/100,0) -> 0 | G43: =IF(G$2<=analysis_period,PropertyTaxAssessedValue*(100-(G$2-1)*prop_tax_assessed_decline)/100,0) -> 0 | H43: =IF(H$2<=analysis_period,PropertyTaxAssessedValue*(100-(H$2-1)*prop_tax_assessed_decline)/100,0) -> 0 | I43: =IF(I$2<=analysis_period,PropertyTaxAssessedValue*(100-(I$2-1)*prop_tax_assessed_decline)/100,0) -> 0 | J43: =IF(J$2<=analysis_period,PropertyTaxAssessedValue*(100-(J$2-1)*prop_tax_assessed_decline)/100,0) -> 0 | K43: =IF(K$2<=analysis_period,PropertyTaxAssessedValue*(100-(K$2-1)*prop_tax_assessed_decline)/100,0) -> 0 | ... AP43: =IF(AP$2<=analysis_period,PropertyTaxAssessedValue*(100-(AP$2-1)*prop_tax_assessed_decline)/100,0) -> 0
A45: Developer Operating Expenses
A46: Operation and maintenance (O&M)
A47: Fixed | C47: =IF(C$2<=analysis_period,IF(om_fixed="n/a",Inputs!D165,om_fixed*(1+inflation_rate/100+om_fixed_escal/100)^B$2),0) -> 0 | D47: =IF(D$2<=analysis_period,IF(om_fixed="n/a",Inputs!E165,om_fixed*(1+inflation_rate/100+om_fixed_escal/100)^C$2),0) -> 0 | E47: =IF(E$2<=analysis_period,IF(om_fixed="n/a",Inputs!F165,om_fixed*(1+inflation_rate/100+om_fixed_escal/100)^D$2),0) -> 0 | F47: =IF(F$2<=analysis_period,IF(om_fixed="n/a",Inputs!G165,om_fixed*(1+inflation_rate/100+om_fixed_escal/100)^E$2),0) -> 0 | G47: =IF(G$2<=analysis_period,IF(om_fixed="n/a",Inputs!H165,om_fixed*(1+inflation_rate/100+om_fixed_escal/100)^F$2),0) -> 0 | H47: =IF(H$2<=analysis_period,IF(om_fixed="n/a",Inputs!I165,om_fixed*(1+inflation_rate/100+om_fixed_escal/100)^G$2),0) -> 0 | I47: =IF(I$2<=analysis_period,IF(om_fixed="n/a",Inputs!J165,om_fixed*(1+inflation_rate/100+om_fixed_escal/100)^H$2),0) -> 0 | J47: =IF(J$2<=analysis_period,IF(om_fixed="n/a",Inputs!K165,om_fixed*(1+inflation_rate/100+om_fixed_escal/100)^I$2),0) -> 0 | ... AP47: =IF(AP$2<=analysis_period,IF(om_fixed="n/a",Inputs!AQ165,om_fixed*(1+inflation_rate/100+om_fixed_escal/100)^AO$2),0) -> 0
A48: Capacity
A49: Capacity (DC kW) | C49: =IF(C$2<=analysis_period,system_capacity,0) -> 0 | D49: =IF(D$2<=analysis_period,system_capacity,0) -> 0 | E49: =IF(E$2<=analysis_period,system_capacity,0) -> 0 | F49: =IF(F$2<=analysis_period,system_capacity,0) -> 0 | G49: =IF(G$2<=analysis_period,system_capacity,0) -> 0 | H49: =IF(H$2<=analysis_period,system_capacity,0) -> 0 | I49: =IF(I$2<=analysis_period,system_capacity,0) -> 0 | J49: =IF(J$2<=analysis_period,system_capacity,0) -> 0 | ... AP49: =IF(AP$2<=analysis_period,system_capacity,0) -> 0
A50: Fixed Cost ($/DC kW-yr) | C50: =IF(C$2<=analysis_period,IF(om_capacity="n/a",Inputs!D166,om_capacity*(1+inflation_rate/100+om_capacity_escal/100)^B$2),0) -> 0 | D50: =IF(D$2<=analysis_period,IF(om_capacity="n/a",Inputs!E166,om_capacity*(1+inflation_rate/100+om_capacity_escal/100)^C$2),0) -> 0 | E50: =IF(E$2<=analysis_period,IF(om_capacity="n/a",Inputs!F166,om_capacity*(1+inflation_rate/100+om_capacity_escal/100)^D$2),0) -> 0 | F50: =IF(F$2<=analysis_period,IF(om_capacity="n/a",Inputs!G166,om_capacity*(1+inflation_rate/100+om_capacity_escal/100)^E$2),0) -> 0 | G50: =IF(G$2<=analysis_period,IF(om_capacity="n/a",Inputs!H166,om_capacity*(1+inflation_rate/100+om_capacity_escal/100)^F$2),0) -> 0 | H50: =IF(H$2<=analysis_period,IF(om_capacity="n/a",Inputs!I166,om_capacity*(1+inflation_rate/100+om_capacity_escal/100)^G$2),0) -> 0 | I50: =IF(I$2<=analysis_period,IF(om_capacity="n/a",Inputs!J166,om_capacity*(1+inflation_rate/100+om_capacity_escal/100)^H$2),0) -> 0 | J50: =IF(J$2<=analysis_period,IF(om_capacity="n/a",Inputs!K166,om_capacity*(1+inflation_rate/100+om_capacity_escal/100)^I$2),0) -> 0 | ... AP50: =IF(AP$2<=analysis_period,IF(om_capacity="n/a",Inputs!AQ166,om_capacity*(1+inflation_rate/100+om_capacity_escal/100)^AO$2),0) -> 0
A51: O&M capacity-based expense | C51: =C49*C50 -> 0 | D51: =D49*D50 -> 0 | E51: =E49*E50 -> 0 | F51: =F49*F50 -> 0 | G51: =G49*G50 -> 0 | H51: =H49*H50 -> 0 | I51: =I49*I50 -> 0 | J51: =J49*J50 -> 0 | ... AP51: =AP49*AP50 -> 0
A52: Variable
A53: Electricity to grid (AC MWh) | C53: =IF(C$8=0,C$5,C$8)/1000 -> 0 | D53: =IF(D$8=0,D$5,D$8)/1000 -> 0 | E53: =IF(E$8=0,E$5,E$8)/1000 -> 0 | F53: =IF(F$8=0,F$5,F$8)/1000 -> 0 | G53: =IF(G$8=0,G$5,G$8)/1000 -> 0 | H53: =IF(H$8=0,H$5,H$8)/1000 -> 0 | I53: =IF(I$8=0,I$5,I$8)/1000 -> 0 | J53: =IF(J$8=0,J$5,J$8)/1000 -> 0 | ... AP53: =IF(AP$8=0,AP$5,AP$8)/1000 -> 0
A54: Variable Cost ($/AC-MWh) | C54: =IF(C$2<=analysis_period,IF(om_production="n/a",Inputs!D167,om_production*(1+inflation_rate/100+om_production_escal/100)^B$2),0) -> 0 | D54: =IF(D$2<=analysis_period,IF(om_production="n/a",Inputs!E167,om_production*(1+inflation_rate/100+om_production_escal/100)^C$2),0) -> 0 | E54: =IF(E$2<=analysis_period,IF(om_production="n/a",Inputs!F167,om_production*(1+inflation_rate/100+om_production_escal/100)^D$2),0) -> 0 | F54: =IF(F$2<=analysis_period,IF(om_production="n/a",Inputs!G167,om_production*(1+inflation_rate/100+om_production_escal/100)^E$2),0) -> 0 | G54: =IF(G$2<=analysis_period,IF(om_production="n/a",Inputs!H167,om_production*(1+inflation_rate/100+om_production_escal/100)^F$2),0) -> 0 | H54: =IF(H$2<=analysis_period,IF(om_production="n/a",Inputs!I167,om_production*(1+inflation_rate/100+om_production_escal/100)^G$2),0) -> 0 | I54: =IF(I$2<=analysis_period,IF(om_production="n/a",Inputs!J167,om_production*(1+inflation_rate/100+om_production_escal/100)^H$2),0) -> 0 | J54: =IF(J$2<=analysis_period,IF(om_production="n/a",Inputs!K167,om_production*(1+inflation_rate/100+om_production_escal/100)^I$2),0) -> 0 | ... AP54: =IF(AP$2<=analysis_period,IF(om_production="n/a",Inputs!AQ167,om_production*(1+inflation_rate/100+om_production_escal/100)^AO$2),0) -> 0
A55: O&M production-based expense | C55: =C53*C54 -> 0 | D55: =D53*D54 -> 0 | E55: =E53*E54 -> 0 | F55: =F53*F54 -> 0 | G55: =G53*G54 -> 0 | H55: =H53*H54 -> 0 | I55: =I53*I54 -> 0 | J55: =J53*J54 -> 0 | ... AP55: =AP53*AP54 -> 0
A56: Expenses Specific to Battery Systems
A57: Battery fixed | B57: {=Inputs!C187:AQ190} -> 0 | C57: 0 | D57: 0 | E57: 0 | F57: 0 | G57: 0 | H57: 0 | I57: 0 | J57: 0 | K57: 0 | L57: 0 | M57: 0 | N57: 0 | O57: 0 | P57: 0 | Q57: 0 | R57: 0 | S57: 0 | T57: 0 | U57: 0 | V57: 0 | W57: 0 | X57: 0 | Y57: 0 | Z57: 0 | AA57: 0 | AB57: 0 | AC57: 0 | AD57: 0 | AE57: 0 | AF57: 0 | AG57: 0 | AH57: 0 | AI57: 0 | AJ57: 0 | AK57: 0 | AL57: 0 | AM57: 0 | AN57: 0 | AO57: 0 | AP57: 0
A58: Battery capacity-based | B58: 0 | C58: 0 | D58: 0 | E58: 0 | F58: 0 | G58: 0 | H58: 0 | I58: 0 | J58: 0 | K58: 0 | L58: 0 | M58: 0 | N58: 0 | O58: 0 | P58: 0 | Q58: 0 | R58: 0 | S58: 0 | T58: 0 | U58: 0 | V58: 0 | W58: 0 | X58: 0 | Y58: 0 | Z58: 0 | AA58: 0 | AB58: 0 | AC58: 0 | AD58: 0 | AE58: 0 | AF58: 0 | AG58: 0 | AH58: 0 | AI58: 0 | AJ58: 0 | AK58: 0 | AL58: 0 | AM58: 0 | AN58: 0 | AO58: 0 | AP58: 0
A59: Battery variable | B59: 0 | C59: 0 | D59: 0 | E59: 0 | F59: 0 | G59: 0 | H59: 0 | I59: 0 | J59: 0 | K59: 0 | L59: 0 | M59: 0 | N59: 0 | O59: 0 | P59: 0 | Q59: 0 | R59: 0 | S59: 0 | T59: 0 | U59: 0 | V59: 0 | W59: 0 | X59: 0 | Y59: 0 | Z59: 0 | AA59: 0 | AB59: 0 | AC59: 0 | AD59: 0 | AE59: 0 | AF59: 0 | AG59: 0 | AH59: 0 | AI59: 0 | AJ59: 0 | AK59: 0 | AL59: 0 | AM59: 0 | AN59: 0 | AO59: 0 | AP59: 0
A60: Battery replacement | B60: 0 | C60: 0 | D60: 0 | E60: 0 | F60: 0 | G60: 0 | H60: 0 | I60: 0 | J60: 0 | K60: 0 | L60: 0 | M60: 0 | N60: 0 | O60: 0 | P60: 0 | Q60: 0 | R60: 0 | S60: 0 | T60: 0 | U60: 0 | V60: 0 | W60: 0 | X60: 0 | Y60: 0 | Z60: 0 | AA60: 0 | AB60: 0 | AC60: 0 | AD60: 0 | AE60: 0 | AF60: 0 | AG60: 0 | AH60: 0 | AI60: 0 | AJ60: 0 | AK60: 0 | AL60: 0 | AM60: 0 | AN60: 0 | AO60: 0 | AP60: 0
A61: Expenses Specific to Fuel Cell Systems
A62: Fuel cell fixed | B62: {=Inputs!C192:AQ196} -> 0 | C62: 0 | D62: 0 | E62: 0 | F62: 0 | G62: 0 | H62: 0 | I62: 0 | J62: 0 | K62: 0 | L62: 0 | M62: 0 | N62: 0 | O62: 0 | P62: 0 | Q62: 0 | R62: 0 | S62: 0 | T62: 0 | U62: 0 | V62: 0 | W62: 0 | X62: 0 | Y62: 0 | Z62: 0 | AA62: 0 | AB62: 0 | AC62: 0 | AD62: 0 | AE62: 0 | AF62: 0 | AG62: 0 | AH62: 0 | AI62: 0 | AJ62: 0 | AK62: 0 | AL62: 0 | AM62: 0 | AN62: 0 | AO62: 0 | AP62: 0
A63: Fuel cell capacity-based | B63: 0 | C63: 0 | D63: 0 | E63: 0 | F63: 0 | G63: 0 | H63: 0 | I63: 0 | J63: 0 | K63: 0 | L63: 0 | M63: 0 | N63: 0 | O63: 0 | P63: 0 | Q63: 0 | R63: 0 | S63: 0 | T63: 0 | U63: 0 | V63: 0 | W63: 0 | X63: 0 | Y63: 0 | Z63: 0 | AA63: 0 | AB63: 0 | AC63: 0 | AD63: 0 | AE63: 0 | AF63: 0 | AG63: 0 | AH63: 0 | AI63: 0 | AJ63: 0 | AK63: 0 | AL63: 0 | AM63: 0 | AN63: 0 | AO63: 0 | AP63: 0
A64: Fuel cell variable | B64: 0 | C64: 0 | D64: 0 | E64: 0 | F64: 0 | G64: 0 | H64: 0 | I64: 0 | J64: 0 | K64: 0 | L64: 0 | M64: 0 | N64: 0 | O64: 0 | P64: 0 | Q64: 0 | R64: 0 | S64: 0 | T64: 0 | U64: 0 | V64: 0 | W64: 0 | X64: 0 | Y64: 0 | Z64: 0 | AA64: 0 | AB64: 0 | AC64: 0 | AD64: 0 | AE64: 0 | AF64: 0 | AG64: 0 | AH64: 0 | AI64: 0 | AJ64: 0 | AK64: 0 | AL64: 0 | AM64: 0 | AN64: 0 | AO64: 0 | AP64: 0
A65: Fuel cell replacement | B65: 0 | C65: 0 | D65: 0 | E65: 0 | F65: 0 | G65: 0 | H65: 0 | I65: 0 | J65: 0 | K65: 0 | L65: 0 | M65: 0 | N65: 0 | O65: 0 | P65: 0 | Q65: 0 | R65: 0 | S65: 0 | T65: 0 | U65: 0 | V65: 0 | W65: 0 | X65: 0 | Y65: 0 | Z65: 0 | AA65: 0 | AB65: 0 | AC65: 0 | AD65: 0 | AE65: 0 | AF65: 0 | AG65: 0 | AH65: 0 | AI65: 0 | AJ65: 0 | AK65: 0 | AL65: 0 | AM65: 0 | AN65: 0 | AO65: 0 | AP65: 0
A66: Fuel cell fuel | B66: 0 | C66: 0 | D66: 0 | E66: 0 | F66: 0 | G66: 0 | H66: 0 | I66: 0 | J66: 0 | K66: 0 | L66: 0 | M66: 0 | N66: 0 | O66: 0 | P66: 0 | Q66: 0 | R66: 0 | S66: 0 | T66: 0 | U66: 0 | V66: 0 | W66: 0 | X66: 0 | Y66: 0 | Z66: 0 | AA66: 0 | AB66: 0 | AC66: 0 | AD66: 0 | AE66: 0 | AF66: 0 | AG66: 0 | AH66: 0 | AI66: 0 | AJ66: 0 | AK66: 0 | AL66: 0 | AM66: 0 | AN66: 0 | AO66: 0 | AP66: 0
A67: Fuel (CSP, generic only) | B67: {=Inputs!C198:AQ200} -> 0 | C67: 0 | D67: 0 | E67: 0 | F67: 0 | G67: 0 | H67: 0 | I67: 0 | J67: 0 | K67: 0 | L67: 0 | M67: 0 | N67: 0 | O67: 0 | P67: 0 | Q67: 0 | R67: 0 | S67: 0 | T67: 0 | U67: 0 | V67: 0 | W67: 0 | X67: 0 | Y67: 0 | Z67: 0 | AA67: 0 | AB67: 0 | AC67: 0 | AD67: 0 | AE67: 0 | AF67: 0 | AG67: 0 | AH67: 0 | AI67: 0 | AJ67: 0 | AK67: 0 | AL67: 0 | AM67: 0 | AN67: 0 | AO67: 0 | AP67: 0
A68: Biomass feedstock (Biopower only) | B68: 0 | C68: 0 | D68: 0 | E68: 0 | F68: 0 | G68: 0 | H68: 0 | I68: 0 | J68: 0 | K68: 0 | L68: 0 | M68: 0 | N68: 0 | O68: 0 | P68: 0 | Q68: 0 | R68: 0 | S68: 0 | T68: 0 | U68: 0 | V68: 0 | W68: 0 | X68: 0 | Y68: 0 | Z68: 0 | AA68: 0 | AB68: 0 | AC68: 0 | AD68: 0 | AE68: 0 | AF68: 0 | AG68: 0 | AH68: 0 | AI68: 0 | AJ68: 0 | AK68: 0 | AL68: 0 | AM68: 0 | AN68: 0 | AO68: 0 | AP68: 0
A69: Coal feedstock (Biopower only) | B69: 0 | C69: 0 | D69: 0 | E69: 0 | F69: 0 | G69: 0 | H69: 0 | I69: 0 | J69: 0 | K69: 0 | L69: 0 | M69: 0 | N69: 0 | O69: 0 | P69: 0 | Q69: 0 | R69: 0 | S69: 0 | T69: 0 | U69: 0 | V69: 0 | W69: 0 | X69: 0 | Y69: 0 | Z69: 0 | AA69: 0 | AB69: 0 | AC69: 0 | AD69: 0 | AE69: 0 | AF69: 0 | AG69: 0 | AH69: 0 | AI69: 0 | AJ69: 0 | AK69: 0 | AL69: 0 | AM69: 0 | AN69: 0 | AO69: 0 | AP69: 0
A70: Geothermal recapitalization | B70: {=Inputs!C202:AQ202} -> 0 | C70: 0 | D70: 0 | E70: 0 | F70: 0 | G70: 0 | H70: 0 | I70: 0 | J70: 0 | K70: 0 | L70: 0 | M70: 0 | N70: 0 | O70: 0 | P70: 0 | Q70: 0 | R70: 0 | S70: 0 | T70: 0 | U70: 0 | V70: 0 | W70: 0 | X70: 0 | Y70: 0 | Z70: 0 | AA70: 0 | AB70: 0 | AC70: 0 | AD70: 0 | AE70: 0 | AF70: 0 | AG70: 0 | AH70: 0 | AI70: 0 | AJ70: 0 | AK70: 0 | AL70: 0 | AM70: 0 | AN70: 0 | AO70: 0 | AP70: 0
A71: Land Lease | C71: =IF(C$2<=analysis_period,IF(om_land_lease="n/a",total_land_area*Inputs!D$204,total_land_area*om_land_lease*(1+inflation_rate/100+om_land_lease_escal/100)^B$2),0) -> 0 | D71: =IF(D$2<=analysis_period,IF(om_land_lease="n/a",total_land_area*Inputs!E$204,total_land_area*om_land_lease*(1+inflation_rate/100+om_land_lease_escal/100)^C$2),0) -> 0 | E71: =IF(E$2<=analysis_period,IF(om_land_lease="n/a",total_land_area*Inputs!F$204,total_land_area*om_land_lease*(1+inflation_rate/100+om_land_lease_escal/100)^D$2),0) -> 0 | F71: =IF(F$2<=analysis_period,IF(om_land_lease="n/a",total_land_area*Inputs!G$204,total_land_area*om_land_lease*(1+inflation_rate/100+om_land_lease_escal/100)^E$2),0) -> 0 | G71: =IF(G$2<=analysis_period,IF(om_land_lease="n/a",total_land_area*Inputs!H$204,total_land_area*om_land_lease*(1+inflation_rate/100+om_land_lease_escal/100)^F$2),0) -> 0 | H71: =IF(H$2<=analysis_period,IF(om_land_lease="n/a",total_land_area*Inputs!I$204,total_land_area*om_land_lease*(1+inflation_rate/100+om_land_lease_escal/100)^G$2),0) -> 0 | I71: =IF(I$2<=analysis_period,IF(om_land_lease="n/a",total_land_area*Inputs!J$204,total_land_area*om_land_lease*(1+inflation_rate/100+om_land_lease_escal/100)^H$2),0) -> 0 | J71: =IF(J$2<=analysis_period,IF(om_land_lease="n/a",total_land_area*Inputs!K$204,total_land_area*om_land_lease*(1+inflation_rate/100+om_land_lease_escal/100)^I$2),0) -> 0 | ... AP71: =IF(AP$2<=analysis_period,IF(om_land_lease="n/a",total_land_area*Inputs!AQ$204,total_land_area*om_land_lease*(1+inflation_rate/100+om_land_lease_escal/100)^AO$2),0) -> 0
A72: Property Tax | C72: =C43*property_tax_rate/100 -> 0 | D72: =D43*property_tax_rate/100 -> 0 | E72: =E43*property_tax_rate/100 -> 0 | F72: =F43*property_tax_rate/100 -> 0 | G72: =G43*property_tax_rate/100 -> 0 | H72: =H43*property_tax_rate/100 -> 0 | I72: =I43*property_tax_rate/100 -> 0 | J72: =J43*property_tax_rate/100 -> 0 | ... AP72: =AP43*property_tax_rate/100 -> 0
A73: Insurance | C73: =IF(C$2<=analysis_period,total_installed_cost*insurance_rate/100*(1+inflation_rate/100)^B$2,0) -> 0 | D73: =IF(D$2<=analysis_period,total_installed_cost*insurance_rate/100*(1+inflation_rate/100)^C$2,0) -> 0 | E73: =IF(E$2<=analysis_period,total_installed_cost*insurance_rate/100*(1+inflation_rate/100)^D$2,0) -> 0 | F73: =IF(F$2<=analysis_period,total_installed_cost*insurance_rate/100*(1+inflation_rate/100)^E$2,0) -> 0 | G73: =IF(G$2<=analysis_period,total_installed_cost*insurance_rate/100*(1+inflation_rate/100)^F$2,0) -> 0 | H73: =IF(H$2<=analysis_period,total_installed_cost*insurance_rate/100*(1+inflation_rate/100)^G$2,0) -> 0 | I73: =IF(I$2<=analysis_period,total_installed_cost*insurance_rate/100*(1+inflation_rate/100)^H$2,0) -> 0 | J73: =IF(J$2<=analysis_period,total_installed_cost*insurance_rate/100*(1+inflation_rate/100)^I$2,0) -> 0 | ... AP73: =IF(AP$2<=analysis_period,total_installed_cost*insurance_rate/100*(1+inflation_rate/100)^AO$2,0) -> 0
A74: Total Expenses | C74: =C$47+C$51+C$55+SUM(C57:C60)+SUM(C62:C73) -> 0 | D74: =D$47+D$51+D$55+SUM(D57:D60)+SUM(D62:D73) -> 0 | E74: =E$47+E$51+E$55+SUM(E57:E60)+SUM(E62:E73) -> 0 | F74: =F$47+F$51+F$55+SUM(F57:F60)+SUM(F62:F73) -> 0 | G74: =G$47+G$51+G$55+SUM(G57:G60)+SUM(G62:G73) -> 0 | H74: =H$47+H$51+H$55+SUM(H57:H60)+SUM(H62:H73) -> 0 | I74: =I$47+I$51+I$55+SUM(I57:I60)+SUM(I62:I73) -> 0 | J74: =J$47+J$51+J$55+SUM(J57:J60)+SUM(J62:J73) -> 0 | ... AP74: =AP$47+AP$51+AP$55+SUM(AP57:AP60)+SUM(AP62:AP73) -> 0
A76: EBITDA | C76: =C41-C74 -> 0 | D76: =D41-D74 -> 0 | E76: =E41-E74 -> 0 | F76: =F41-F74 -> 0 | G76: =G41-G74 -> 0 | H76: =H41-H74 -> 0 | I76: =I41-I74 -> 0 | J76: =J41-J74 -> 0 | ... AP76: =AP41-AP74 -> 0
A78: Cash Flow: Project
A79: Cash Flows from Operating Activities
A80: EBITDA | C80: =C76 -> 0 | D80: =D76 -> 0 | E80: =E76 -> 0 | F80: =F76 -> 0 | G80: =G76 -> 0 | H80: =H76 -> 0 | I80: =I76 -> 0 | J80: =J76 -> 0 | ... AP80: =AP76 -> 0
A81: Plus: PBI (if not included above)
A82: =A35 -> Federal | C82: =IF(pbi_fed_for_ds="Yes",0,C590) -> 0 | D82: =IF(pbi_fed_for_ds="Yes",0,D590) -> 0 | E82: =IF(pbi_fed_for_ds="Yes",0,E590) -> 0 | F82: =IF(pbi_fed_for_ds="Yes",0,F590) -> 0 | G82: =IF(pbi_fed_for_ds="Yes",0,G590) -> 0 | H82: =IF(pbi_fed_for_ds="Yes",0,H590) -> 0 | I82: =IF(pbi_fed_for_ds="Yes",0,I590) -> 0 | J82: =IF(pbi_fed_for_ds="Yes",0,J590) -> 0 | ... AP82: =IF(pbi_fed_for_ds="Yes",0,AP590) -> 0
A83: =A36 -> State | C83: =IF(pbi_sta_for_ds="Yes",0,C594) -> 0 | D83: =IF(pbi_sta_for_ds="Yes",0,D594) -> 0 | E83: =IF(pbi_sta_for_ds="Yes",0,E594) -> 0 | F83: =IF(pbi_sta_for_ds="Yes",0,F594) -> 0 | G83: =IF(pbi_sta_for_ds="Yes",0,G594) -> 0 | H83: =IF(pbi_sta_for_ds="Yes",0,H594) -> 0 | I83: =IF(pbi_sta_for_ds="Yes",0,I594) -> 0 | J83: =IF(pbi_sta_for_ds="Yes",0,J594) -> 0 | ... AP83: =IF(pbi_sta_for_ds="Yes",0,AP594) -> 0
A84: =A37 -> Utility | C84: =IF(pbi_uti_for_ds="Yes",0,C598) -> 0 | D84: =IF(pbi_uti_for_ds="Yes",0,D598) -> 0 | E84: =IF(pbi_uti_for_ds="Yes",0,E598) -> 0 | F84: =IF(pbi_uti_for_ds="Yes",0,F598) -> 0 | G84: =IF(pbi_uti_for_ds="Yes",0,G598) -> 0 | H84: =IF(pbi_uti_for_ds="Yes",0,H598) -> 0 | I84: =IF(pbi_uti_for_ds="Yes",0,I598) -> 0 | J84: =IF(pbi_uti_for_ds="Yes",0,J598) -> 0 | ... AP84: =IF(pbi_uti_for_ds="Yes",0,AP598) -> 0
A85: =A38 -> Other | C85: =IF(pbi_oth_for_ds="Yes",0,C602) -> 0 | D85: =IF(pbi_oth_for_ds="Yes",0,D602) -> 0 | E85: =IF(pbi_oth_for_ds="Yes",0,E602) -> 0 | F85: =IF(pbi_oth_for_ds="Yes",0,F602) -> 0 | G85: =IF(pbi_oth_for_ds="Yes",0,G602) -> 0 | H85: =IF(pbi_oth_for_ds="Yes",0,H602) -> 0 | I85: =IF(pbi_oth_for_ds="Yes",0,I602) -> 0 | J85: =IF(pbi_oth_for_ds="Yes",0,J602) -> 0 | ... AP85: =IF(pbi_oth_for_ds="Yes",0,AP602) -> 0
A86: Total | C86: =SUM(C82:C85) -> 0 | D86: =SUM(D82:D85) -> 0 | E86: =SUM(E82:E85) -> 0 | F86: =SUM(F82:F85) -> 0 | G86: =SUM(G82:G85) -> 0 | H86: =SUM(H82:H85) -> 0 | I86: =SUM(I82:I85) -> 0 | J86: =SUM(J82:J85) -> 0 | ... AP86: =SUM(AP82:AP85) -> 0
A87: Plus: Interest earned on reserve accounts | B87: 0 | C87: =C750 -> 0 | D87: =D750 -> 0 | E87: =E750 -> 0 | F87: =F750 -> 0 | G87: =G750 -> 0 | H87: =H750 -> 0 | I87: =I750 -> 0 | J87: =J750 -> 0 | ... AP87: =AP750 -> 0
A88: Less: Debt interest payment | B88: 0 | C88: =-C609 -> 0 | D88: =-D609 -> 0 | E88: =-E609 -> 0 | F88: =-F609 -> 0 | G88: =-G609 -> 0 | H88: =-H609 -> 0 | I88: =-I609 -> 0 | J88: =-J609 -> 0 | ... AP88: =-AP609 -> 0
A89: Total | B89: =B80+B86+B87+B88 -> 0 | C89: =C80+C86+C87+C88 -> 0 | D89: =D80+D86+D87+D88 -> 0 | E89: =E80+E86+E87+E88 -> 0 | F89: =F80+F86+F87+F88 -> 0 | G89: =G80+G86+G87+G88 -> 0 | H89: =H80+H86+H87+H88 -> 0 | I89: =I80+I86+I87+I88 -> 0 | ... AP89: =AP80+AP86+AP87+AP88 -> 0
A91: Cash Flows from Investing Activities
A92: Capital Costs
A93: Total installed cost | B93: =-total_installed_cost -> 0
A94: Debt closing costs | B94: =-(cost_debt_closing) -> 0
A95: Debt up-front fee | B95: =-CostDebtUpfront -> 0
A96: Financing cost | B96: =-cost_other_financing -> 0
A97: Construction financing | B97: =-Inputs!I85 -> 0
A98: Total IBI | B98: =C571+C577 -> 0
A99: Total CBI | B99: =C584 -> 0
A100: Total purchase of property | B100: =SUM(B93:B99) -> 0
A101: Reserve Accounts (Increase)/Decrease
A102: Debt service reserve | B102: =-B636-B637 -> 0 | C102: =-C636-C637 -> 0 | D102: =-D636-D637 -> 0 | E102: =-E636-E637 -> 0 | F102: =-F636-F637 -> 0 | G102: =-G636-G637 -> 0 | H102: =-H636-H637 -> 0 | I102: =-I636-I637 -> 0 | ... AP102: =-AP636-AP637 -> 0
A103: Working capital reserve | B103: =-B642-B643 -> 0 | C103: =-C642-C643 -> 0 | D103: =-D642-D643 -> 0 | E103: =-E642-E643 -> 0 | F103: =-F642-F643 -> 0 | G103: =-G642-G643 -> 0 | H103: =-H642-H643 -> 0 | I103: =-I642-I643 -> 0 | ... AP103: =-AP642-AP643 -> 0
A104: Receivables reserve | B104: =-B648-B649 -> 0 | C104: =-C648-C649 -> 0 | D104: =-D648-D649 -> 0 | E104: =-E648-E649 -> 0 | F104: =-F648-F649 -> 0 | G104: =-G648-G649 -> 0 | H104: =-H648-H649 -> 0 | I104: =-I648-I649 -> 0 | ... AP104: =-AP648-AP649 -> 0
A105: Major equipment reserve 1 | B105: =-B654-B655 -> 0 | C105: =-C654-C655 -> 0 | D105: =-D654-D655 -> 0 | E105: =-E654-E655 -> 0 | F105: =-F654-F655 -> 0 | G105: =-G654-G655 -> 0 | H105: =-H654-H655 -> 0 | I105: =-I654-I655 -> 0 | ... AP105: =-AP654-AP655 -> 0
A106: Major equipment reserve 2 | B106: =-B686-B687 -> 0 | C106: =-C686-C687 -> 0 | D106: =-D686-D687 -> 0 | E106: =-E686-E687 -> 0 | F106: =-F686-F687 -> 0 | G106: =-G686-G687 -> 0 | H106: =-H686-H687 -> 0 | I106: =-I686-I687 -> 0 | ... AP106: =-AP686-AP687 -> 0
A107: Major equipment reserve 3 | B107: =-B718-B719 -> 0 | C107: =-C718-C719 -> 0 | D107: =-D718-D719 -> 0 | E107: =-E718-E719 -> 0 | F107: =-F718-F719 -> 0 | G107: =-G718-G719 -> 0 | H107: =-H718-H719 -> 0 | I107: =-I718-I719 -> 0 | ... AP107: =-AP718-AP719 -> 0
A108: Total | B108: =SUM(B102:B107) -> 0 | C108: =SUM(C102:C107) -> 0 | D108: =SUM(D102:D107) -> 0 | E108: =SUM(E102:E107) -> 0 | F108: =SUM(F102:F107) -> 0 | G108: =SUM(G102:G107) -> 0 | H108: =SUM(H102:H107) -> 0 | I108: =SUM(I102:I107) -> 0 | ... AP108: =SUM(AP102:AP107) -> 0
...

Sheet Depreciation Schedules
A1: Depreciation Schedules (Half Year)
A2: Year | B2: 5-yr MACRS | C2: 15-yr MACRS | D2: 5-yr SL | E2: 15-yr SL | F2: 20-yr SL | G2: 39-yr SL
A3: 1 | B3: 20 | C3: 5 | D3: 10 | E3: 3.33 | F3: 2.5 | G3: =2.56410256410256*0.5 -> 1.2820513
A4: 2 | B4: 32 | C4: 9.5 | D4: 20 | E4: 6.67 | F4: 5 | G4: 2.5641026
A5: 3 | B5: 19.2 | C5: 8.55 | D5: 20 | E5: 6.67 | F5: 5 | G5: 2.5641026
A6: 4 | B6: 11.52 | C6: 7.7 | D6: 20 | E6: 6.67 | F6: 5 | G6: 2.5641026
A7: 5 | B7: 11.52 | C7: 6.93 | D7: 20 | E7: 6.67 | F7: 5 | G7: 2.5641026
A8: 6 | B8: 5.76 | C8: 6.23 | D8: 10 | E8: 6.67 | F8: 5 | G8: 2.5641026
A9: 7 | B9: 0 | C9: 5.9 | D9: 0 | E9: 6.67 | F9: 5 | G9: 2.5641026
A10: 8 | B10: 0 | C10: 5.9 | D10: 0 | E10: 6.67 | F10: 5 | G10: 2.5641026
A11: 9 | B11: 0 | C11: 5.91 | D11: 0 | E11: 6.67 | F11: 5 | G11: 2.5641026
A12: 10 | B12: 0 | C12: 5.9 | D12: 0 | E12: 6.67 | F12: 5 | G12: 2.5641026
A13: 11 | B13: 0 | C13: 5.91 | D13: 0 | E13: 6.67 | F13: 5 | G13: 2.5641026
A14: 12 | B14: 0 | C14: 5.9 | D14: 0 | E14: 6.66 | F14: 5 | G14: 2.5641026
A15: 13 | B15: 0 | C15: 5.91 | D15: 0 | E15: 6.67 | F15: 5 | G15: 2.5641026
... A41: 39 | B41: 0 | C41: 0 | D41: 0 | E41: 0 | F41: 0 | G41: 2.5641026
A42: 40 | B42: 0 | C42: 0 | D42: 0 | E42: 0 | F42: 0 | G42: =2.56410256410256*0.5 -> 1.2820513
A43: For additional information on depreciation schedules, see IRS publication 946.
A44: http://www.irs.gov/pub/irs-pdf/p946.pdf
