Workbook
Name analysis_period: Inputs!$C$38
Name annual_fuel_usage: Inputs!$C$23
Name AnnualLandLease: Inputs!$D$215
Name AnnualOMCapacity: Inputs!$D$166
Name AnnualOMFixed: Inputs!$D$165
Name AnnualOMProduction: Inputs!$D$167
Name AnnualPBIFederal: Inputs!$D$179
Name AnnualPBIOther: Inputs!$D$182
Name AnnualPBIState: Inputs!$D$180
Name AnnualPBIUtility: Inputs!$D$181
Name AnnualPTCFederal: Inputs!$D$184
Name AnnualPTCState: Inputs!$D$185
Name AnnualTaxFederal: Inputs!$C$170
Name AnnualTaxState: Inputs!$C$169
Name batt_annual_discharge_energy: Inputs!$C$153
Name CapacityPayment: Inputs!$C$34
Name cbi_fed_amount: Inputs!$C$125
Name cbi_fed_deprbas_fed: Inputs!$G$125
Name cbi_fed_deprbas_sta: Inputs!$H$125
Name cbi_fed_maxvalue: Inputs!$D$125
Name cbi_fed_tax_fed: Inputs!$E$125
Name cbi_fed_tax_sta: Inputs!$F$125
Name cbi_oth_amount: Inputs!$C$128
Name cbi_oth_deprbas_fed: Inputs!$G$128
Name cbi_oth_deprbas_sta: Inputs!$H$128
Name cbi_oth_maxvalue: Inputs!$D$128
Name cbi_oth_tax_fed: Inputs!$E$128
Name cbi_oth_tax_sta: Inputs!$F$128
Name cbi_sta_amount: Inputs!$C$126
Name cbi_sta_deprbas_fed: Inputs!$G$126
Name cbi_sta_deprbas_sta: Inputs!$H$126
Name cbi_sta_maxvalue: Inputs!$D$126
Name cbi_sta_tax_fed: Inputs!$E$126
Name cbi_sta_tax_sta: Inputs!$F$126
Name cbi_uti_amount: Inputs!$C$127
Name cbi_uti_deprbas_fed: Inputs!$G$127
Name cbi_uti_deprbas_sta: Inputs!$H$127
Name cbi_uti_maxvalue: Inputs!$D$127
Name cbi_uti_tax_fed: Inputs!$E$127
Name cbi_uti_tax_sta: Inputs!$F$127
Name cf_ancillary_services_1_revenue: Inputs!$C$157
Name cf_ancillary_services_2_revenue: Inputs!$C$158
Name cf_ancillary_services_3_revenue: Inputs!$C$159
Name cf_ancillary_services_4_revenue: Inputs!$C$160
Name cf_annual_cost_lcos: Inputs!$C$212
Name cf_annual_discharge_lcos: Inputs!$C$213
Name cf_battery_replacement_cost: Inputs!$C$192
Name cf_capacity_payment: Inputs!$C$162
Name cf_curtailment_value: Inputs!$C$161
Name cf_disbursement_debtservice: Inputs!$C$207
Name cf_energy_market_revenue: Inputs!$C$156
Name cf_energy_net: Inputs!$C$151
Name cf_energy_purchases: Inputs!$C$150
Name cf_energy_sales: Inputs!$C$149
Name cf_energy_without_battery: Inputs!$C$152
Name cf_fuelcell_replacement_cost: Inputs!$C$197
Name cf_funding_debtservice: Inputs!$C$206
Name cf_om_capacity1_expense: Inputs!$C$190
Name cf_om_capacity2_expense: Inputs!$C$195
Name cf_om_fixed1_expense: Inputs!$C$189

Sheet Inputs
B1: Merchant Plant Inputs
B2: SYSTEM DESIGN | E2: KEY
B3: Nameplate capacity (kW) | C3: 0 | E3: Calculated
E4: Input from SAM
B5: SYSTEM COSTS | E5: Annual values from SAM
B6: Total installed cost ($) | C6: 0 | E6: Value depends on option in SAM
B8: OPERATION AND MAINTENANCE COSTS | E8: METRICS
B9: Fixed annual cost ($/yr) | C9: 0 | E9: LCOE, nominal (¢/kWh) | F9: ='Cash Flow'!B150 -> 0
B10: Escalation (% above inflation) | C10: 0 | E10: NPV ($) | F10: ='Cash Flow'!B141 -> 0
B11: Fixed cost by capacity ($/kW-yr) | C11: 0 | E11: IRR (%) | F11: =HLOOKUP(F12,'Cash Flow'!B2:AP138,137) -> 0
B12: Escalation (% above inflation) | C12: 0 | E12: IRR Year | F12: =analysis_period -> 0
B13: Variable cost by generation ($/MWh) | C13: 0 | E13: IRR at end of project (%) | F13: =HLOOKUP(analysis_period,'Cash Flow'!B2:AP138,137) -> 0
B14: Escalation (% above inflation) | C14: 0 | E14: Total capital cost ($) | F14: =-'Cash Flow'!B104 -> 0
E15: Equity ($) | F15: =F14-F16 -> 0
B16: LAND LEASE | E16: Size of debt ($) | F16: ='Cash Flow'!B601 -> 0
B17: Land area estimate (acres) | C17: 0 | E17: Minimum debt service coverage ratio | F17: ='Cash Flow'!B621 -> 0
B18: Annual land lease cost ($/acre) | C18: 0 | E18: Debt fraction (%) | F18: =F16/F14*100 -> #DIV/0!
B19: Land lease escalation rate (% above inflation) | C19: 0
B21: FUEL COSTS (CSP, GENERIC, AND BIOPOWER SYSTEMS ONLY)
B22: Fuel (CSP and generic system only)
B23: Annual usage (kWh) | C23: 0
B24: Heat rate (MMBtu/MWh) | C24: 0
B25: Cost ($/MMBtu) | C25: 0
B26: Escalation (%/year above inflation) | C26: 0
B28: Revenue Sources
B29: Energy market | C29: 1
B30: Ancillary service 1 | C30: 0
B31: Ancillary service 2 | C31: 0
B32: Ancillary service 3 | C32: 0
B33: Ancillary service 4 | C33: 0
B34: Capacity payment | C34: 0
B36: FINANCIAL PARAMETERS
B37: Analysis Parameters
B38: Analysis period (years, 40 max) | C38: 0
B39: Inflation rate (%/year) | C39: 0
B40: Real discount rate (%/year) | C40: 0
B41: Nominal discount rate (%/year) | C41: =((inflation_rate/100+1)*(real_discount_rate/100+1)-1)*100 -> 0
B42: Tax and Insurance Rates
B43: Federal income tax rate in Year 1 (%/year) | C43: =AnnualTaxFederal -> 0
B44: State income tax rate in Year 1 (%/year) | C44: =AnnualTaxState -> 0
B45: Sales tax (% of total direct cost) | C45: 0
B46: Insurance rate (annual, % of installed cost) | C46: 0
B47: Property Tax
B48: Assessed percentage (% of total installed cost) | C48: 0
B49: Assesed value ($) | C49: =total_installed_cost*prop_tax_cost_assessed_percent/100 -> 0
B50: Annual decline (%/year) | C50: 0
B51: Property tax rate (%/year) | C51: 0
B52: Salvage Value
B53: Net salvage value (% of total installed cost) | C53: 0
B54: End of analysis period value ($) | C54: =total_installed_cost*salvage_percentage/100 -> 0
B56: PROJECT TERM DEBT
B57: Debt sizing and payment schedule
B58: Debt percent (mortgage stye with constant payments) | C58: Calculated
B59: Size of debt for mortgage style | C59: N/A
B60: Debt service coverage ratio (sculpted payments with constant DSCR) | C60: 0
B61: Limit debt fraction (for sculpted payments only) | C61: No
B62: Maximum debt percent (%) (for sculpted payments only) | C62: 100
B63: Annual payment schedule | C63: Equal payments
B64: Debt Parameters
B65: Tenor (years) | C65: 0
B66: Moratorium (years) | C66: 0
B67: Annual all-in interest rate (%) | C67: 0
B68: Debt closing costs ($) | C68: 0
B69: Up-front fee (% of total debt) | C69: 0
B70: Up-front fee amount ($, from SAM results) | C70: 0
B72: COST OF ACQUIRING FINANCING
B73: Other financing cost ($) | C73: 0
B75: CONSTRUCTION FINANCING
B76: Total construction financing cost ($) | C76: 0
B78: CONSTRUCTION FINANCING CALCULATION (provided here for reference, only total financing cost above is input to cash flow)
C79: Percent of installed cost | D79: Up-front fee (% of principal) | E79: Months prior to operation | F79: Annual interest rate (%) | G79: Principal | H79: Interest | I79: Total construction financing cost
B80: Loan 1 | C80: 0 | D80: 0 | E80: 0 | F80: 0 | G80: =C80/100*total_installed_cost -> 0 | H80: =G80*F80/100*E80/12*0.5 -> 0 | I80: =H80+D80/100*G80 -> 0
B81: Loan 2 | C81: 0 | D81: 0 | E81: 0 | F81: 0 | G81: =C81/100*total_installed_cost -> 0 | H81: =G81*F81/100*E81/12*0.5 -> 0 | I81: =H81+D81/100*G81 -> 0
B82: Loan 3 | C82: 0 | D82: 0 | E82: 0 | F82: 0 | G82: =C82/100*total_installed_cost -> 0 | H82: =G82*F82/100*E82/12*0.5 -> 0 | I82: =H82+D82/100*G82 -> 0
B83: Loan 4 | C83: 0 | D83: 0 | E83: 0 | F83: 0 | G83: =C83/100*total_installed_cost -> 0 | H83: =G83*F83/100*E83/12*0.5 -> 0 | I83: =H83+D83/100*G83 -> 0
B84: Loan 5 | C84: 0 | D84: 0 | E84: 0 | F84: 0 | G84: =C84/100*total_installed_cost -> 0 | H84: =G84*F84/100*E84/12*0.5 -> 0 | I84: =H84+D84/100*G84 -> 0
B85: Totals: | G85: =SUM(G80:G84) -> 0 | H85: =SUM(H80:H84) -> 0 | I85: =SUM(I80:I84) -> 0
B87: RESERVE ACCOUNTS
B88: Interest on reserves (%/year) | C88: 0
B89: Working capital reserve (months of operating costs) | C89: 0
B90: Debt service reserve account (months of P&I payments) | C90: 0
B91: Receivables reserve | C91: 0
B92: Major equipment replacement reserve accounts | C92: Replacement cost ($/W) | D92: Year 1 dollars | E92: Replacement frequency (years)
B93: Replacement reserve 1 | C93: 0 | D93: =C93*system_capacity*1000 -> 0 | E93: 0
B94: Replacement reserve 2 | C94: 0 | D94: =C94*system_capacity*1000 -> 0 | E94: 0
B95: Replacement reserve 3 | C95: 0 | D95: =C95*system_capacity*1000 -> 0 | E95: 0
B96: Depreciation treatment for replacement reserves
B97: Federal | C97: 5-yr MACRS
B98: State | C98: 5-yr MACRS
B100: TAX CREDITS
B101: Investment Tax Credit | E101: Reduces depreciation basis
B102: As fixed amount | C102: Amount ($) | E102: Federal | F102: State
B103: Federal ($) | C103: =SUM($D$172:$AQ$172) -> 0 | E103: Yes | F103: Yes
B104: State ($) | C104: =SUM($D$173:$AQ$173) -> 0 | E104: No | F104: No
B105: As percentage | C105: % | D105: Maximum ($)
B106: Federal (% of total installed cost) | C106: =SUM($D$174:$AQ$174) -> 0 | D106: =SUM($D$175:$AQ$175) -> 0 | E106: Yes | F106: Yes
B107: State (% of total installed cost) | C107: =SUM($D$176:$AQ$176) -> 0 | D107: =SUM($D$177:$AQ$177) -> 0 | E107: No | F107: No
B108: Production Tax Credit | C108: Amount ($/kWh) | D108: Term (years) | E108: Escalation (%/year)
B109: Federal | C109: 0 | D109: 0 | E109: 0
B110: State | C110: 0 | D110: 0 | E110: 0
...

Sheet Cash Flow
A1: Merchant Plant Cash Flow
A2: Operating Year | B2: 0 | C2: =IF(B2<analysis_period,B2+1,"") | D2: =IF(C2<analysis_period,C2+1,"") | E2: =IF(D2<analysis_period,D2+1,"") | F2: =IF(E2<analysis_period,E2+1,"") | G2: =IF(F2<analysis_period,F2+1,"") | H2: =IF(G2<analysis_period,G2+1,"") | I2: =IF(H2<analysis_period,H2+1,"") | J2: =IF(I2<analysis_period,I2+1,"") | ... AP2: =IF(AO2<analysis_period,AO2+1,"")
A4: Energy
A5: Electricity to grid (AC kWh) | B5: {=Inputs!C149:AQ150} -> 0 | C5: 0 | D5: 0 | E5: 0 | F5: 0 | G5: 0 | H5: 0 | I5: 0 | J5: 0 | K5: 0 | L5: 0 | M5: 0 | N5: 0 | O5: 0 | P5: 0 | Q5: 0 | R5: 0 | S5: 0 | T5: 0 | U5: 0 | V5: 0 | W5: 0 | X5: 0 | Y5: 0 | Z5: 0 | AA5: 0 | AB5: 0 | AC5: 0 | AD5: 0 | AE5: 0 | AF5: 0 | AG5: 0 | AH5: 0 | AI5: 0 | AJ5: 0 | AK5: 0 | AL5: 0 | AM5: 0 | AN5: 0 | AO5: 0 | AP5: 0
A6: Electricity from grid (AC kWh) | B6: 0 | C6: 0 | D6: 0 | E6: 0 | F6: 0 | G6: 0 | H6: 0 | I6: 0 | J6: 0 | K6: 0 | L6: 0 | M6: 0 | N6: 0 | O6: 0 | P6: 0 | Q6: 0 | R6: 0 | S6: 0 | T6: 0 | U6: 0 | V6: 0 | W6: 0 | X6: 0 | Y6: 0 | Z6: 0 | AA6: 0 | AB6: 0 | AC6: 0 | AD6: 0 | AE6: 0 | AF6: 0 | AG6: 0 | AH6: 0 | AI6: 0 | AJ6: 0 | AK6: 0 | AL6: 0 | AM6: 0 | AN6: 0 | AO6: 0 | AP6: 0
A7: Electricity to grid net (AC kWh) | B7: =SUM(B$5:B$6) -> 0 | C7: =SUM(C5:C6) -> 0 | D7: =SUM(D5:D6) -> 0 | E7: =SUM(E5:E6) -> 0 | F7: =SUM(F5:F6) -> 0 | G7: =SUM(G5:G6) -> 0 | H7: =SUM(H5:H6) -> 0 | I7: =SUM(I5:I6) -> 0 | J7: =SUM(J5:J6) -> 0 | ... AP7: =SUM(AP5:AP6) -> 0
A8: Electricity generated without storage (AC kWh) | B8: {=Inputs!C152:AQ154} -> 0 | C8: 0 | D8: 0 | E8: 0 | F8: 0 | G8: 0 | H8: 0 | I8: 0 | J8: 0 | K8: 0 | L8: 0 | M8: 0 | N8: 0 | O8: 0 | P8: 0 | Q8: 0 | R8: 0 | S8: 0 | T8: 0 | U8: 0 | V8: 0 | W8: 0 | X8: 0 | Y8: 0 | Z8: 0 | AA8: 0 | AB8: 0 | AC8: 0 | AD8: 0 | AE8: 0 | AF8: 0 | AG8: 0 | AH8: 0 | AI8: 0 | AJ8: 0 | AK8: 0 | AL8: 0 | AM8: 0 | AN8: 0 | AO8: 0 | AP8: 0
A9: Battery annual energy discharged (AC kWh) | B9: 0 | C9: 0 | D9: 0 | E9: 0 | F9: 0 | G9: 0 | H9: 0 | I9: 0 | J9: 0 | K9: 0 | L9: 0 | M9: 0 | N9: 0 | O9: 0 | P9: 0 | Q9: 0 | R9: 0 | S9: 0 | T9: 0 | U9: 0 | V9: 0 | W9: 0 | X9: 0 | Y9: 0 | Z9: 0 | AA9: 0 | AB9: 0 | AC9: 0 | AD9: 0 | AE9: 0 | AF9: 0 | AG9: 0 | AH9: 0 | AI9: 0 | AJ9: 0 | AK9: 0 | AL9: 0 | AM9: 0 | AN9: 0 | AO9: 0 | AP9: 0
A10: Fuel cell annual energy discharged (AC kWh) | B10: 0 | C10: 0 | D10: 0 | E10: 0 | F10: 0 | G10: 0 | H10: 0 | I10: 0 | J10: 0 | K10: 0 | L10: 0 | M10: 0 | N10: 0 | O10: 0 | P10: 0 | Q10: 0 | R10: 0 | S10: 0 | T10: 0 | U10: 0 | V10: 0 | W10: 0 | X10: 0 | Y10: 0 | Z10: 0 | AA10: 0 | AB10: 0 | AC10: 0 | AD10: 0 | AE10: 0 | AF10: 0 | AG10: 0 | AH10: 0 | AI10: 0 | AJ10: 0 | AK10: 0 | AL10: 0 | AM10: 0 | AN10: 0 | AO10: 0 | AP10: 0
A12: Revenue
A13: Energy and Capacity Revenue
A14: Energy market | B14: {=Inputs!C156:AQ156} -> 0 | C14: 0 | D14: 0 | E14: 0 | F14: 0 | G14: 0 | H14: 0 | I14: 0 | J14: 0 | K14: 0 | L14: 0 | M14: 0 | N14: 0 | O14: 0 | P14: 0 | Q14: 0 | R14: 0 | S14: 0 | T14: 0 | U14: 0 | V14: 0 | W14: 0 | X14: 0 | Y14: 0 | Z14: 0 | AA14: 0 | AB14: 0 | AC14: 0 | AD14: 0 | AE14: 0 | AF14: 0 | AG14: 0 | AH14: 0 | AI14: 0 | AJ14: 0 | AK14: 0 | AL14: 0 | AM14: 0 | AN14: 0 | AO14: 0 | AP14: 0
A15: Ancillary service 1 | B15: {=Inputs!C157:AQ157} -> 0 | C15: 0 | D15: 0 | E15: 0 | F15: 0 | G15: 0 | H15: 0 | I15: 0 | J15: 0 | K15: 0 | L15: 0 | M15: 0 | N15: 0 | O15: 0 | P15: 0 | Q15: 0 | R15: 0 | S15: 0 | T15: 0 | U15: 0 | V15: 0 | W15: 0 | X15: 0 | Y15: 0 | Z15: 0 | AA15: 0 | AB15: 0 | AC15: 0 | AD15: 0 | AE15: 0 | AF15: 0 | AG15: 0 | AH15: 0 | AI15: 0 | AJ15: 0 | AK15: 0 | AL15: 0 | AM15: 0 | AN15: 0 | AO15: 0 | AP15: 0
A16: Ancillary service 2 | B16: {=Inputs!C158:AQ158} -> 0 | C16: 0 | D16: 0 | E16: 0 | F16: 0 | G16: 0 | H16: 0 | I16: 0 | J16: 0 | K16: 0 | L16: 0 | M16: 0 | N16: 0 | O16: 0 | P16: 0 | Q16: 0 | R16: 0 | S16: 0 | T16: 0 | U16: 0 | V16: 0 | W16: 0 | X16: 0 | Y16: 0 | Z16: 0 | AA16: 0 | AB16: 0 | AC16: 0 | AD16: 0 | AE16: 0 | AF16: 0 | AG16: 0 | AH16: 0 | AI16: 0 | AJ16: 0 | AK16: 0 | AL16: 0 | AM16: 0 | AN16: 0 | AO16: 0 | AP16: 0
A17: Ancillary service 3 | B17: {=Inputs!C159:AQ159} -> 0 | C17: 0 | D17: 0 | E17: 0 | F17: 0 | G17: 0 | H17: 0 | I17: 0 | J17: 0 | K17: 0 | L17: 0 | M17: 0 | N17: 0 | O17: 0 | P17: 0 | Q17: 0 | R17: 0 | S17: 0 | T17: 0 | U17: 0 | V17: 0 | W17: 0 | X17: 0 | Y17: 0 | Z17: 0 | AA17: 0 | AB17: 0 | AC17: 0 | AD17: 0 | AE17: 0 | AF17: 0 | AG17: 0 | AH17: 0 | AI17: 0 | AJ17: 0 | AK17: 0 | AL17: 0 | AM17: 0 | AN17: 0 | AO17: 0 | AP17: 0
A18: Ancillary service 4 | B18: {=Inputs!C160:AQ160} -> 0 | C18: 0 | D18: 0 | E18: 0 | F18: 0 | G18: 0 | H18: 0 | I18: 0 | J18: 0 | K18: 0 | L18: 0 | M18: 0 | N18: 0 | O18: 0 | P18: 0 | Q18: 0 | R18: 0 | S18: 0 | T18: 0 | U18: 0 | V18: 0 | W18: 0 | X18: 0 | Y18: 0 | Z18: 0 | AA18: 0 | AB18: 0 | AC18: 0 | AD18: 0 | AE18: 0 | AF18: 0 | AG18: 0 | AH18: 0 | AI18: 0 | AJ18: 0 | AK18: 0 | AL18: 0 | AM18: 0 | AN18: 0 | AO18: 0 | AP18: 0
A19: Curtailment payments | B19: {=Inputs!C161:AQ163} -> 0 | C19: 0 | D19: 0 | E19: 0 | F19: 0 | G19: 0 | H19: 0 | I19: 0 | J19: 0 | K19: 0 | L19: 0 | M19: 0 | N19: 0 | O19: 0 | P19: 0 | Q19: 0 | R19: 0 | S19: 0 | T19: 0 | U19: 0 | V19: 0 | W19: 0 | X19: 0 | Y19: 0 | Z19: 0 | AA19: 0 | AB19: 0 | AC19: 0 | AD19: 0 | AE19: 0 | AF19: 0 | AG19: 0 | AH19: 0 | AI19: 0 | AJ19: 0 | AK19: 0 | AL19: 0 | AM19: 0 | AN19: 0 | AO19: 0 | AP19: 0
A20: Capacity payments | B20: 0 | C20: 0 | D20: 0 | E20: 0 | F20: 0 | G20: 0 | H20: 0 | I20: 0 | J20: 0 | K20: 0 | L20: 0 | M20: 0 | N20: 0 | O20: 0 | P20: 0 | Q20: 0 | R20: 0 | S20: 0 | T20: 0 | U20: 0 | V20: 0 | W20: 0 | X20: 0 | Y20: 0 | Z20: 0 | AA20: 0 | AB20: 0 | AC20: 0 | AD20: 0 | AE20: 0 | AF20: 0 | AG20: 0 | AH20: 0 | AI20: 0 | AJ20: 0 | AK20: 0 | AL20: 0 | AM20: 0 | AN20: 0 | AO20: 0 | AP20: 0
A21: Thermal revenue (fuel cell only) | B21: 0 | C21: 0 | D21: 0 | E21: 0 | F21: 0 | G21: 0 | H21: 0 | I21: 0 | J21: 0 | K21: 0 | L21: 0 | M21: 0 | N21: 0 | O21: 0 | P21: 0 | Q21: 0 | R21: 0 | S21: 0 | T21: 0 | U21: 0 | V21: 0 | W21: 0 | X21: 0 | Y21: 0 | Z21: 0 | AA21: 0 | AB21: 0 | AC21: 0 | AD21: 0 | AE21: 0 | AF21: 0 | AG21: 0 | AH21: 0 | AI21: 0 | AJ21: 0 | AK21: 0 | AL21: 0 | AM21: 0 | AN21: 0 | AO21: 0 | AP21: 0
A22: Subtotal revenue | C22: =SUM(C14:C21) -> 0 | D22: =SUM(D14:D21) -> 0 | E22: =SUM(E14:E21) -> 0 | F22: =SUM(F14:F21) -> 0 | G22: =SUM(G14:G21) -> 0 | H22: =SUM(H14:H21) -> 0 | I22: =SUM(I14:I21) -> 0 | J22: =SUM(J14:J21) -> 0 | ... AP22: =SUM(AP14:AP21) -> 0
A23: Production Based Incentive (included if available for debt service)
A24: Federal | C24: =IF(pbi_fed_for_ds="Yes",C580,0) -> 0 | D24: =IF(pbi_fed_for_ds="Yes",D580,0) -> 0 | E24: =IF(pbi_fed_for_ds="Yes",E580,0) -> 0 | F24: =IF(pbi_fed_for_ds="Yes",F580,0) -> 0 | G24: =IF(pbi_fed_for_ds="Yes",G580,0) -> 0 | H24: =IF(pbi_fed_for_ds="Yes",H580,0) -> 0 | I24: =IF(pbi_fed_for_ds="Yes",I580,0) -> 0 | J24: =IF(pbi_fed_for_ds="Yes",J580,0) -> 0 | ... AP24: =IF(pbi_fed_for_ds="Yes",AP580,0) -> 0
A25: State | C25: =IF(pbi_sta_for_ds="Yes",C584,0) -> 0 | D25: =IF(pbi_sta_for_ds="Yes",D584,0) -> 0 | E25: =IF(pbi_sta_for_ds="Yes",E584,0) -> 0 | F25: =IF(pbi_sta_for_ds="Yes",F584,0) -> 0 | G25: =IF(pbi_sta_for_ds="Yes",G584,0) -> 0 | H25: =IF(pbi_sta_for_ds="Yes",H584,0) -> 0 | I25: =IF(pbi_sta_for_ds="Yes",I584,0) -> 0 | J25: =IF(pbi_sta_for_ds="Yes",J584,0) -> 0 | ... AP25: =IF(pbi_sta_for_ds="Yes",AP584,0) -> 0
A26: Utility | C26: =IF(pbi_uti_for_ds="Yes",C588,0) -> 0 | D26: =IF(pbi_uti_for_ds="Yes",D588,0) -> 0 | E26: =IF(pbi_uti_for_ds="Yes",E588,0) -> 0 | F26: =IF(pbi_uti_for_ds="Yes",F588,0) -> 0 | G26: =IF(pbi_uti_for_ds="Yes",G588,0) -> 0 | H26: =IF(pbi_uti_for_ds="Yes",H588,0) -> 0 | I26: =IF(pbi_uti_for_ds="Yes",I588,0) -> 0 | J26: =IF(pbi_uti_for_ds="Yes",J588,0) -> 0 | ... AP26: =IF(pbi_uti_for_ds="Yes",AP588,0) -> 0
A27: Other | C27: =IF(pbi_oth_for_ds="Yes",C592,0) -> 0 | D27: =IF(pbi_oth_for_ds="Yes",D592,0) -> 0 | E27: =IF(pbi_oth_for_ds="Yes",E592,0) -> 0 | F27: =IF(pbi_oth_for_ds="Yes",F592,0) -> 0 | G27: =IF(pbi_oth_for_ds="Yes",G592,0) -> 0 | H27: =IF(pbi_oth_for_ds="Yes",H592,0) -> 0 | I27: =IF(pbi_oth_for_ds="Yes",I592,0) -> 0 | J27: =IF(pbi_oth_for_ds="Yes",J592,0) -> 0 | ... AP27: =IF(pbi_oth_for_ds="Yes",AP592,0) -> 0
A28: Subtotal PBI | C28: =SUM(C24:C27) -> 0 | D28: =SUM(D24:D27) -> 0 | E28: =SUM(E24:E27) -> 0 | F28: =SUM(F24:F27) -> 0 | G28: =SUM(G24:G27) -> 0 | H28: =SUM(H24:H27) -> 0 | I28: =SUM(I24:I27) -> 0 | J28: =SUM(J24:J27) -> 0 | ... AP28: =SUM(AP24:AP27) -> 0
A29: Salvage value | C29: =IF(C2=analysis_period,total_installed_cost*salvage_percentage/100,0) -> 0 | D29: =IF(D2=analysis_period,total_installed_cost*salvage_percentage/100,0) -> 0 | E29: =IF(E2=analysis_period,total_installed_cost*salvage_percentage/100,0) -> 0 | F29: =IF(F2=analysis_period,total_installed_cost*salvage_percentage/100,0) -> 0 | G29: =IF(G2=analysis_period,total_installed_cost*salvage_percentage/100,0) -> 0 | H29: =IF(H2=analysis_period,total_installed_cost*salvage_percentage/100,0) -> 0 | I29: =IF(I2=analysis_period,total_installed_cost*salvage_percentage/100,0) -> 0 | J29: =IF(J2=analysis_period,total_installed_cost*salvage_percentage/100,0) -> 0 | ... AP29: =IF(AP2=analysis_period,total_installed_cost*salvage_percentage/100,0) -> 0
A30: Total Revenue | C30: =IF(C2<=analysis_period,C22+C28+C29,0) -> 0 | D30: =IF(D2<=analysis_period,D22+D28+D29,0) -> 0 | E30: =IF(E2<=analysis_period,E22+E28+E29,0) -> 0 | F30: =IF(F2<=analysis_period,F22+F28+F29,0) -> 0 | G30: =IF(G2<=analysis_period,G22+G28+G29,0) -> 0 | H30: =IF(H2<=analysis_period,H22+H28+H29,0) -> 0 | I30: =IF(I2<=analysis_period,I22+I28+I29,0) -> 0 | J30: =IF(J2<=analysis_period,J22+J28+J29,0) -> 0 | ... AP30: =IF(AP2<=analysis_period,AP22+AP28+AP29,0) -> 0
A32: Property tax net assessed value | C32: =PropertyTaxAssessedValue -> 0 | D32: =IF(D2<=analysis_period,PropertyTaxAssessedValue*(100-(D$2-1)*prop_tax_assessed_decline)/100,0) -> 0 | E32: =IF(E2<=analysis_period,PropertyTaxAssessedValue*(100-(E$2-1)*prop_tax_assessed_decline)/100,0) -> 0 | F32: =IF(F2<=analysis_period,PropertyTaxAssessedValue*(100-(F$2-1)*prop_tax_assessed_decline)/100,0) -> 0 | G32: =IF(G2<=analysis_period,PropertyTaxAssessedValue*(100-(G$2-1)*prop_tax_assessed_decline)/100,0) -> 0 | H32: =IF(H2<=analysis_period,PropertyTaxAssessedValue*(100-(H$2-1)*prop_tax_assessed_decline)/100,0) -> 0 | I32: =IF(I2<=analysis_period,PropertyTaxAssessedValue*(100-(I$2-1)*prop_tax_assessed_decline)/100,0) -> 0 | J32: =IF(J2<=analysis_period,PropertyTaxAssessedValue*(100-(J$2-1)*prop_tax_assessed_decline)/100,0) -> 0 | K32: =IF(K2<=analysis_period,PropertyTaxAssessedValue*(100-(K$2-1)*prop_tax_assessed_decline)/100,0) -> 0 | ... AP32: =IF(AP2<=analysis_period,PropertyTaxAssessedValue*(100-(AP$2-1)*prop_tax_assessed_decline)/100,0) -> 0
A34: Operating Expenses
A35: Operation and maintenance (O&M)
A36: Fixed | C36: =IF(C$2<=analysis_period,IF(om_fixed="n/a",Inputs!D165,om_fixed*(1+inflation_rate/100+om_fixed_escal/100)^B$2),0) -> 0 | D36: =IF(D$2<=analysis_period,IF(om_fixed="n/a",Inputs!E165,om_fixed*(1+inflation_rate/100+om_fixed_escal/100)^C$2),0) -> 0 | E36: =IF(E$2<=analysis_period,IF(om_fixed="n/a",Inputs!F165,om_fixed*(1+inflation_rate/100+om_fixed_escal/100)^D$2),0) -> 0 | F36: =IF(F$2<=analysis_period,IF(om_fixed="n/a",Inputs!G165,om_fixed*(1+inflation_rate/100+om_fixed_escal/100)^E$2),0) -> 0 | G36: =IF(G$2<=analysis_period,IF(om_fixed="n/a",Inputs!H165,om_fixed*(1+inflation_rate/100+om_fixed_escal/100)^F$2),0) -> 0 | H36: =IF(H$2<=analysis_period,IF(om_fixed="n/a",Inputs!I165,om_fixed*(1+inflation_rate/100+om_fixed_escal/100)^G$2),0) -> 0 | I36: =IF(I$2<=analysis_period,IF(om_fixed="n/a",Inputs!J165,om_fixed*(1+inflation_rate/100+om_fixed_escal/100)^H$2),0) -> 0 | J36: =IF(J$2<=analysis_period,IF(om_fixed="n/a",Inputs!K165,om_fixed*(1+inflation_rate/100+om_fixed_escal/100)^I$2),0) -> 0 | ... AP36: =IF(AP$2<=analysis_period,IF(om_fixed="n/a",Inputs!AQ165,om_fixed*(1+inflation_rate/100+om_fixed_escal/100)^AO$2),0) -> 0
A37: Capacity
A38: Capacity (DC kW) | C38: =IF(C$2<=analysis_period,system_capacity,0) -> 0 | D38: =IF(D$2<=analysis_period,system_capacity,0) -> 0 | E38: =IF(E$2<=analysis_period,system_capacity,0) -> 0 | F38: =IF(F$2<=analysis_period,system_capacity,0) -> 0 | G38: =IF(G$2<=analysis_period,system_capacity,0) -> 0 | H38: =IF(H$2<=analysis_period,system_capacity,0) -> 0 | I38: =IF(I$2<=analysis_period,system_capacity,0) -> 0 | J38: =IF(J$2<=analysis_period,system_capacity,0) -> 0 | ... AP38: =IF(AP$2<=analysis_period,system_capacity,0) -> 0
A39: Fixed Cost ($/DC kW-yr) | C39: =IF(C$2<=analysis_period,IF(om_capacity="n/a",Inputs!D166,om_capacity*(1+inflation_rate/100+om_capacity_escal/100)^B$2),0) -> 0 | D39: =IF(D$2<=analysis_period,IF(om_capacity="n/a",Inputs!E166,om_capacity*(1+inflation_rate/100+om_capacity_escal/100)^C$2),0) -> 0 | E39: =IF(E$2<=analysis_period,IF(om_capacity="n/a",Inputs!F166,om_capacity*(1+inflation_rate/100+om_capacity_escal/100)^D$2),0) -> 0 | F39: =IF(F$2<=analysis_period,IF(om_capacity="n/a",Inputs!G166,om_capacity*(1+inflation_rate/100+om_capacity_escal/100)^E$2),0) -> 0 | G39: =IF(G$2<=analysis_period,IF(om_capacity="n/a",Inputs!H166,om_capacity*(1+inflation_rate/100+om_capacity_escal/100)^F$2),0) -> 0 | H39: =IF(H$2<=analysis_period,IF(om_capacity="n/a",Inputs!I166,om_capacity*(1+inflation_rate/100+om_capacity_escal/100)^G$2),0) -> 0 | I39: =IF(I$2<=analysis_period,IF(om_capacity="n/a",Inputs!J166,om_capacity*(1+inflation_rate/100+om_capacity_escal/100)^H$2),0) -> 0 | J39: =IF(J$2<=analysis_period,IF(om_capacity="n/a",Inputs!K166,om_capacity*(1+inflation_rate/100+om_capacity_escal/100)^I$2),0) -> 0 | ... AP39: =IF(AP$2<=analysis_period,IF(om_capacity="n/a",Inputs!AQ166,om_capacity*(1+inflation_rate/100+om_capacity_escal/100)^AO$2),0) -> 0
A40: O&M capacity-based expense | C40: =C38*C39 -> 0 | D40: =D38*D39 -> 0 | E40: =E38*E39 -> 0 | F40: =F38*F39 -> 0 | G40: =G38*G39 -> 0 | H40: =H38*H39 -> 0 | I40: =I38*I39 -> 0 | J40: =J38*J39 -> 0 | ... AP40: =AP38*AP39 -> 0
A41: Variable
A42: Generation (AC-MWh) | C42: =IF(C$8=0,C$5,C$8)/1000 -> 0 | D42: =IF(D$8=0,D$5,D$8)/1000 -> 0 | E42: =IF(E$8=0,E$5,E$8)/1000 -> 0 | F42: =IF(F$8=0,F$5,F$8)/1000 -> 0 | G42: =IF(G$8=0,G$5,G$8)/1000 -> 0 | H42: =IF(H$8=0,H$5,H$8)/1000 -> 0 | I42: =IF(I$8=0,I$5,I$8)/1000 -> 0 | J42: =IF(J$8=0,J$5,J$8)/1000 -> 0 | ... AP42: =IF(AP$8=0,AP$5,AP$8)/1000 -> 0
A43: Variable Cost ($/AC-MWh) | C43: =IF(C$2<=analysis_period,IF(om_production="n/a",Inputs!D167,om_production*(1+inflation_rate/100+om_production_escal/100)^B$2),0) -> 0 | D43: =IF(D$2<=analysis_period,IF(om_production="n/a",Inputs!E167,om_production*(1+inflation_rate/100+om_production_escal/100)^C$2),0) -> 0 | E43: =IF(E$2<=analysis_period,IF(om_production="n/a",Inputs!F167,om_production*(1+inflation_rate/100+om_production_escal/100)^D$2),0) -> 0 | F43: =IF(F$2<=analysis_period,IF(om_production="n/a",Inputs!G167,om_production*(1+inflation_rate/100+om_production_escal/100)^E$2),0) -> 0 | G43: =IF(G$2<=analysis_period,IF(om_production="n/a",Inputs!H167,om_production*(1+inflation_rate/100+om_production_escal/100)^F$2),0) -> 0 | H43: =IF(H$2<=analysis_period,IF(om_production="n/a",Inputs!I167,om_production*(1+inflation_rate/100+om_production_escal/100)^G$2),0) -> 0 | I43: =IF(I$2<=analysis_period,IF(om_production="n/a",Inputs!J167,om_production*(1+inflation_rate/100+om_production_escal/100)^H$2),0) -> 0 | J43: =IF(J$2<=analysis_period,IF(om_production="n/a",Inputs!K167,om_production*(1+inflation_rate/100+om_production_escal/100)^I$2),0) -> 0 | ... AP43: =IF(AP$2<=analysis_period,IF(om_production="n/a",Inputs!AQ167,om_production*(1+inflation_rate/100+om_production_escal/100)^AO$2),0) -> 0
A44: O&M production-based expense | C44: =C42*C43 -> 0 | D44: =D42*D43 -> 0 | E44: =E42*E43 -> 0 | F44: =F42*F43 -> 0 | G44: =G42*G43 -> 0 | H44: =H42*H43 -> 0 | I44: =I42*I43 -> 0 | J44: =J42*J43 -> 0 | ... AP44: =AP42*AP43 -> 0
A45: Electricity purchase | B45: {=Inputs!C187:AQ187} -> 0 | C45: 0 | D45: 0 | E45: 0 | F45: 0 | G45: 0 | H45: 0 | I45: 0 | J45: 0 | K45: 0 | L45: 0 | M45: 0 | N45: 0 | O45: 0 | P45: 0 | Q45: 0 | R45: 0 | S45: 0 | T45: 0 | U45: 0 | V45: 0 | W45: 0 | X45: 0 | Y45: 0 | Z45: 0 | AA45: 0 | AB45: 0 | AC45: 0 | AD45: 0 | AE45: 0 | AF45: 0 | AG45: 0 | AH45: 0 | AI45: 0 | AJ45: 0 | AK45: 0 | AL45: 0 | AM45: 0 | AN45: 0 | AO45: 0 | AP45: 0
A46: Expenses Specific to Battery Systems
A47: Battery fixed | B47: {=Inputs!C189:AQ192} -> 0 | C47: 0 | D47: 0 | E47: 0 | F47: 0 | G47: 0 | H47: 0 | I47: 0 | J47: 0 | K47: 0 | L47: 0 | M47: 0 | N47: 0 | O47: 0 | P47: 0 | Q47: 0 | R47: 0 | S47: 0 | T47: 0 | U47: 0 | V47: 0 | W47: 0 | X47: 0 | Y47: 0 | Z47: 0 | AA47: 0 | AB47: 0 | AC47: 0 | AD47: 0 | AE47: 0 | AF47: 0 | AG47: 0 | AH47: 0 | AI47: 0 | AJ47: 0 | AK47: 0 | AL47: 0 | AM47: 0 | AN47: 0 | AO47: 0 | AP47: 0
A48: Battery capacity-based | B48: 0 | C48: 0 | D48: 0 | E48: 0 | F48: 0 | G48: 0 | H48: 0 | I48: 0 | J48: 0 | K48: 0 | L48: 0 | M48: 0 | N48: 0 | O48: 0 | P48: 0 | Q48: 0 | R48: 0 | S48: 0 | T48: 0 | U48: 0 | V48: 0 | W48: 0 | X48: 0 | Y48: 0 | Z48: 0 | AA48: 0 | AB48: 0 | AC48: 0 | AD48: 0 | AE48: 0 | AF48: 0 | AG48: 0 | AH48: 0 | AI48: 0 | AJ48: 0 | AK48: 0 | AL48: 0 | AM48: 0 | AN48: 0 | AO48: 0 | AP48: 0
A49: Battery variable | B49: 0 | C49: 0 | D49: 0 | E49: 0 | F49: 0 | G49: 0 | H49: 0 | I49: 0 | J49: 0 | K49: 0 | L49: 0 | M49: 0 | N49: 0 | O49: 0 | P49: 0 | Q49: 0 | R49: 0 | S49: 0 | T49: 0 | U49: 0 | V49: 0 | W49: 0 | X49: 0 | Y49: 0 | Z49: 0 | AA49: 0 | AB49: 0 | AC49: 0 | AD49: 0 | AE49: 0 | AF49: 0 | AG49: 0 | AH49: 0 | AI49: 0 | AJ49: 0 | AK49: 0 | AL49: 0 | AM49: 0 | AN49: 0 | AO49: 0 | AP49: 0
A50: Battery replacement | B50: 0 | C50: 0 | D50: 0 | E50: 0 | F50: 0 | G50: 0 | H50: 0 | I50: 0 | J50: 0 | K50: 0 | L50: 0 | M50: 0 | N50: 0 | O50: 0 | P50: 0 | Q50: 0 | R50: 0 | S50: 0 | T50: 0 | U50: 0 | V50: 0 | W50: 0 | X50: 0 | Y50: 0 | Z50: 0 | AA50: 0 | AB50: 0 | AC50: 0 | AD50: 0 | AE50: 0 | AF50: 0 | AG50: 0 | AH50: 0 | AI50: 0 | AJ50: 0 | AK50: 0 | AL50: 0 | AM50: 0 | AN50: 0 | AO50: 0 | AP50: 0
A51: Expenses Specific to Fuel Cell Systems
A52: Fuel cell fixed | B52: {=Inputs!C194:AQ198} -> 0 | C52: 0 | D52: 0 | E52: 0 | F52: 0 | G52: 0 | H52: 0 | I52: 0 | J52: 0 | K52: 0 | L52: 0 | M52: 0 | N52: 0 | O52: 0 | P52: 0 | Q52: 0 | R52: 0 | S52: 0 | T52: 0 | U52: 0 | V52: 0 | W52: 0 | X52: 0 | Y52: 0 | Z52: 0 | AA52: 0 | AB52: 0 | AC52: 0 | AD52: 0 | AE52: 0 | AF52: 0 | AG52: 0 | AH52: 0 | AI52: 0 | AJ52: 0 | AK52: 0 | AL52: 0 | AM52: 0 | AN52: 0 | AO52: 0 | AP52: 0
A53: Fuel cell capacity-based | B53: 0 | C53: 0 | D53: 0 | E53: 0 | F53: 0 | G53: 0 | H53: 0 | I53: 0 | J53: 0 | K53: 0 | L53: 0 | M53: 0 | N53: 0 | O53: 0 | P53: 0 | Q53: 0 | R53: 0 | S53: 0 | T53: 0 | U53: 0 | V53: 0 | W53: 0 | X53: 0 | Y53: 0 | Z53: 0 | AA53: 0 | AB53: 0 | AC53: 0 | AD53: 0 | AE53: 0 | AF53: 0 | AG53: 0 | AH53: 0 | AI53: 0 | AJ53: 0 | AK53: 0 | AL53: 0 | AM53: 0 | AN53: 0 | AO53: 0 | AP53: 0
A54: Fuel cell variable | B54: 0 | C54: 0 | D54: 0 | E54: 0 | F54: 0 | G54: 0 | H54: 0 | I54: 0 | J54: 0 | K54: 0 | L54: 0 | M54: 0 | N54: 0 | O54: 0 | P54: 0 | Q54: 0 | R54: 0 | S54: 0 | T54: 0 | U54: 0 | V54: 0 | W54: 0 | X54: 0 | Y54: 0 | Z54: 0 | AA54: 0 | AB54: 0 | AC54: 0 | AD54: 0 | AE54: 0 | AF54: 0 | AG54: 0 | AH54: 0 | AI54: 0 | AJ54: 0 | AK54: 0 | AL54: 0 | AM54: 0 | AN54: 0 | AO54: 0 | AP54: 0
A55: Fuel cell replacement | B55: 0 | C55: 0 | D55: 0 | E55: 0 | F55: 0 | G55: 0 | H55: 0 | I55: 0 | J55: 0 | K55: 0 | L55: 0 | M55: 0 | N55: 0 | O55: 0 | P55: 0 | Q55: 0 | R55: 0 | S55: 0 | T55: 0 | U55: 0 | V55: 0 | W55: 0 | X55: 0 | Y55: 0 | Z55: 0 | AA55: 0 | AB55: 0 | AC55: 0 | AD55: 0 | AE55: 0 | AF55: 0 | AG55: 0 | AH55: 0 | AI55: 0 | AJ55: 0 | AK55: 0 | AL55: 0 | AM55: 0 | AN55: 0 | AO55: 0 | AP55: 0
A56: Fuel cell fuel | B56: 0 | C56: 0 | D56: 0 | E56: 0 | F56: 0 | G56: 0 | H56: 0 | I56: 0 | J56: 0 | K56: 0 | L56: 0 | M56: 0 | N56: 0 | O56: 0 | P56: 0 | Q56: 0 | R56: 0 | S56: 0 | T56: 0 | U56: 0 | V56: 0 | W56: 0 | X56: 0 | Y56: 0 | Z56: 0 | AA56: 0 | AB56: 0 | AC56: 0 | AD56: 0 | AE56: 0 | AF56: 0 | AG56: 0 | AH56: 0 | AI56: 0 | AJ56: 0 | AK56: 0 | AL56: 0 | AM56: 0 | AN56: 0 | AO56: 0 | AP56: 0
A57: Fuel (CSP, generic only) | B57: {=Inputs!C200:AQ202} -> 0 | C57: 0 | D57: 0 | E57: 0 | F57: 0 | G57: 0 | H57: 0 | I57: 0 | J57: 0 | K57: 0 | L57: 0 | M57: 0 | N57: 0 | O57: 0 | P57: 0 | Q57: 0 | R57: 0 | S57: 0 | T57: 0 | U57: 0 | V57: 0 | W57: 0 | X57: 0 | Y57: 0 | Z57: 0 | AA57: 0 | AB57: 0 | AC57: 0 | AD57: 0 | AE57: 0 | AF57: 0 | AG57: 0 | AH57: 0 | AI57: 0 | AJ57: 0 | AK57: 0 | AL57: 0 | AM57: 0 | AN57: 0 | AO57: 0 | AP57: 0
A58: Biomass feedstock (Biopower only) | B58: 0 | C58: 0 | D58: 0 | E58: 0 | F58: 0 | G58: 0 | H58: 0 | I58: 0 | J58: 0 | K58: 0 | L58: 0 | M58: 0 | N58: 0 | O58: 0 | P58: 0 | Q58: 0 | R58: 0 | S58: 0 | T58: 0 | U58: 0 | V58: 0 | W58: 0 | X58: 0 | Y58: 0 | Z58: 0 | AA58: 0 | AB58: 0 | AC58: 0 | AD58: 0 | AE58: 0 | AF58: 0 | AG58: 0 | AH58: 0 | AI58: 0 | AJ58: 0 | AK58: 0 | AL58: 0 | AM58: 0 | AN58: 0 | AO58: 0 | AP58: 0
A59: Coal feedstock (Biopower only) | B59: 0 | C59: 0 | D59: 0 | E59: 0 | F59: 0 | G59: 0 | H59: 0 | I59: 0 | J59: 0 | K59: 0 | L59: 0 | M59: 0 | N59: 0 | O59: 0 | P59: 0 | Q59: 0 | R59: 0 | S59: 0 | T59: 0 | U59: 0 | V59: 0 | W59: 0 | X59: 0 | Y59: 0 | Z59: 0 | AA59: 0 | AB59: 0 | AC59: 0 | AD59: 0 | AE59: 0 | AF59: 0 | AG59: 0 | AH59: 0 | AI59: 0 | AJ59: 0 | AK59: 0 | AL59: 0 | AM59: 0 | AN59: 0 | AO59: 0 | AP59: 0
A60: Geothermal recapitalization | B60: {=Inputs!C204:AQ204} -> 0 | C60: 0 | D60: 0 | E60: 0 | F60: 0 | G60: 0 | H60: 0 | I60: 0 | J60: 0 | K60: 0 | L60: 0 | M60: 0 | N60: 0 | O60: 0 | P60: 0 | Q60: 0 | R60: 0 | S60: 0 | T60: 0 | U60: 0 | V60: 0 | W60: 0 | X60: 0 | Y60: 0 | Z60: 0 | AA60: 0 | AB60: 0 | AC60: 0 | AD60: 0 | AE60: 0 | AF60: 0 | AG60: 0 | AH60: 0 | AI60: 0 | AJ60: 0 | AK60: 0 | AL60: 0 | AM60: 0 | AN60: 0 | AO60: 0 | AP60: 0
A61: Land Lease | C61: {=IF(C$2<=analysis_period,IF(om_land_lease="n/a",total_land_area*Inputs!D$215,total_land_area*om_land_lease*(1+inflation_rate/100+om_land_lease_escal/100)^B$2),0)} -> 0 | D61: {=IF(D$2<=analysis_period,IF(om_land_lease="n/a",total_land_area*Inputs!E$215,total_land_area*om_land_lease*(1+inflation_rate/100+om_land_lease_escal/100)^C$2),0)} -> 0 | E61: {=IF(E$2<=analysis_period,IF(om_land_lease="n/a",total_land_area*Inputs!F$215,total_land_area*om_land_lease*(1+inflation_rate/100+om_land_lease_escal/100)^D$2),0)} -> 0 | F61: {=IF(F$2<=analysis_period,IF(om_land_lease="n/a",total_land_area*Inputs!G$215,total_land_area*om_land_lease*(1+inflation_rate/100+om_land_lease_escal/100)^E$2),0)} -> 0 | G61: {=IF(G$2<=analysis_period,IF(om_land_lease="n/a",total_land_area*Inputs!H$215,total_land_area*om_land_lease*(1+inflation_rate/100+om_land_lease_escal/100)^F$2),0)} -> 0 | H61: {=IF(H$2<=analysis_period,IF(om_land_lease="n/a",total_land_area*Inputs!I$215,total_land_area*om_land_lease*(1+inflation_rate/100+om_land_lease_escal/100)^G$2),0)} -> 0 | I61: {=IF(I$2<=analysis_period,IF(om_land_lease="n/a",total_land_area*Inputs!J$215,total_land_area*om_land_lease*(1+inflation_rate/100+om_land_lease_escal/100)^H$2),0)} -> 0 | J61: {=IF(J$2<=analysis_period,IF(om_land_lease="n/a",total_land_area*Inputs!K$215,total_land_area*om_land_lease*(1+inflation_rate/100+om_land_lease_escal/100)^I$2),0)} -> 0 | ... AP61: {=IF(AP$2<=analysis_period,IF(om_land_lease="n/a",total_land_area*Inputs!AQ$215,total_land_area*om_land_lease*(1+inflation_rate/100+om_land_lease_escal/100)^AO$2),0)} -> 0
A62: Property Tax | C62: =C32*property_tax_rate/100 -> 0 | D62: =D32*property_tax_rate/100 -> 0 | E62: =E32*property_tax_rate/100 -> 0 | F62: =F32*property_tax_rate/100 -> 0 | G62: =G32*property_tax_rate/100 -> 0 | H62: =H32*property_tax_rate/100 -> 0 | I62: =I32*property_tax_rate/100 -> 0 | J62: =J32*property_tax_rate/100 -> 0 | ... AP62: =AP32*property_tax_rate/100 -> 0
A63: Insurance | C63: =IF(C$2<=analysis_period,total_installed_cost*insurance_rate/100*(1+inflation_rate/100)^B$2,0) -> 0 | D63: =IF(D$2<=analysis_period,total_installed_cost*insurance_rate/100*(1+inflation_rate/100)^C$2,0) -> 0 | E63: =IF(E$2<=analysis_period,total_installed_cost*insurance_rate/100*(1+inflation_rate/100)^D$2,0) -> 0 | F63: =IF(F$2<=analysis_period,total_installed_cost*insurance_rate/100*(1+inflation_rate/100)^E$2,0) -> 0 | G63: =IF(G$2<=analysis_period,total_installed_cost*insurance_rate/100*(1+inflation_rate/100)^F$2,0) -> 0 | H63: =IF(H$2<=analysis_period,total_installed_cost*insurance_rate/100*(1+inflation_rate/100)^G$2,0) -> 0 | I63: =IF(I$2<=analysis_period,total_installed_cost*insurance_rate/100*(1+inflation_rate/100)^H$2,0) -> 0 | J63: =IF(J$2<=analysis_period,total_installed_cost*insurance_rate/100*(1+inflation_rate/100)^I$2,0) -> 0 | ... AP63: =IF(AP$2<=analysis_period,total_installed_cost*insurance_rate/100*(1+inflation_rate/100)^AO$2,0) -> 0
A64: Total Expenses | C64: =C$36+C$40+C$44+C$45+SUM(C47:C50)+SUM(C52:C63) -> 0 | D64: =D$36+D$40+D$44+D$45+SUM(D47:D50)+SUM(D52:D63) -> 0 | E64: =E$36+E$40+E$44+E$45+SUM(E47:E50)+SUM(E52:E63) -> 0 | F64: =F$36+F$40+F$44+F$45+SUM(F47:F50)+SUM(F52:F63) -> 0 | G64: =G$36+G$40+G$44+G$45+SUM(G47:G50)+SUM(G52:G63) -> 0 | H64: =H$36+H$40+H$44+H$45+SUM(H47:H50)+SUM(H52:H63) -> 0 | I64: =I$36+I$40+I$44+I$45+SUM(I47:I50)+SUM(I52:I63) -> 0 | J64: =J$36+J$40+J$44+J$45+SUM(J47:J50)+SUM(J52:J63) -> 0 | ... AP64: =AP$36+AP$40+AP$44+AP$45+SUM(AP47:AP50)+SUM(AP52:AP63) -> 0
A66: EBITDA | C66: =C$30-C$64 -> 0 | D66: =D$30-D$64 -> 0 | E66: =E$30-E$64 -> 0 | F66: =F$30-F$64 -> 0 | G66: =G$30-G$64 -> 0 | H66: =H$30-H$64 -> 0 | I66: =I$30-I$64 -> 0 | J66: =J$30-J$64 -> 0 | ... AP66: =AP$30-AP$64 -> 0
A68: Cash Flow: Project
A69: Cash Flows from Operating Activities
A70: EBITDA | C70: =C66 -> 0 | D70: =D66 -> 0 | E70: =E66 -> 0 | F70: =F66 -> 0 | G70: =G66 -> 0 | H70: =H66 -> 0 | I70: =I66 -> 0 | J70: =J66 -> 0 | ... AP70: =AP66 -> 0
A71: Plus: PBI (if not included above)
A72: =A24 -> Federal | C72: =IF(pbi_fed_for_ds="Yes",0,C580) -> 0 | D72: =IF(pbi_fed_for_ds="Yes",0,D580) -> 0 | E72: =IF(pbi_fed_for_ds="Yes",0,E580) -> 0 | F72: =IF(pbi_fed_for_ds="Yes",0,F580) -> 0 | G72: =IF(pbi_fed_for_ds="Yes",0,G580) -> 0 | H72: =IF(pbi_fed_for_ds="Yes",0,H580) -> 0 | I72: =IF(pbi_fed_for_ds="Yes",0,I580) -> 0 | J72: =IF(pbi_fed_for_ds="Yes",0,J580) -> 0 | ... AP72: =IF(pbi_fed_for_ds="Yes",0,AP580) -> 0
A73: =A25 -> State | C73: =IF(pbi_sta_for_ds="Yes",0,C584) -> 0 | D73: =IF(pbi_sta_for_ds="Yes",0,D584) -> 0 | E73: =IF(pbi_sta_for_ds="Yes",0,E584) -> 0 | F73: =IF(pbi_sta_for_ds="Yes",0,F584) -> 0 | G73: =IF(pbi_sta_for_ds="Yes",0,G584) -> 0 | H73: =IF(pbi_sta_for_ds="Yes",0,H584) -> 0 | I73: =IF(pbi_sta_for_ds="Yes",0,I584) -> 0 | J73: =IF(pbi_sta_for_ds="Yes",0,J584) -> 0 | ... AP73: =IF(pbi_sta_for_ds="Yes",0,AP584) -> 0
A74: =A26 -> Utility | C74: =IF(pbi_uti_for_ds="Yes",0,C588) -> 0 | D74: =IF(pbi_uti_for_ds="Yes",0,D588) -> 0 | E74: =IF(pbi_uti_for_ds="Yes",0,E588) -> 0 | F74: =IF(pbi_uti_for_ds="Yes",0,F588) -> 0 | G74: =IF(pbi_uti_for_ds="Yes",0,G588) -> 0 | H74: =IF(pbi_uti_for_ds="Yes",0,H588) -> 0 | I74: =IF(pbi_uti_for_ds="Yes",0,I588) -> 0 | J74: =IF(pbi_uti_for_ds="Yes",0,J588) -> 0 | ... AP74: =IF(pbi_uti_for_ds="Yes",0,AP588) -> 0
A75: =A27 -> Other | C75: =IF(pbi_oth_for_ds="Yes",0,C592) -> 0 | D75: =IF(pbi_oth_for_ds="Yes",0,D592) -> 0 | E75: =IF(pbi_oth_for_ds="Yes",0,E592) -> 0 | F75: =IF(pbi_oth_for_ds="Yes",0,F592) -> 0 | G75: =IF(pbi_oth_for_ds="Yes",0,G592) -> 0 | H75: =IF(pbi_oth_for_ds="Yes",0,H592) -> 0 | I75: =IF(pbi_oth_for_ds="Yes",0,I592) -> 0 | J75: =IF(pbi_oth_for_ds="Yes",0,J592) -> 0 | ... AP75: =IF(pbi_oth_for_ds="Yes",0,AP592) -> 0
A76: Total | C76: =SUM(C72:C75) -> 0 | D76: =SUM(D72:D75) -> 0 | E76: =SUM(E72:E75) -> 0 | F76: =SUM(F72:F75) -> 0 | G76: =SUM(G72:G75) -> 0 | H76: =SUM(H72:H75) -> 0 | I76: =SUM(I72:I75) -> 0 | J76: =SUM(J72:J75) -> 0 | ... AP76: =SUM(AP72:AP75) -> 0
A77: Plus: Interest earned on reserve accounts | B77: 0 | C77: =C740 -> 0 | D77: =D740 -> 0 | E77: =E740 -> 0 | F77: =F740 -> 0 | G77: =G740 -> 0 | H77: =H740 -> 0 | I77: =I740 -> 0 | J77: =J740 -> 0 | ... AP77: =AP740 -> 0
A78: Less: Debt interest payment | B78: 0 | C78: =-C599 -> 0 | D78: =-D599 -> 0 | E78: =-E599 -> 0 | F78: =-F599 -> 0 | G78: =-G599 -> 0 | H78: =-H599 -> 0 | I78: =-I599 -> 0 | J78: =-J599 -> 0 | ... AP78: =-AP599 -> 0
A79: Total | B79: =B70+B76+B77+B78 -> 0 | C79: =C70+C76+C77+C78 -> 0 | D79: =D70+D76+D77+D78 -> 0 | E79: =E70+E76+E77+E78 -> 0 | F79: =F70+F76+F77+F78 -> 0 | G79: =G70+G76+G77+G78 -> 0 | H79: =H70+H76+H77+H78 -> 0 | I79: =I70+I76+I77+I78 -> 0 | ... AP79: =AP70+AP76+AP77+AP78 -> 0
A81: Cash Flows from Investing Activities
A82: Capital Costs
A83: Total installed cost | B83: =-total_installed_cost -> 0
A84: Debt closing costs | B84: =-(cost_debt_closing) -> 0
A85: Debt up-front fee | B85: =-CostDebtUpfront -> 0
A86: Financing cost | B86: =-cost_other_financing -> 0
A87: Construction financing | B87: =-Inputs!I85 -> 0
A88: Total IBI | B88: =C561+C567 -> 0
A89: Total CBI | B89: =C574 -> 0
A90: Total purchase of property | B90: =SUM(B83:B89) -> 0
A91: Reserve Accounts (Increase)/Decrease
A92: Debt service reserve | B92: =-B626-B627 -> 0 | C92: =-C626-C627 -> 0 | D92: =-D626-D627 -> 0 | E92: =-E626-E627 -> 0 | F92: =-F626-F627 -> 0 | G92: =-G626-G627 -> 0 | H92: =-H626-H627 -> 0 | I92: =-I626-I627 -> 0 | ... AP92: =-AP626-AP627 -> 0
A93: Working capital reserve | B93: =-B632-B633 -> 0 | C93: =-C632-C633 -> 0 | D93: =-D632-D633 -> 0 | E93: =-E632-E633 -> 0 | F93: =-F632-F633 -> 0 | G93: =-G632-G633 -> 0 | H93: =-H632-H633 -> 0 | I93: =-I632-I633 -> 0 | ... AP93: =-AP632-AP633 -> 0
A94: Receivables reserve | B94: =-B638-B639 -> 0 | C94: =-C638-C639 -> 0 | D94: =-D638-D639 -> 0 | E94: =-E638-E639 -> 0 | F94: =-F638-F639 -> 0 | G94: =-G638-G639 -> 0 | H94: =-H638-H639 -> 0 | I94: =-I638-I639 -> 0 | ... AP94: =-AP638-AP639 -> 0
A95: Major equipment reserve 1 | B95: =-B644-B645 -> 0 | C95: =-C644-C645 -> 0 | D95: =-D644-D645 -> 0 | E95: =-E644-E645 -> 0 | F95: =-F644-F645 -> 0 | G95: =-G644-G645 -> 0 | H95: =-H644-H645 -> 0 | I95: =-I644-I645 -> 0 | ... AP95: =-AP644-AP645 -> 0
A96: Major equipment reserve 2 | B96: =-B676-B677 -> 0 | C96: =-C676-C677 -> 0 | D96: =-D676-D677 -> 0 | E96: =-E676-E677 -> 0 | F96: =-F676-F677 -> 0 | G96: =-G676-G677 -> 0 | H96: =-H676-H677 -> 0 | I96: =-I676-I677 -> 0 | ... AP96: =-AP676-AP677 -> 0
A97: Major equipment reserve 3 | B97: =-B708-B709 -> 0 | C97: =-C708-C709 -> 0 | D97: =-D708-D709 -> 0 | E97: =-E708-E709 -> 0 | F97: =-F708-F709 -> 0 | G97: =-G708-G709 -> 0 | H97: =-H708-H709 -> 0 | I97: =-I708-I709 -> 0 | ... AP97: =-AP708-AP709 -> 0
A98: Total | B98: =SUM(B92:B97) -> 0 | C98: =SUM(C92:C97) -> 0 | D98: =SUM(D92:D97) -> 0 | E98: =SUM(E92:E97) -> 0 | F98: =SUM(F92:F97) -> 0 | G98: =SUM(G92:G97) -> 0 | H98: =SUM(H92:H97) -> 0 | I98: =SUM(I92:I97) -> 0 | ... AP98: =SUM(AP92:AP97) -> 0
A99: Reserve Capital Spending
A100: Major equipment spending 1 | B100: =B645 -> 0 | C100: =C645 -> 0 | D100: =D645 -> 0 | E100: =E645 -> 0 | F100: =F645 -> 0 | G100: =G645 -> 0 | H100: =H645 -> 0 | I100: =I645 -> 0 | ... AP100: =AP645 -> 0
A101: Major equipment spending 2 | B101: =B677 -> 0 | C101: =C677 -> 0 | D101: =D677 -> 0 | E101: =E677 -> 0 | F101: =F677 -> 0 | G101: =G677 -> 0 | H101: =H677 -> 0 | I101: =I677 -> 0 | ... AP101: =AP677 -> 0
A102: Major equipment spending 3 | B102: =B709 -> 0 | C102: =C709 -> 0 | D102: =D709 -> 0 | E102: =E709 -> 0 | F102: =F709 -> 0 | G102: =G709 -> 0 | H102: =H709 -> 0 | I102: =I709 -> 0 | ... AP102: =AP709 -> 0
A103: Total | B103: =SUM(B100:B102) -> 0 | C103: =SUM(C100:C102) -> 0 | D103: =SUM(D100:D102) -> 0 | E103: =SUM(E100:E102) -> 0 | F103: =SUM(F100:F102) -> 0 | G103: =SUM(G100:G102) -> 0 | H103: =SUM(H100:H102) -> 0 | I103: =SUM(I100:I102) -> 0 | ... AP103: =SUM(AP100:AP102) -> 0
A104: Total | B104: =B$90+B$98+B$103 -> 0 | C104: =C$98+C$103 -> 0 | D104: =D$98+D$103 -> 0 | E104: =E$98+E$103 -> 0 | F104: =F$98+F$103 -> 0 | G104: =G$98+G$103 -> 0 | H104: =H$98+H$103 -> 0 | I104: =I$98+I$103 -> 0 | J104: =J$98+J$103 -> 0 | ... AP104: =AP$98+AP$103 -> 0
A106: Cash Flows from Financing Activities
A107: Incentives and size of debt
A108: Size of debt | B108: =$B$613 -> 0
...

Sheet Depreciation Schedules
A1: Depreciation Schedules (Half Year)
A2: Year | B2: 5-yr MACRS | C2: 15-yr MACRS | D2: 5-yr SL | E2: 15-yr SL | F2: 20-yr SL | G2: 39-yr SL
A3: 1 | B3: 20 | C3: 5 | D3: 10 | E3: 3.33 | F3: 2.5 | G3: =2.56410256410256*0.5 -> 1.2820513
A4: 2 | B4: 32 | C4: 9.5 | D4: 20 | E4: 6.67 | F4: 5 | G4: 2.5641026
A5: 3 | B5: 19.2 | C5: 8.55 | D5: 20 | E5: 6.67 | F5: 5 | G5: 2.5641026
A6: 4 | B6: 11.52 | C6: 7.7 | D6: 20 | E6: 6.67 | F6: 5 | G6: 2.5641026
A7: 5 | B7: 11.52 | C7: 6.93 | D7: 20 | E7: 6.67 | F7: 5 | G7: 2.5641026
A8: 6 | B8: 5.76 | C8: 6.23 | D8: 10 | E8: 6.67 | F8: 5 | G8: 2.5641026
A9: 7 | B9: 0 | C9: 5.9 | D9: 0 | E9: 6.67 | F9: 5 | G9: 2.5641026
A10: 8 | B10: 0 | C10: 5.9 | D10: 0 | E10: 6.67 | F10: 5 | G10: 2.5641026
A11: 9 | B11: 0 | C11: 5.91 | D11: 0 | E11: 6.67 | F11: 5 | G11: 2.5641026
A12: 10 | B12: 0 | C12: 5.9 | D12: 0 | E12: 6.67 | F12: 5 | G12: 2.5641026
A13: 11 | B13: 0 | C13: 5.91 | D13: 0 | E13: 6.67 | F13: 5 | G13: 2.5641026
A14: 12 | B14: 0 | C14: 5.9 | D14: 0 | E14: 6.66 | F14: 5 | G14: 2.5641026
A15: 13 | B15: 0 | C15: 5.91 | D15: 0 | E15: 6.67 | F15: 5 | G15: 2.5641026
... A41: 39 | B41: 0 | C41: 0 | D41: 0 | E41: 0 | F41: 0 | G41: 2.5641026
A42: 40 | B42: 0 | C42: 0 | D42: 0 | E42: 0 | F42: 0 | G42: =2.56410256410256*0.5 -> 1.2820513
A43: For additional information on depreciation schedules, see IRS publication 946.
A44: http://www.irs.gov/pub/irs-pdf/p946.pdf
A45: * Note custom schedule is defined on Inputs sheet around Row 180
