Workbook
Name analysis_period: Inputs!$C$47
Name annual_fuel_usage: Inputs!$C$19
Name AnnualLandLease: Inputs!$D$225
Name AnnualOMCapacity: Inputs!$D$176
Name AnnualOMFixed: Inputs!$D$175
Name AnnualOMProduction: Inputs!$D$177
Name AnnualPBIFederal: Inputs!$D$189
Name AnnualPBIOther: Inputs!$D$192
Name AnnualPBIState: Inputs!$D$190
Name AnnualPBIUtility: Inputs!$D$191
Name AnnualPTCFederal: Inputs!$D$194
Name AnnualPTCState: Inputs!$D$195
Name AnnualTaxFederal: Inputs!$C$180
Name AnnualTaxState: Inputs!$C$179
Name batt_annual_discharge_energy: Inputs!$C$166
Name cbi_fed_amount: Inputs!$C$138
Name cbi_fed_deprbas_fed: Inputs!$G$138
Name cbi_fed_deprbas_sta: Inputs!$H$138
Name cbi_fed_maxvalue: Inputs!$D$138
Name cbi_fed_tax_fed: Inputs!$E$138
Name cbi_fed_tax_sta: Inputs!$F$138
Name cbi_oth_amount: Inputs!$C$141
Name cbi_oth_deprbas_fed: Inputs!$G$141
Name cbi_oth_deprbas_sta: Inputs!$H$141
Name cbi_oth_maxvalue: Inputs!$D$141
Name cbi_oth_tax_fed: Inputs!$E$141
Name cbi_oth_tax_sta: Inputs!$F$141
Name cbi_sta_amount: Inputs!$C$139
Name cbi_sta_deprbas_fed: Inputs!$G$139
Name cbi_sta_deprbas_sta: Inputs!$H$139
Name cbi_sta_maxvalue: Inputs!$D$139
Name cbi_sta_tax_fed: Inputs!$E$139
Name cbi_sta_tax_sta: Inputs!$F$139
Name cbi_uti_amount: Inputs!$C$140
Name cbi_uti_deprbas_fed: Inputs!$G$140
Name cbi_uti_deprbas_sta: Inputs!$H$140
Name cbi_uti_maxvalue: Inputs!$D$140
Name cbi_uti_tax_fed: Inputs!$E$140
Name cbi_uti_tax_sta: Inputs!$F$140
Name cf_annual_cost_lcos: Inputs!$C$222
Name cf_annual_discharge_lcos: Inputs!$C$223
Name cf_battery_replacement_cost: Inputs!$C$202
Name cf_capacity_payment: Inputs!$C$171
Name cf_curtailment_value: Inputs!$C$172
Name cf_disbursement_debtservice: Inputs!$C$217
Name cf_energy_net: Inputs!$C$164
Name cf_energy_purchases: Inputs!$C$163
Name cf_energy_sales: Inputs!$C$162
Name cf_energy_value: Inputs!$C$170
Name cf_energy_without_battery: Inputs!$C$165
Name cf_fuelcell_replacement_cost: Inputs!$C$207
Name cf_funding_debtservice: Inputs!$C$216
Name cf_om_capacity1_expense: Inputs!$C$200
Name cf_om_capacity2_expense: Inputs!$C$205
Name cf_om_fixed1_expense: Inputs!$C$199
Name cf_om_fixed2_expense: Inputs!$C$204
Name cf_om_fuel_expense: Inputs!$C$210
Name cf_om_opt_fuel_1_expense: Inputs!$C$211
Name cf_om_opt_fuel_2_expense: Inputs!$C$212
Name cf_om_production1_expense: Inputs!$C$201

Sheet Inputs
B1: Partnership Flip Inputs
B2: SYSTEM DESIGN | E2: KEY
B3: Nameplate capacity (kW) | C3: 0 | E3: Calculated
E4: Input from SAM
B5: SYSTEM COSTS | E5: Annual values from SAM
B6: Total installed cost ($) | C6: 0 | E6: Value depends on option in SAM
B8: OPERATION AND MAINTENANCE COSTS | E8: METRICS
B9: Fixed annual cost ($/yr) | C9: 0 | E9: PPA price, year 1 (¢/kWh) | F9: ='Cash Flow'!C16 -> 0
B10: Escalation (% above inflation) | C10: 0 | E10: PPA price escalation (%/yr) | F10: =ppa_escalation -> 0
B11: Fixed cost by capacity ($/kW-yr) | C11: 0 | E11: Levelized PPA price nominal (¢/kWh) | F11: ='Cash Flow'!B152 -> 0
B12: Escalation (% above inflation) | C12: 0 | E12: LCOE, nominal (¢/kWh) | F12: ='Cash Flow'!B148 -> 0
B13: Variable cost by generation ($/MWh) | C13: 0 | E13: Investor IRR (%) | F13: =HLOOKUP(IF(PPAPriceInput="Calculated",flip_actual_year,F14),'Cash Flow'!B2:AP202,201) -> 0
B14: Escalation (% above inflation) | C14: 0 | E14: Investor IRR year | F14: =flip_actual_year -> 0
E15: Investor IRR at end of project (%) | F15: =HLOOKUP(analysis_period,'Cash Flow'!B2:AP202,201) -> 0
E16: Investor NPV | F16: ='Cash Flow'!B205 -> 0
B17: FUEL COSTS (CSP, GENERIC, AND BIOPOWER SYSTEMS ONLY) | E17: Developer IRR at end of project (%) | F17: =HLOOKUP(analysis_period,'Cash Flow'!B2:AP184,183) -> 0
B18: Fuel (CSP and generic system only) | E18: Developer NPV | F18: ='Cash Flow'!B186 -> 0
B19: Annual usage (kWh) | C19: 0 | E19: Total capital cost ($) | F19: =-'Cash Flow'!B105 -> 0
B20: Heat rate (MMBtu/MWh) | C20: 0 | E20: Equity ($) | F20: =F19-F21 -> 0
B21: Cost ($/MMBtu) | C21: 0 | E21: Size of debt ($) | F21: ='Cash Flow'!B645 -> 0
B22: Escalation (%/year above inflation) | C22: 0 | E22: Minimum debt service coverage ratio | F22: ='Cash Flow'!B665 -> 0
E23: Debt fraction (%) | F23: =F21/F19*100 -> #DIV/0!
B24: LAND LEASE
B25: Land area estimate (acres) | C25: 0
B26: Annual land lease cost ($/acre) | C26: 0
B27: Land lease escalation rate (% above inflation) | C27: 0
B29: FINANCIAL PARAMETERS
B30: Solution Mode
B31: Tax investor IRR target | C31: 0
B32: Actual flip year | C32: 0
B33: Target year | C33: 0
B34: PPA price ($/kWh) | C34: Calculated
B35: PPA priced escalation (%/year) | C35: 0
B36: PPA price is modified by TOD multipliers | C36: No
B37: Equity Flip Structure | D37: Developer share
B38: Tax investor share of equity (%) | C38: 0 | D38: =100-C38 -> 100
B39: Tax investor share of project cash pre-flip (%) | C39: 0 | D39: =100-C39 -> 100
B40: Tax investor share of project cash post-flip (%) | C40: 0 | D40: =100-C40 -> 100
B41: Tax investor share of tax benefits pre-flip (%) | C41: 0 | D41: =100-C41 -> 100
B42: Tax investor share of tax benefits post-flip (%) | C42: 0 | D42: =100-C42 -> 100
B43: Developer Capital Recovery (All Equity Only)
B44: Method | C44: Full capital recovery
B45: Duration (years, 40 max)
B46: Analysis Parameters
B47: Analysis period (years, 40 max) | C47: 0
B48: Inflation rate (%/year) | C48: 0
B49: Real discount rate (%/year) | C49: 0
B50: Nominal discount rate (%/year) | C50: =((inflation_rate/100+1)*(real_discount_rate/100+1)-1)*100 -> 0
B51: Tax and Insurance Rates
B52: Federal income tax rate in Year 1 (%/year) | C52: =AnnualTaxFederal -> 0
B53: State income tax rate in Year 1 (%/year) | C53: =AnnualTaxState -> 0
B54: Sales tax (% of total direct cost) | C54: 0
B55: Insurance rate (annual, % of installed cost) | C55: 0
B56: Property Tax
B57: Assessed percentage (% of total installed cost) | C57: 0
B58: Assesed value ($) | C58: =total_installed_cost*prop_tax_cost_assessed_percent/100 -> 0
B59: Annual decline (%/year) | C59: 0
B60: Property tax rate (%/year) | C60: 0
B61: Salvage Value
B62: Net salvage value (% of total installed cost) | C62: 0
B63: End of analysis period value ($) | C63: =total_installed_cost*salvage_percentage/100 -> 0
B65: PROJECT TERM DEBT
B66: Debt sizing and payment schedule
B67: Debt percent (%) ("Calculated" for sculpted payments) | C67: Calculated
B68: Size of debt ($) ("N/A" for sculpted payments) | C68: N/A
B69: Debt service coverage ratio ("Calculated" for mortgage style) | C69: 0
B70: Limit debt fraction (for sculpted payments only) | C70: No
B71: Maximum debt percent (%) (for sculpted payments only) | C71: 100
B72: Annual payment schedule (for mortgage style debt only) | C72: Equal payments
B73: Debt Parameters
B74: Tenor (years) | C74: 0
B75: Moratorium (years) | C75: 0
B76: Annual all-in interest rate (%) | C76: 0
B77: Debt closing costs ($) | C77: 0
B78: Up-front fee (% of total debt) | C78: 0
B79: Up-front fee amount ($, from SAM results) | C79: 0
B81: COST OF ACQUIRING FINANCING
B82: Equity closing cost ($) | C82: 0
B83: Other financing cost ($) | C83: 0
B84: Development fee (%) | C84: 0
B85: Development fee ($) | C85: =cost_dev_fee_percent/100*total_installed_cost -> 0
B86: Tax on development fee in Year 1 ($) | C86: =C85*(federal_tax_rate/100*(1-state_tax_rate/100)+state_tax_rate/100) -> 0
B88: CONSTRUCTION FINANCING
B89: Total construction financing cost ($) | C89: 0
B91: CONSTRUCTION FINANCING CALCULATION (provided here for reference, only total financing cost above is input to cash flow)
C92: Percent of installed cost | D92: Up-front fee (% of principal) | E92: Months prior to operation | F92: Annual interest rate (%) | G92: Principal | H92: Interest | I92: Total construction financing cost
B93: Loan 1 | C93: 0 | D93: 0 | E93: 0 | F93: 0 | G93: =C93/100*total_installed_cost -> 0 | H93: =G93*F93/100*E93/12*0.5 -> 0 | I93: =H93+D93/100*G93 -> 0
B94: Loan 2 | C94: 0 | D94: 0 | E94: 0 | F94: 0 | G94: =C94/100*total_installed_cost -> 0 | H94: =G94*F94/100*E94/12*0.5 -> 0 | I94: =H94+D94/100*G94 -> 0
B95: Loan 3 | C95: 0 | D95: 0 | E95: 0 | F95: 0 | G95: =C95/100*total_installed_cost -> 0 | H95: =G95*F95/100*E95/12*0.5 -> 0 | I95: =H95+D95/100*G95 -> 0
B96: Loan 4 | C96: 0 | D96: 0 | E96: 0 | F96: 0 | G96: =C96/100*total_installed_cost -> 0 | H96: =G96*F96/100*E96/12*0.5 -> 0 | I96: =H96+D96/100*G96 -> 0
B97: Loan 5 | C97: 0 | D97: 0 | E97: 0 | F97: 0 | G97: =C97/100*total_installed_cost -> 0 | H97: =G97*F97/100*E97/12*0.5 -> 0 | I97: =H97+D97/100*G97 -> 0
B98: Totals: | G98: =SUM(G93:G97) -> 0 | H98: =SUM(H93:H97) -> 0 | I98: =SUM(I93:I97) -> 0
B100: RESERVE ACCOUNTS
B101: Interest on reserves (%/year) | C101: 0
B102: Working capital reserve (months of operating costs) | C102: 0
B103: Debt service reserve account (months of P&I payments) | C103: 0
B104: Receivables reserve | C104: 0
B105: Major equipment replacement reserve accounts | C105: Replacement cost ($/W) | D105: Year 1 dollars | E105: Replacement frequency (years)
B106: Replacement reserve 1 | C106: 0 | D106: =C106*system_capacity*1000 -> 0 | E106: 0
B107: Replacement reserve 2 | C107: 0 | D107: =C107*system_capacity*1000 -> 0 | E107: 0
...

Sheet Cash Flow
A1: Partnership Flip Cash Flow
A2: Operating Year | B2: 0 | C2: =IF(B2="","",IF(B2+1<=analysis_period,B2+1,"")) | D2: =IF(C2="","",IF(C2+1<=analysis_period,C2+1,"")) | E2: =IF(D2="","",IF(D2+1<=analysis_period,D2+1,"")) | F2: =IF(E2="","",IF(E2+1<=analysis_period,E2+1,"")) | G2: =IF(F2="","",IF(F2+1<=analysis_period,F2+1,"")) | H2: =IF(G2="","",IF(G2+1<=analysis_period,G2+1,"")) | I2: =IF(H2="","",IF(H2+1<=analysis_period,H2+1,"")) | J2: =IF(I2="","",IF(I2+1<=analysis_period,I2+1,"")) | ... AP2: =IF(AO2="","",IF(AO2+1<=analysis_period,AO2+1,""))
A4: Energy
A5: Electricity to grid (AC kWh) | B5: {=Inputs!C162:AQ163} -> 0 | C5: 0 | D5: 0 | E5: 0 | F5: 0 | G5: 0 | H5: 0 | I5: 0 | J5: 0 | K5: 0 | L5: 0 | M5: 0 | N5: 0 | O5: 0 | P5: 0 | Q5: 0 | R5: 0 | S5: 0 | T5: 0 | U5: 0 | V5: 0 | W5: 0 | X5: 0 | Y5: 0 | Z5: 0 | AA5: 0 | AB5: 0 | AC5: 0 | AD5: 0 | AE5: 0 | AF5: 0 | AG5: 0 | AH5: 0 | AI5: 0 | AJ5: 0 | AK5: 0 | AL5: 0 | AM5: 0 | AN5: 0 | AO5: 0 | AP5: 0
A6: Electricity from grid (AC kWh) | B6: 0 | C6: 0 | D6: 0 | E6: 0 | F6: 0 | G6: 0 | H6: 0 | I6: 0 | J6: 0 | K6: 0 | L6: 0 | M6: 0 | N6: 0 | O6: 0 | P6: 0 | Q6: 0 | R6: 0 | S6: 0 | T6: 0 | U6: 0 | V6: 0 | W6: 0 | X6: 0 | Y6: 0 | Z6: 0 | AA6: 0 | AB6: 0 | AC6: 0 | AD6: 0 | AE6: 0 | AF6: 0 | AG6: 0 | AH6: 0 | AI6: 0 | AJ6: 0 | AK6: 0 | AL6: 0 | AM6: 0 | AN6: 0 | AO6: 0 | AP6: 0
A7: Electricity to grid net (AC kWh) | B7: =SUM(B5:B6) -> 0 | C7: =SUM(C5:C6) -> 0 | D7: =SUM(D5:D6) -> 0 | E7: =SUM(E5:E6) -> 0 | F7: =SUM(F5:F6) -> 0 | G7: =SUM(G5:G6) -> 0 | H7: =SUM(H5:H6) -> 0 | I7: =SUM(I5:I6) -> 0 | ... AP7: =SUM(AP5:AP6) -> 0
A8: Electricity generated without storage (AC kWh) | B8: {=Inputs!C165:AQ167} -> 0 | C8: 0 | D8: 0 | E8: 0 | F8: 0 | G8: 0 | H8: 0 | I8: 0 | J8: 0 | K8: 0 | L8: 0 | M8: 0 | N8: 0 | O8: 0 | P8: 0 | Q8: 0 | R8: 0 | S8: 0 | T8: 0 | U8: 0 | V8: 0 | W8: 0 | X8: 0 | Y8: 0 | Z8: 0 | AA8: 0 | AB8: 0 | AC8: 0 | AD8: 0 | AE8: 0 | AF8: 0 | AG8: 0 | AH8: 0 | AI8: 0 | AJ8: 0 | AK8: 0 | AL8: 0 | AM8: 0 | AN8: 0 | AO8: 0 | AP8: 0
A9: Battery annual energy discharged (AC kWh) | B9: 0 | C9: 0 | D9: 0 | E9: 0 | F9: 0 | G9: 0 | H9: 0 | I9: 0 | J9: 0 | K9: 0 | L9: 0 | M9: 0 | N9: 0 | O9: 0 | P9: 0 | Q9: 0 | R9: 0 | S9: 0 | T9: 0 | U9: 0 | V9: 0 | W9: 0 | X9: 0 | Y9: 0 | Z9: 0 | AA9: 0 | AB9: 0 | AC9: 0 | AD9: 0 | AE9: 0 | AF9: 0 | AG9: 0 | AH9: 0 | AI9: 0 | AJ9: 0 | AK9: 0 | AL9: 0 | AM9: 0 | AN9: 0 | AO9: 0 | AP9: 0
A10: Fuel cell annual energy discharged (AC kWh) | B10: 0 | C10: 0 | D10: 0 | E10: 0 | F10: 0 | G10: 0 | H10: 0 | I10: 0 | J10: 0 | K10: 0 | L10: 0 | M10: 0 | N10: 0 | O10: 0 | P10: 0 | Q10: 0 | R10: 0 | S10: 0 | T10: 0 | U10: 0 | V10: 0 | W10: 0 | X10: 0 | Y10: 0 | Z10: 0 | AA10: 0 | AB10: 0 | AC10: 0 | AD10: 0 | AE10: 0 | AF10: 0 | AG10: 0 | AH10: 0 | AI10: 0 | AJ10: 0 | AK10: 0 | AL10: 0 | AM10: 0 | AN10: 0 | AO10: 0 | AP10: 0
A12: Partial Income Statement: Project
A13: Revenues
A14: PPA
A15: Net production (AC kWh) | C15: =C$5 -> 0 | D15: =D$5 -> 0 | E15: =E$5 -> 0 | F15: =F$5 -> 0 | G15: =G$5 -> 0 | H15: =H$5 -> 0 | I15: =I$5 -> 0 | J15: =J$5 -> 0 | ... AP15: =AP$5 -> 0
A16: Price (¢/kWh) | B16: {=Inputs!C169:AQ169} -> 0 | C16: 0 | D16: 0 | E16: 0 | F16: 0 | G16: 0 | H16: 0 | I16: 0 | J16: 0 | K16: 0 | L16: 0 | M16: 0 | N16: 0 | O16: 0 | P16: 0 | Q16: 0 | R16: 0 | S16: 0 | T16: 0 | U16: 0 | V16: 0 | W16: 0 | X16: 0 | Y16: 0 | Z16: 0 | AA16: 0 | AB16: 0 | AC16: 0 | AD16: 0 | AE16: 0 | AF16: 0 | AG16: 0 | AH16: 0 | AI16: 0 | AJ16: 0 | AK16: 0 | AL16: 0 | AM16: 0 | AN16: 0 | AO16: 0 | AP16: 0
A17: PPA revenue (TOD multipliers may apply) | B17: {=Inputs!C170:AQ170} -> 0 | C17: 0 | D17: 0 | E17: 0 | F17: 0 | G17: 0 | H17: 0 | I17: 0 | J17: 0 | K17: 0 | L17: 0 | M17: 0 | N17: 0 | O17: 0 | P17: 0 | Q17: 0 | R17: 0 | S17: 0 | T17: 0 | U17: 0 | V17: 0 | W17: 0 | X17: 0 | Y17: 0 | Z17: 0 | AA17: 0 | AB17: 0 | AC17: 0 | AD17: 0 | AE17: 0 | AF17: 0 | AG17: 0 | AH17: 0 | AI17: 0 | AJ17: 0 | AK17: 0 | AL17: 0 | AM17: 0 | AN17: 0 | AO17: 0 | AP17: 0
A18: Other revenue
A19: Curtailment payments | B19: {=Inputs!C171:AQ173} -> 0 | C19: 0 | D19: 0 | E19: 0 | F19: 0 | G19: 0 | H19: 0 | I19: 0 | J19: 0 | K19: 0 | L19: 0 | M19: 0 | N19: 0 | O19: 0 | P19: 0 | Q19: 0 | R19: 0 | S19: 0 | T19: 0 | U19: 0 | V19: 0 | W19: 0 | X19: 0 | Y19: 0 | Z19: 0 | AA19: 0 | AB19: 0 | AC19: 0 | AD19: 0 | AE19: 0 | AF19: 0 | AG19: 0 | AH19: 0 | AI19: 0 | AJ19: 0 | AK19: 0 | AL19: 0 | AM19: 0 | AN19: 0 | AO19: 0 | AP19: 0
A20: Capacity payments | B20: 0 | C20: 0 | D20: 0 | E20: 0 | F20: 0 | G20: 0 | H20: 0 | I20: 0 | J20: 0 | K20: 0 | L20: 0 | M20: 0 | N20: 0 | O20: 0 | P20: 0 | Q20: 0 | R20: 0 | S20: 0 | T20: 0 | U20: 0 | V20: 0 | W20: 0 | X20: 0 | Y20: 0 | Z20: 0 | AA20: 0 | AB20: 0 | AC20: 0 | AD20: 0 | AE20: 0 | AF20: 0 | AG20: 0 | AH20: 0 | AI20: 0 | AJ20: 0 | AK20: 0 | AL20: 0 | AM20: 0 | AN20: 0 | AO20: 0 | AP20: 0
A21: Thermal revenue (fuel cell only) | B21: 0 | C21: 0 | D21: 0 | E21: 0 | F21: 0 | G21: 0 | H21: 0 | I21: 0 | J21: 0 | K21: 0 | L21: 0 | M21: 0 | N21: 0 | O21: 0 | P21: 0 | Q21: 0 | R21: 0 | S21: 0 | T21: 0 | U21: 0 | V21: 0 | W21: 0 | X21: 0 | Y21: 0 | Z21: 0 | AA21: 0 | AB21: 0 | AC21: 0 | AD21: 0 | AE21: 0 | AF21: 0 | AG21: 0 | AH21: 0 | AI21: 0 | AJ21: 0 | AK21: 0 | AL21: 0 | AM21: 0 | AN21: 0 | AO21: 0 | AP21: 0
A22: Production Based Incentive (included if available for debt service)
A23: Federal | C23: =IF(pbi_fed_for_ds="Yes",C624,0) -> 0 | D23: =IF(pbi_fed_for_ds="Yes",D624,0) -> 0 | E23: =IF(pbi_fed_for_ds="Yes",E624,0) -> 0 | F23: =IF(pbi_fed_for_ds="Yes",F624,0) -> 0 | G23: =IF(pbi_fed_for_ds="Yes",G624,0) -> 0 | H23: =IF(pbi_fed_for_ds="Yes",H624,0) -> 0 | I23: =IF(pbi_fed_for_ds="Yes",I624,0) -> 0 | J23: =IF(pbi_fed_for_ds="Yes",J624,0) -> 0 | ... AP23: =IF(pbi_fed_for_ds="Yes",AP624,0) -> 0
A24: State | C24: =IF(pbi_sta_for_ds="Yes",C628,0) -> 0 | D24: =IF(pbi_sta_for_ds="Yes",D628,0) -> 0 | E24: =IF(pbi_sta_for_ds="Yes",E628,0) -> 0 | F24: =IF(pbi_sta_for_ds="Yes",F628,0) -> 0 | G24: =IF(pbi_sta_for_ds="Yes",G628,0) -> 0 | H24: =IF(pbi_sta_for_ds="Yes",H628,0) -> 0 | I24: =IF(pbi_sta_for_ds="Yes",I628,0) -> 0 | J24: =IF(pbi_sta_for_ds="Yes",J628,0) -> 0 | ... AP24: =IF(pbi_sta_for_ds="Yes",AP628,0) -> 0
A25: Utility | C25: =IF(pbi_uti_for_ds="Yes",C632,0) -> 0 | D25: =IF(pbi_uti_for_ds="Yes",D632,0) -> 0 | E25: =IF(pbi_uti_for_ds="Yes",E632,0) -> 0 | F25: =IF(pbi_uti_for_ds="Yes",F632,0) -> 0 | G25: =IF(pbi_uti_for_ds="Yes",G632,0) -> 0 | H25: =IF(pbi_uti_for_ds="Yes",H632,0) -> 0 | I25: =IF(pbi_uti_for_ds="Yes",I632,0) -> 0 | J25: =IF(pbi_uti_for_ds="Yes",J632,0) -> 0 | ... AP25: =IF(pbi_uti_for_ds="Yes",AP632,0) -> 0
A26: Other | C26: =IF(pbi_oth_for_ds="Yes",C636,0) -> 0 | D26: =IF(pbi_oth_for_ds="Yes",D636,0) -> 0 | E26: =IF(pbi_oth_for_ds="Yes",E636,0) -> 0 | F26: =IF(pbi_oth_for_ds="Yes",F636,0) -> 0 | G26: =IF(pbi_oth_for_ds="Yes",G636,0) -> 0 | H26: =IF(pbi_oth_for_ds="Yes",H636,0) -> 0 | I26: =IF(pbi_oth_for_ds="Yes",I636,0) -> 0 | J26: =IF(pbi_oth_for_ds="Yes",J636,0) -> 0 | ... AP26: =IF(pbi_oth_for_ds="Yes",AP636,0) -> 0
A27: Total PBI | C27: =SUM(C23:C26) -> 0 | D27: =SUM(D23:D26) -> 0 | E27: =SUM(E23:E26) -> 0 | F27: =SUM(F23:F26) -> 0 | G27: =SUM(G23:G26) -> 0 | H27: =SUM(H23:H26) -> 0 | I27: =SUM(I23:I26) -> 0 | J27: =SUM(J23:J26) -> 0 | ... AP27: =SUM(AP23:AP26) -> 0
A28: Salvage Value | C28: =IF(C2=analysis_period,total_installed_cost*salvage_percentage/100,0) -> 0 | D28: =IF(D2=analysis_period,total_installed_cost*salvage_percentage/100,0) -> 0 | E28: =IF(E2=analysis_period,total_installed_cost*salvage_percentage/100,0) -> 0 | F28: =IF(F2=analysis_period,total_installed_cost*salvage_percentage/100,0) -> 0 | G28: =IF(G2=analysis_period,total_installed_cost*salvage_percentage/100,0) -> 0 | H28: =IF(H2=analysis_period,total_installed_cost*salvage_percentage/100,0) -> 0 | I28: =IF(I2=analysis_period,total_installed_cost*salvage_percentage/100,0) -> 0 | J28: =IF(J2=analysis_period,total_installed_cost*salvage_percentage/100,0) -> 0 | ... AP28: =IF(AP2=analysis_period,total_installed_cost*salvage_percentage/100,0) -> 0
A29: Total Revenue | C29: =IF(C2<=analysis_period,C$17+SUM(C19:C21)+C$27+C$28,0) -> 0 | D29: =IF(D2<=analysis_period,D$17+SUM(D19:D21)+D$27+D$28,0) -> 0 | E29: =IF(E2<=analysis_period,E$17+SUM(E19:E21)+E$27+E$28,0) -> 0 | F29: =IF(F2<=analysis_period,F$17+SUM(F19:F21)+F$27+F$28,0) -> 0 | G29: =IF(G2<=analysis_period,G$17+SUM(G19:G21)+G$27+G$28,0) -> 0 | H29: =IF(H2<=analysis_period,H$17+SUM(H19:H21)+H$27+H$28,0) -> 0 | I29: =IF(I2<=analysis_period,I$17+SUM(I19:I21)+I$27+I$28,0) -> 0 | J29: =IF(J2<=analysis_period,J$17+SUM(J19:J21)+J$27+J$28,0) -> 0 | ... AP29: =IF(AP2<=analysis_period,AP$17+SUM(AP19:AP21)+AP$27+AP$28,0) -> 0
A31: Property tax net assessed value | C31: =PropertyTaxAssessedValue -> 0 | D31: =IF(D$2<=analysis_period,PropertyTaxAssessedValue*(100-(D$2-1)*prop_tax_assessed_decline)/100,0) -> 0 | E31: =IF(E$2<=analysis_period,PropertyTaxAssessedValue*(100-(E$2-1)*prop_tax_assessed_decline)/100,0) -> 0 | F31: =IF(F$2<=analysis_period,PropertyTaxAssessedValue*(100-(F$2-1)*prop_tax_assessed_decline)/100,0) -> 0 | G31: =IF(G$2<=analysis_period,PropertyTaxAssessedValue*(100-(G$2-1)*prop_tax_assessed_decline)/100,0) -> 0 | H31: =IF(H$2<=analysis_period,PropertyTaxAssessedValue*(100-(H$2-1)*prop_tax_assessed_decline)/100,0) -> 0 | I31: =IF(I$2<=analysis_period,PropertyTaxAssessedValue*(100-(I$2-1)*prop_tax_assessed_decline)/100,0) -> 0 | J31: =IF(J$2<=analysis_period,PropertyTaxAssessedValue*(100-(J$2-1)*prop_tax_assessed_decline)/100,0) -> 0 | K31: =IF(K$2<=analysis_period,PropertyTaxAssessedValue*(100-(K$2-1)*prop_tax_assessed_decline)/100,0) -> 0 | ... AP31: =IF(AP$2<=analysis_period,PropertyTaxAssessedValue*(100-(AP$2-1)*prop_tax_assessed_decline)/100,0) -> 0
A33: Operating Expenses
A34: Operation and maintenance (O&M)
A35: Fixed | C35: =IF(C$2<=analysis_period,IF(om_fixed="n/a",Inputs!D175,om_fixed*(1+inflation_rate/100+om_fixed_escal/100)^B$2),0) -> 0 | D35: =IF(D$2<=analysis_period,IF(om_fixed="n/a",Inputs!E175,om_fixed*(1+inflation_rate/100+om_fixed_escal/100)^C$2),0) -> 0 | E35: =IF(E$2<=analysis_period,IF(om_fixed="n/a",Inputs!F175,om_fixed*(1+inflation_rate/100+om_fixed_escal/100)^D$2),0) -> 0 | F35: =IF(F$2<=analysis_period,IF(om_fixed="n/a",Inputs!G175,om_fixed*(1+inflation_rate/100+om_fixed_escal/100)^E$2),0) -> 0 | G35: =IF(G$2<=analysis_period,IF(om_fixed="n/a",Inputs!H175,om_fixed*(1+inflation_rate/100+om_fixed_escal/100)^F$2),0) -> 0 | H35: =IF(H$2<=analysis_period,IF(om_fixed="n/a",Inputs!I175,om_fixed*(1+inflation_rate/100+om_fixed_escal/100)^G$2),0) -> 0 | I35: =IF(I$2<=analysis_period,IF(om_fixed="n/a",Inputs!J175,om_fixed*(1+inflation_rate/100+om_fixed_escal/100)^H$2),0) -> 0 | J35: =IF(J$2<=analysis_period,IF(om_fixed="n/a",Inputs!K175,om_fixed*(1+inflation_rate/100+om_fixed_escal/100)^I$2),0) -> 0 | ... AP35: =IF(AP$2<=analysis_period,IF(om_fixed="n/a",Inputs!AQ175,om_fixed*(1+inflation_rate/100+om_fixed_escal/100)^AO$2),0) -> 0
A36: Capacity
A37: Capacity (DC kW) | C37: =IF(C$2<=analysis_period,system_capacity,0) -> 0 | D37: =IF(D$2<=analysis_period,system_capacity,0) -> 0 | E37: =IF(E$2<=analysis_period,system_capacity,0) -> 0 | F37: =IF(F$2<=analysis_period,system_capacity,0) -> 0 | G37: =IF(G$2<=analysis_period,system_capacity,0) -> 0 | H37: =IF(H$2<=analysis_period,system_capacity,0) -> 0 | I37: =IF(I$2<=analysis_period,system_capacity,0) -> 0 | J37: =IF(J$2<=analysis_period,system_capacity,0) -> 0 | ... AP37: =IF(AP$2<=analysis_period,system_capacity,0) -> 0
A38: Fixed Cost ($/DC kW-yr) | C38: =IF(C$2<=analysis_period,IF(om_capacity="n/a",Inputs!D176,om_capacity*(1+inflation_rate/100+om_capacity_escal/100)^B$2),0) -> 0 | D38: =IF(D$2<=analysis_period,IF(om_capacity="n/a",Inputs!E176,om_capacity*(1+inflation_rate/100+om_capacity_escal/100)^C$2),0) -> 0 | E38: =IF(E$2<=analysis_period,IF(om_capacity="n/a",Inputs!F176,om_capacity*(1+inflation_rate/100+om_capacity_escal/100)^D$2),0) -> 0 | F38: =IF(F$2<=analysis_period,IF(om_capacity="n/a",Inputs!G176,om_capacity*(1+inflation_rate/100+om_capacity_escal/100)^E$2),0) -> 0 | G38: =IF(G$2<=analysis_period,IF(om_capacity="n/a",Inputs!H176,om_capacity*(1+inflation_rate/100+om_capacity_escal/100)^F$2),0) -> 0 | H38: =IF(H$2<=analysis_period,IF(om_capacity="n/a",Inputs!I176,om_capacity*(1+inflation_rate/100+om_capacity_escal/100)^G$2),0) -> 0 | I38: =IF(I$2<=analysis_period,IF(om_capacity="n/a",Inputs!J176,om_capacity*(1+inflation_rate/100+om_capacity_escal/100)^H$2),0) -> 0 | J38: =IF(J$2<=analysis_period,IF(om_capacity="n/a",Inputs!K176,om_capacity*(1+inflation_rate/100+om_capacity_escal/100)^I$2),0) -> 0 | ... AP38: =IF(AP$2<=analysis_period,IF(om_capacity="n/a",Inputs!AQ176,om_capacity*(1+inflation_rate/100+om_capacity_escal/100)^AO$2),0) -> 0
A39: O&M capacity-based expense | C39: =C37*C38 -> 0 | D39: =D37*D38 -> 0 | E39: =E37*E38 -> 0 | F39: =F37*F38 -> 0 | G39: =G37*G38 -> 0 | H39: =H37*H38 -> 0 | I39: =I37*I38 -> 0 | J39: =J37*J38 -> 0 | ... AP39: =AP37*AP38 -> 0
A40: Variable
A41: Generation (AC-MWh) | C41: =IF(C$8>0,C$8,C$5)/1000 -> 0 | D41: =IF(D$8>0,D$8,D$5)/1000 -> 0 | E41: =IF(E$8>0,E$8,E$5)/1000 -> 0 | F41: =IF(F$8>0,F$8,F$5)/1000 -> 0 | G41: =IF(G$8>0,G$8,G$5)/1000 -> 0 | H41: =IF(H$8>0,H$8,H$5)/1000 -> 0 | I41: =IF(I$8>0,I$8,I$5)/1000 -> 0 | J41: =IF(J$8>0,J$8,J$5)/1000 -> 0 | ... AP41: =IF(AP$8>0,AP$8,AP$5)/1000 -> 0
A42: Variable Cost ($/AC-MWh) | C42: =IF(C$2<=analysis_period,IF(om_production="n/a",Inputs!D177,om_production*(1+inflation_rate/100+om_production_escal/100)^B$2),0) -> 0 | D42: =IF(D$2<=analysis_period,IF(om_production="n/a",Inputs!E177,om_production*(1+inflation_rate/100+om_production_escal/100)^C$2),0) -> 0 | E42: =IF(E$2<=analysis_period,IF(om_production="n/a",Inputs!F177,om_production*(1+inflation_rate/100+om_production_escal/100)^D$2),0) -> 0 | F42: =IF(F$2<=analysis_period,IF(om_production="n/a",Inputs!G177,om_production*(1+inflation_rate/100+om_production_escal/100)^E$2),0) -> 0 | G42: =IF(G$2<=analysis_period,IF(om_production="n/a",Inputs!H177,om_production*(1+inflation_rate/100+om_production_escal/100)^F$2),0) -> 0 | H42: =IF(H$2<=analysis_period,IF(om_production="n/a",Inputs!I177,om_production*(1+inflation_rate/100+om_production_escal/100)^G$2),0) -> 0 | I42: =IF(I$2<=analysis_period,IF(om_production="n/a",Inputs!J177,om_production*(1+inflation_rate/100+om_production_escal/100)^H$2),0) -> 0 | J42: =IF(J$2<=analysis_period,IF(om_production="n/a",Inputs!K177,om_production*(1+inflation_rate/100+om_production_escal/100)^I$2),0) -> 0 | ... AP42: =IF(AP$2<=analysis_period,IF(om_production="n/a",Inputs!AQ177,om_production*(1+inflation_rate/100+om_production_escal/100)^AO$2),0) -> 0
A43: O&M production-based expense | C43: =C41*C42 -> 0 | D43: =D41*D42 -> 0 | E43: =E41*E42 -> 0 | F43: =F41*F42 -> 0 | G43: =G41*G42 -> 0 | H43: =H41*H42 -> 0 | I43: =I41*I42 -> 0 | J43: =J41*J42 -> 0 | ... AP43: =AP41*AP42 -> 0
A44: Electricity purchase (Systems with battery only) | C44: {=Inputs!D197:AQ197} -> 0 | D44: 0 | E44: 0 | F44: 0 | G44: 0 | H44: 0 | I44: 0 | J44: 0 | K44: 0 | L44: 0 | M44: 0 | N44: 0 | O44: 0 | P44: 0 | Q44: 0 | R44: 0 | S44: 0 | T44: 0 | U44: 0 | V44: 0 | W44: 0 | X44: 0 | Y44: 0 | Z44: 0 | AA44: 0 | AB44: 0 | AC44: 0 | AD44: 0 | AE44: 0 | AF44: 0 | AG44: 0 | AH44: 0 | AI44: 0 | AJ44: 0 | AK44: 0 | AL44: 0 | AM44: 0 | AN44: 0 | AO44: 0 | AP44: 0
A45: Expenses Specific to Battery Systems
A46: Battery fixed | B46: {=Inputs!C199:AQ202} -> 0 | C46: 0 | D46: 0 | E46: 0 | F46: 0 | G46: 0 | H46: 0 | I46: 0 | J46: 0 | K46: 0 | L46: 0 | M46: 0 | N46: 0 | O46: 0 | P46: 0 | Q46: 0 | R46: 0 | S46: 0 | T46: 0 | U46: 0 | V46: 0 | W46: 0 | X46: 0 | Y46: 0 | Z46: 0 | AA46: 0 | AB46: 0 | AC46: 0 | AD46: 0 | AE46: 0 | AF46: 0 | AG46: 0 | AH46: 0 | AI46: 0 | AJ46: 0 | AK46: 0 | AL46: 0 | AM46: 0 | AN46: 0 | AO46: 0 | AP46: 0
A47: Battery capacity-based | B47: 0 | C47: 0 | D47: 0 | E47: 0 | F47: 0 | G47: 0 | H47: 0 | I47: 0 | J47: 0 | K47: 0 | L47: 0 | M47: 0 | N47: 0 | O47: 0 | P47: 0 | Q47: 0 | R47: 0 | S47: 0 | T47: 0 | U47: 0 | V47: 0 | W47: 0 | X47: 0 | Y47: 0 | Z47: 0 | AA47: 0 | AB47: 0 | AC47: 0 | AD47: 0 | AE47: 0 | AF47: 0 | AG47: 0 | AH47: 0 | AI47: 0 | AJ47: 0 | AK47: 0 | AL47: 0 | AM47: 0 | AN47: 0 | AO47: 0 | AP47: 0
A48: Battery variable | B48: 0 | C48: 0 | D48: 0 | E48: 0 | F48: 0 | G48: 0 | H48: 0 | I48: 0 | J48: 0 | K48: 0 | L48: 0 | M48: 0 | N48: 0 | O48: 0 | P48: 0 | Q48: 0 | R48: 0 | S48: 0 | T48: 0 | U48: 0 | V48: 0 | W48: 0 | X48: 0 | Y48: 0 | Z48: 0 | AA48: 0 | AB48: 0 | AC48: 0 | AD48: 0 | AE48: 0 | AF48: 0 | AG48: 0 | AH48: 0 | AI48: 0 | AJ48: 0 | AK48: 0 | AL48: 0 | AM48: 0 | AN48: 0 | AO48: 0 | AP48: 0
A49: Battery replacement | B49: 0 | C49: 0 | D49: 0 | E49: 0 | F49: 0 | G49: 0 | H49: 0 | I49: 0 | J49: 0 | K49: 0 | L49: 0 | M49: 0 | N49: 0 | O49: 0 | P49: 0 | Q49: 0 | R49: 0 | S49: 0 | T49: 0 | U49: 0 | V49: 0 | W49: 0 | X49: 0 | Y49: 0 | Z49: 0 | AA49: 0 | AB49: 0 | AC49: 0 | AD49: 0 | AE49: 0 | AF49: 0 | AG49: 0 | AH49: 0 | AI49: 0 | AJ49: 0 | AK49: 0 | AL49: 0 | AM49: 0 | AN49: 0 | AO49: 0 | AP49: 0
A50: Expenses Specific to Fuel Cell Systems
A51: Fuel cell fixed | B51: {=Inputs!C204:AQ208} -> 0 | C51: 0 | D51: 0 | E51: 0 | F51: 0 | G51: 0 | H51: 0 | I51: 0 | J51: 0 | K51: 0 | L51: 0 | M51: 0 | N51: 0 | O51: 0 | P51: 0 | Q51: 0 | R51: 0 | S51: 0 | T51: 0 | U51: 0 | V51: 0 | W51: 0 | X51: 0 | Y51: 0 | Z51: 0 | AA51: 0 | AB51: 0 | AC51: 0 | AD51: 0 | AE51: 0 | AF51: 0 | AG51: 0 | AH51: 0 | AI51: 0 | AJ51: 0 | AK51: 0 | AL51: 0 | AM51: 0 | AN51: 0 | AO51: 0 | AP51: 0
A52: Fuel cell capacity-based | B52: 0 | C52: 0 | D52: 0 | E52: 0 | F52: 0 | G52: 0 | H52: 0 | I52: 0 | J52: 0 | K52: 0 | L52: 0 | M52: 0 | N52: 0 | O52: 0 | P52: 0 | Q52: 0 | R52: 0 | S52: 0 | T52: 0 | U52: 0 | V52: 0 | W52: 0 | X52: 0 | Y52: 0 | Z52: 0 | AA52: 0 | AB52: 0 | AC52: 0 | AD52: 0 | AE52: 0 | AF52: 0 | AG52: 0 | AH52: 0 | AI52: 0 | AJ52: 0 | AK52: 0 | AL52: 0 | AM52: 0 | AN52: 0 | AO52: 0 | AP52: 0
A53: Fuel cell variable | B53: 0 | C53: 0 | D53: 0 | E53: 0 | F53: 0 | G53: 0 | H53: 0 | I53: 0 | J53: 0 | K53: 0 | L53: 0 | M53: 0 | N53: 0 | O53: 0 | P53: 0 | Q53: 0 | R53: 0 | S53: 0 | T53: 0 | U53: 0 | V53: 0 | W53: 0 | X53: 0 | Y53: 0 | Z53: 0 | AA53: 0 | AB53: 0 | AC53: 0 | AD53: 0 | AE53: 0 | AF53: 0 | AG53: 0 | AH53: 0 | AI53: 0 | AJ53: 0 | AK53: 0 | AL53: 0 | AM53: 0 | AN53: 0 | AO53: 0 | AP53: 0
A54: Fuel cell replacement | B54: 0 | C54: 0 | D54: 0 | E54: 0 | F54: 0 | G54: 0 | H54: 0 | I54: 0 | J54: 0 | K54: 0 | L54: 0 | M54: 0 | N54: 0 | O54: 0 | P54: 0 | Q54: 0 | R54: 0 | S54: 0 | T54: 0 | U54: 0 | V54: 0 | W54: 0 | X54: 0 | Y54: 0 | Z54: 0 | AA54: 0 | AB54: 0 | AC54: 0 | AD54: 0 | AE54: 0 | AF54: 0 | AG54: 0 | AH54: 0 | AI54: 0 | AJ54: 0 | AK54: 0 | AL54: 0 | AM54: 0 | AN54: 0 | AO54: 0 | AP54: 0
A55: Fuel cell fuel | B55: 0 | C55: 0 | D55: 0 | E55: 0 | F55: 0 | G55: 0 | H55: 0 | I55: 0 | J55: 0 | K55: 0 | L55: 0 | M55: 0 | N55: 0 | O55: 0 | P55: 0 | Q55: 0 | R55: 0 | S55: 0 | T55: 0 | U55: 0 | V55: 0 | W55: 0 | X55: 0 | Y55: 0 | Z55: 0 | AA55: 0 | AB55: 0 | AC55: 0 | AD55: 0 | AE55: 0 | AF55: 0 | AG55: 0 | AH55: 0 | AI55: 0 | AJ55: 0 | AK55: 0 | AL55: 0 | AM55: 0 | AN55: 0 | AO55: 0 | AP55: 0
A56: Fuel (CSP and generic only) | B56: {=Inputs!C210:AQ212} -> 0 | C56: 0 | D56: 0 | E56: 0 | F56: 0 | G56: 0 | H56: 0 | I56: 0 | J56: 0 | K56: 0 | L56: 0 | M56: 0 | N56: 0 | O56: 0 | P56: 0 | Q56: 0 | R56: 0 | S56: 0 | T56: 0 | U56: 0 | V56: 0 | W56: 0 | X56: 0 | Y56: 0 | Z56: 0 | AA56: 0 | AB56: 0 | AC56: 0 | AD56: 0 | AE56: 0 | AF56: 0 | AG56: 0 | AH56: 0 | AI56: 0 | AJ56: 0 | AK56: 0 | AL56: 0 | AM56: 0 | AN56: 0 | AO56: 0 | AP56: 0
A57: Biomass feedstock (Biopower only) | B57: 0 | C57: 0 | D57: 0 | E57: 0 | F57: 0 | G57: 0 | H57: 0 | I57: 0 | J57: 0 | K57: 0 | L57: 0 | M57: 0 | N57: 0 | O57: 0 | P57: 0 | Q57: 0 | R57: 0 | S57: 0 | T57: 0 | U57: 0 | V57: 0 | W57: 0 | X57: 0 | Y57: 0 | Z57: 0 | AA57: 0 | AB57: 0 | AC57: 0 | AD57: 0 | AE57: 0 | AF57: 0 | AG57: 0 | AH57: 0 | AI57: 0 | AJ57: 0 | AK57: 0 | AL57: 0 | AM57: 0 | AN57: 0 | AO57: 0 | AP57: 0
A58: Coal feedstock (Biopower only) | B58: 0 | C58: 0 | D58: 0 | E58: 0 | F58: 0 | G58: 0 | H58: 0 | I58: 0 | J58: 0 | K58: 0 | L58: 0 | M58: 0 | N58: 0 | O58: 0 | P58: 0 | Q58: 0 | R58: 0 | S58: 0 | T58: 0 | U58: 0 | V58: 0 | W58: 0 | X58: 0 | Y58: 0 | Z58: 0 | AA58: 0 | AB58: 0 | AC58: 0 | AD58: 0 | AE58: 0 | AF58: 0 | AG58: 0 | AH58: 0 | AI58: 0 | AJ58: 0 | AK58: 0 | AL58: 0 | AM58: 0 | AN58: 0 | AO58: 0 | AP58: 0
A59: Geothermal recapitalization | B59: {=Inputs!C214:AQ214} -> 0 | C59: 0 | D59: 0 | E59: 0 | F59: 0 | G59: 0 | H59: 0 | I59: 0 | J59: 0 | K59: 0 | L59: 0 | M59: 0 | N59: 0 | O59: 0 | P59: 0 | Q59: 0 | R59: 0 | S59: 0 | T59: 0 | U59: 0 | V59: 0 | W59: 0 | X59: 0 | Y59: 0 | Z59: 0 | AA59: 0 | AB59: 0 | AC59: 0 | AD59: 0 | AE59: 0 | AF59: 0 | AG59: 0 | AH59: 0 | AI59: 0 | AJ59: 0 | AK59: 0 | AL59: 0 | AM59: 0 | AN59: 0 | AO59: 0 | AP59: 0
A60: Land Lease | C60: =IF(C$2<=analysis_period,IF(om_land_lease="n/a",total_land_area*Inputs!D$225,total_land_area*om_land_lease*(1+inflation_rate/100+om_land_lease_escal/100)^B$2),0) -> 0 | D60: =IF(D$2<=analysis_period,IF(om_land_lease="n/a",total_land_area*Inputs!E$225,total_land_area*om_land_lease*(1+inflation_rate/100+om_land_lease_escal/100)^C$2),0) -> 0 | E60: =IF(E$2<=analysis_period,IF(om_land_lease="n/a",total_land_area*Inputs!F$225,total_land_area*om_land_lease*(1+inflation_rate/100+om_land_lease_escal/100)^D$2),0) -> 0 | F60: =IF(F$2<=analysis_period,IF(om_land_lease="n/a",total_land_area*Inputs!G$225,total_land_area*om_land_lease*(1+inflation_rate/100+om_land_lease_escal/100)^E$2),0) -> 0 | G60: =IF(G$2<=analysis_period,IF(om_land_lease="n/a",total_land_area*Inputs!H$225,total_land_area*om_land_lease*(1+inflation_rate/100+om_land_lease_escal/100)^F$2),0) -> 0 | H60: =IF(H$2<=analysis_period,IF(om_land_lease="n/a",total_land_area*Inputs!I$225,total_land_area*om_land_lease*(1+inflation_rate/100+om_land_lease_escal/100)^G$2),0) -> 0 | I60: =IF(I$2<=analysis_period,IF(om_land_lease="n/a",total_land_area*Inputs!J$225,total_land_area*om_land_lease*(1+inflation_rate/100+om_land_lease_escal/100)^H$2),0) -> 0 | J60: =IF(J$2<=analysis_period,IF(om_land_lease="n/a",total_land_area*Inputs!K$225,total_land_area*om_land_lease*(1+inflation_rate/100+om_land_lease_escal/100)^I$2),0) -> 0 | ... AP60: =IF(AP$2<=analysis_period,IF(om_land_lease="n/a",total_land_area*Inputs!AQ$225,total_land_area*om_land_lease*(1+inflation_rate/100+om_land_lease_escal/100)^AO$2),0) -> 0
A61: Property Tax | C61: =C31*property_tax_rate/100 -> 0 | D61: =D31*property_tax_rate/100 -> 0 | E61: =E31*property_tax_rate/100 -> 0 | F61: =F31*property_tax_rate/100 -> 0 | G61: =G31*property_tax_rate/100 -> 0 | H61: =H31*property_tax_rate/100 -> 0 | I61: =I31*property_tax_rate/100 -> 0 | J61: =J31*property_tax_rate/100 -> 0 | ... AP61: =AP31*property_tax_rate/100 -> 0
A62: Insurance | C62: =IF(C$2<=analysis_period,total_installed_cost*insurance_rate/100*(1+inflation_rate/100)^B$2,0) -> 0 | D62: =IF(D$2<=analysis_period,total_installed_cost*insurance_rate/100*(1+inflation_rate/100)^C$2,0) -> 0 | E62: =IF(E$2<=analysis_period,total_installed_cost*insurance_rate/100*(1+inflation_rate/100)^D$2,0) -> 0 | F62: =IF(F$2<=analysis_period,total_installed_cost*insurance_rate/100*(1+inflation_rate/100)^E$2,0) -> 0 | G62: =IF(G$2<=analysis_period,total_installed_cost*insurance_rate/100*(1+inflation_rate/100)^F$2,0) -> 0 | H62: =IF(H$2<=analysis_period,total_installed_cost*insurance_rate/100*(1+inflation_rate/100)^G$2,0) -> 0 | I62: =IF(I$2<=analysis_period,total_installed_cost*insurance_rate/100*(1+inflation_rate/100)^H$2,0) -> 0 | J62: =IF(J$2<=analysis_period,total_installed_cost*insurance_rate/100*(1+inflation_rate/100)^I$2,0) -> 0 | ... AP62: =IF(AP$2<=analysis_period,total_installed_cost*insurance_rate/100*(1+inflation_rate/100)^AO$2,0) -> 0
A63: Total Expenses | C63: =C$35+C$39+C$43+C$44++SUM(C$46:C$49)+SUM(C$51:C$62) -> 0 | D63: =D$35+D$39+D$43+D$44++SUM(D46:D49)+SUM(D51:D62) -> 0 | E63: =E$35+E$39+E$43+E$44++SUM(E46:E49)+SUM(E51:E62) -> 0 | F63: =F$35+F$39+F$43+F$44++SUM(F46:F49)+SUM(F51:F62) -> 0 | G63: =G$35+G$39+G$43+G$44++SUM(G46:G49)+SUM(G51:G62) -> 0 | H63: =H$35+H$39+H$43+H$44++SUM(H46:H49)+SUM(H51:H62) -> 0 | I63: =I$35+I$39+I$43+I$44++SUM(I46:I49)+SUM(I51:I62) -> 0 | J63: =J$35+J$39+J$43+J$44++SUM(J46:J49)+SUM(J51:J62) -> 0 | K63: =K$35+K$39+K$43+K$44++SUM(K46:K49)+SUM(K51:K62) -> 0 | ... AP63: =AP$35+AP$39+AP$43+AP$44++SUM(AP46:AP49)+SUM(AP51:AP62) -> 0
A65: EBITDA | C65: =C$29-C$63 -> 0 | D65: =D$29-D$63 -> 0 | E65: =E$29-E$63 -> 0 | F65: =F$29-F$63 -> 0 | G65: =G$29-G$63 -> 0 | H65: =H$29-H$63 -> 0 | I65: =I$29-I$63 -> 0 | J65: =J$29-J$63 -> 0 | ... AP65: =AP$29-AP$63 -> 0
A67: Cash Flow: Project
A68: Cash Flows from Operating Activities
A69: EBITDA | C69: =C65 -> 0 | D69: =D65 -> 0 | E69: =E65 -> 0 | F69: =F65 -> 0 | G69: =G65 -> 0 | H69: =H65 -> 0 | I69: =I65 -> 0 | J69: =J65 -> 0 | ... AP69: =AP65 -> 0
A70: Plus: PBI (if not included above)
A71: =A23 -> Federal | C71: =IF(pbi_fed_for_ds="Yes",0,C624) -> 0 | D71: =IF(pbi_fed_for_ds="Yes",0,D624) -> 0 | E71: =IF(pbi_fed_for_ds="Yes",0,E624) -> 0 | F71: =IF(pbi_fed_for_ds="Yes",0,F624) -> 0 | G71: =IF(pbi_fed_for_ds="Yes",0,G624) -> 0 | H71: =IF(pbi_fed_for_ds="Yes",0,H624) -> 0 | I71: =IF(pbi_fed_for_ds="Yes",0,I624) -> 0 | J71: =IF(pbi_fed_for_ds="Yes",0,J624) -> 0 | ... AP71: =IF(pbi_fed_for_ds="Yes",0,AP624) -> 0
A72: =A24 -> State | C72: =IF(pbi_sta_for_ds="Yes",0,C628) -> 0 | D72: =IF(pbi_sta_for_ds="Yes",0,D628) -> 0 | E72: =IF(pbi_sta_for_ds="Yes",0,E628) -> 0 | F72: =IF(pbi_sta_for_ds="Yes",0,F628) -> 0 | G72: =IF(pbi_sta_for_ds="Yes",0,G628) -> 0 | H72: =IF(pbi_sta_for_ds="Yes",0,H628) -> 0 | I72: =IF(pbi_sta_for_ds="Yes",0,I628) -> 0 | J72: =IF(pbi_sta_for_ds="Yes",0,J628) -> 0 | ... AP72: =IF(pbi_sta_for_ds="Yes",0,AP628) -> 0
A73: =A25 -> Utility | C73: =IF(pbi_uti_for_ds="Yes",0,C632) -> 0 | D73: =IF(pbi_uti_for_ds="Yes",0,D632) -> 0 | E73: =IF(pbi_uti_for_ds="Yes",0,E632) -> 0 | F73: =IF(pbi_uti_for_ds="Yes",0,F632) -> 0 | G73: =IF(pbi_uti_for_ds="Yes",0,G632) -> 0 | H73: =IF(pbi_uti_for_ds="Yes",0,H632) -> 0 | I73: =IF(pbi_uti_for_ds="Yes",0,I632) -> 0 | J73: =IF(pbi_uti_for_ds="Yes",0,J632) -> 0 | ... AP73: =IF(pbi_uti_for_ds="Yes",0,AP632) -> 0
A74: =A26 -> Other | C74: =IF(pbi_oth_for_ds="Yes",0,C636) -> 0 | D74: =IF(pbi_oth_for_ds="Yes",0,D636) -> 0 | E74: =IF(pbi_oth_for_ds="Yes",0,E636) -> 0 | F74: =IF(pbi_oth_for_ds="Yes",0,F636) -> 0 | G74: =IF(pbi_oth_for_ds="Yes",0,G636) -> 0 | H74: =IF(pbi_oth_for_ds="Yes",0,H636) -> 0 | I74: =IF(pbi_oth_for_ds="Yes",0,I636) -> 0 | J74: =IF(pbi_oth_for_ds="Yes",0,J636) -> 0 | ... AP74: =IF(pbi_oth_for_ds="Yes",0,AP636) -> 0
A75: Total | C75: =SUM(C71:C74) -> 0 | D75: =SUM(D71:D74) -> 0 | E75: =SUM(E71:E74) -> 0 | F75: =SUM(F71:F74) -> 0 | G75: =SUM(G71:G74) -> 0 | H75: =SUM(H71:H74) -> 0 | I75: =SUM(I71:I74) -> 0 | J75: =SUM(J71:J74) -> 0 | ... AP75: =SUM(AP71:AP74) -> 0
A76: Plus: Interest earned on reserve accounts | B76: 0 | C76: =C784 -> 0 | D76: =D784 -> 0 | E76: =E784 -> 0 | F76: =F784 -> 0 | G76: =G784 -> 0 | H76: =H784 -> 0 | I76: =I784 -> 0 | J76: =J784 -> 0 | ... AP76: =AP784 -> 0
A77: Less: Debt interest payment | B77: 0 | C77: =-C643 -> 0 | D77: =-D643 -> 0 | E77: =-E643 -> 0 | F77: =-F643 -> 0 | G77: =-G643 -> 0 | H77: =-H643 -> 0 | I77: =-I643 -> 0 | J77: =-J643 -> 0 | ... AP77: =-AP643 -> 0
A78: Total | B78: =B69+B75+B76+B77 -> 0 | C78: =C69+C75+C76+C77 -> 0 | D78: =D69+D75+D76+D77 -> 0 | E78: =E69+E75+E76+E77 -> 0 | F78: =F69+F75+F76+F77 -> 0 | G78: =G69+G75+G76+G77 -> 0 | H78: =H69+H75+H76+H77 -> 0 | I78: =I69+I75+I76+I77 -> 0 | ... AP78: =AP69+AP75+AP76+AP77 -> 0
A80: Cash Flows from Investing Activities
A81: Capital Costs
A82: Total installed cost | B82: =-total_installed_cost -> 0
A83: Equity closing cost | B83: =-cost_equity_closing -> 0
A84: Development fee | B84: =-Inputs!C85 -> 0
A85: Debt closing costs | B85: =IF(cost_debt_closing="N/A",0,-cost_debt_closing) -> 0
A86: Debt up-front fee | B86: =IF(cost_debt_fee="N/A",0,-CostDebtUpfront) -> 0
A87: Financing cost | B87: =-cost_other_financing -> 0
A88: Construction financing | B88: =-Inputs!I98 -> 0
A89: Total IBI | B89: =C605+C611 -> 0
A90: Total CBI | B90: =C618 -> 0
A91: Total purchase of property | B91: =SUM(B82:B90) -> 0
A92: Reserve Accounts (Increase)/Decrease
A93: Debt service reserve | B93: =-B670-B671 -> 0 | C93: =-C670-C671 -> 0 | D93: =-D670-D671 -> 0 | E93: =-E670-E671 -> 0 | F93: =-F670-F671 -> 0 | G93: =-G670-G671 -> 0 | H93: =-H670-H671 -> 0 | I93: =-I670-I671 -> 0 | ... AP93: =-AP670-AP671 -> 0
A94: Working capital reserve | B94: =-B676-B677 -> 0 | C94: =-C676-C677 -> 0 | D94: =-D676-D677 -> 0 | E94: =-E676-E677 -> 0 | F94: =-F676-F677 -> 0 | G94: =-G676-G677 -> 0 | H94: =-H676-H677 -> 0 | I94: =-I676-I677 -> 0 | ... AP94: =-AP676-AP677 -> 0
A95: Receivables reserve | B95: =-B682-B683 -> 0 | C95: =-C682-C683 -> 0 | D95: =-D682-D683 -> 0 | E95: =-E682-E683 -> 0 | F95: =-F682-F683 -> 0 | G95: =-G682-G683 -> 0 | H95: =-H682-H683 -> 0 | I95: =-I682-I683 -> 0 | ... AP95: =-AP682-AP683 -> 0
A96: Major equipment reserve 1 | B96: =-B688-B689 -> 0 | C96: =-C688-C689 -> 0 | D96: =-D688-D689 -> 0 | E96: =-E688-E689 -> 0 | F96: =-F688-F689 -> 0 | G96: =-G688-G689 -> 0 | H96: =-H688-H689 -> 0 | I96: =-I688-I689 -> 0 | ... AP96: =-AP688-AP689 -> 0
A97: Major equipment reserve 2 | B97: =-B720-B721 -> 0 | C97: =-C720-C721 -> 0 | D97: =-D720-D721 -> 0 | E97: =-E720-E721 -> 0 | F97: =-F720-F721 -> 0 | G97: =-G720-G721 -> 0 | H97: =-H720-H721 -> 0 | I97: =-I720-I721 -> 0 | ... AP97: =-AP720-AP721 -> 0
A98: Major equipment reserve 3 | B98: =-B752-B753 -> 0 | C98: =-C752-C753 -> 0 | D98: =-D752-D753 -> 0 | E98: =-E752-E753 -> 0 | F98: =-F752-F753 -> 0 | G98: =-G752-G753 -> 0 | H98: =-H752-H753 -> 0 | I98: =-I752-I753 -> 0 | ... AP98: =-AP752-AP753 -> 0
A99: Total | B99: =SUM(B93:B98) -> 0 | C99: =SUM(C93:C98) -> 0 | D99: =SUM(D93:D98) -> 0 | E99: =SUM(E93:E98) -> 0 | F99: =SUM(F93:F98) -> 0 | G99: =SUM(G93:G98) -> 0 | H99: =SUM(H93:H98) -> 0 | I99: =SUM(I93:I98) -> 0 | ... AP99: =SUM(AP93:AP98) -> 0
A100: Reserve Capital Spending
A101: Major equipment spending 1 | B101: =B689 -> 0 | C101: =C689 -> 0 | D101: =D689 -> 0 | E101: =E689 -> 0 | F101: =F689 -> 0 | G101: =G689 -> 0 | H101: =H689 -> 0 | I101: =I689 -> 0 | ... AP101: =AP689 -> 0
A102: Major equipment spending 2 | B102: =B721 -> 0 | C102: =C721 -> 0 | D102: =D721 -> 0 | E102: =E721 -> 0 | F102: =F721 -> 0 | G102: =G721 -> 0 | H102: =H721 -> 0 | I102: =I721 -> 0 | ... AP102: =AP721 -> 0
A103: Major equipment spending 3 | B103: =B753 -> 0 | C103: =C753 -> 0 | D103: =D753 -> 0 | E103: =E753 -> 0 | F103: =F753 -> 0 | G103: =G753 -> 0 | H103: =H753 -> 0 | I103: =I753 -> 0 | ... AP103: =AP753 -> 0
A104: Total | B104: =SUM(B101:B103) -> 0 | C104: =SUM(C101:C103) -> 0 | D104: =SUM(D101:D103) -> 0 | E104: =SUM(E101:E103) -> 0 | F104: =SUM(F101:F103) -> 0 | G104: =SUM(G101:G103) -> 0 | H104: =SUM(H101:H103) -> 0 | I104: =SUM(I101:I103) -> 0 | ... AP104: =SUM(AP101:AP103) -> 0
A105: Total | B105: =B91+B99+B104 -> 0 | C105: =C$99+C$104 -> 0 | D105: =D$99+D$104 -> 0 | E105: =E$99+E$104 -> 0 | F105: =F$99+F$104 -> 0 | G105: =G$99+G$104 -> 0 | H105: =H$99+H$104 -> 0 | I105: =I$99+I$104 -> 0 | J105: =J$99+J$104 -> 0 | ... AP105: =AP$99+AP$104 -> 0
A107: Cash Flows from Financing Activities
A108: Incentives and size of debt
...

Sheet Depreciation Schedules
A1: Depreciation Schedules (Half Year)
A2: Year | B2: 5-yr MACRS | C2: 15-yr MACRS | D2: 5-yr SL | E2: 15-yr SL | F2: 20-yr SL | G2: 39-yr SL
A3: 1 | B3: 20 | C3: 5 | D3: 10 | E3: 3.33 | F3: 2.5 | G3: =2.56410256410256*0.5 -> 1.2820513
A4: 2 | B4: 32 | C4: 9.5 | D4: 20 | E4: 6.67 | F4: 5 | G4: 2.5641026
A5: 3 | B5: 19.2 | C5: 8.55 | D5: 20 | E5: 6.67 | F5: 5 | G5: 2.5641026
A6: 4 | B6: 11.52 | C6: 7.7 | D6: 20 | E6: 6.67 | F6: 5 | G6: 2.5641026
A7: 5 | B7: 11.52 | C7: 6.93 | D7: 20 | E7: 6.67 | F7: 5 | G7: 2.5641026
A8: 6 | B8: 5.76 | C8: 6.23 | D8: 10 | E8: 6.67 | F8: 5 | G8: 2.5641026
A9: 7 | B9: 0 | C9: 5.9 | D9: 0 | E9: 6.67 | F9: 5 | G9: 2.5641026
A10: 8 | B10: 0 | C10: 5.9 | D10: 0 | E10: 6.67 | F10: 5 | G10: 2.5641026
A11: 9 | B11: 0 | C11: 5.91 | D11: 0 | E11: 6.67 | F11: 5 | G11: 2.5641026
A12: 10 | B12: 0 | C12: 5.9 | D12: 0 | E12: 6.67 | F12: 5 | G12: 2.5641026
A13: 11 | B13: 0 | C13: 5.91 | D13: 0 | E13: 6.67 | F13: 5 | G13: 2.5641026
A14: 12 | B14: 0 | C14: 5.9 | D14: 0 | E14: 6.66 | F14: 5 | G14: 2.5641026
A15: 13 | B15: 0 | C15: 5.91 | D15: 0 | E15: 6.67 | F15: 5 | G15: 2.5641026
... A41: 39 | B41: 0 | C41: 0 | D41: 0 | E41: 0 | F41: 0 | G41: 2.5641026
A42: 40 | B42: 0 | C42: 0 | D42: 0 | E42: 0 | F42: 0 | G42: =2.56410256410256*0.5 -> 1.2820513
A43: For additional information on depreciation schedules, see IRS publication 946.
A44: http://www.irs.gov/pub/irs-pdf/p946.pdf
A45: * Note custom schedule is defined on Inputs sheet around Row 180
